Workbook

Sheet DCF (2)
B1: Pepsico DCF Valuation
B2: (in USD million except per Share Data)
B3: Valuation Date | C3: 45138
B4: Latest Filing | C4: 45094
B5: Choose Discounting | C5: =IF(D5=A59,B59,B60) -> Year end discounting | D5: 2
C7: 6 | D7: 12 | E7: 12 | F7: 12 | G7: 12
B8: Date of cash flows | C8: Dec. 31, 2023 | D8: Dec. 31, 2024 | E8: Dec. 31, 2025 | F8: Dec. 31, 2026 | G8: Dec. 31, 2027
B10: EBIT | C10: ='PepsiCo-IS'!G22 -> 9563.1158 | D10: ='PepsiCo-IS'!I22 -> 15658.592 | E10: ='PepsiCo-IS'!J22 -> 16976.878 | F10: ='PepsiCo-IS'!K22 -> 18409.165 | G10: ='PepsiCo-IS'!L22 -> 19965.757
B11: Tax Rate | C11: ='PepsiCo-IS'!G59 -> 0.21645768 | D11: ='PepsiCo-IS'!I59 -> 0.21975928 | E11: ='PepsiCo-IS'!J59 -> 0.23566586 | F11: ='PepsiCo-IS'!K59 -> 0.25157243 | G11: ='PepsiCo-IS'!L59 -> 0.26747901
B12: NOPAT | C12: =C10*(1-C11) -> 7493.1059 | D12: =D10*(1-D11) -> 12217.471 | E12: =E10*(1-E11) -> 12976.007 | F12: =F10*(1-F11) -> 13777.926 | G12: =G10*(1-G11) -> 14625.336
B13: Add: Depreciation and amortisation | C13: ='Pepsico-CFS'!B8 -> 1655.908 | D13: ='Pepsico-CFS'!C8 -> 3580.5256 | E13: ='Pepsico-CFS'!D8 -> 3870.9446 | F13: ='Pepsico-CFS'!E8 -> 4187.0864 | G13: ='Pepsico-CFS'!F8 -> 4531.2419
B14: Add/Less: (Increase)/ Decrease in net working capital | C14: =SUM('Pepsico-CFS'!B11:B14) -> 4638.9017 | D14: =SUM('Pepsico-CFS'!C11:C14) -> 916.44749 | E14: =SUM('Pepsico-CFS'!D11:D14) -> 757.59314 | F14: =SUM('Pepsico-CFS'!E11:E14) -> 823.39412 | G14: =SUM('Pepsico-CFS'!F11:F14) -> 895.12621
B15: Less: Capital expenditure | C15: ='Pepsico-CFS'!B19 -> -6708.4559 | D15: ='Pepsico-CFS'!C19 -> -4224.2602 | E15: ='Pepsico-CFS'!D19 -> -6342.5553 | F15: ='Pepsico-CFS'!E19 -> -6882.0533 | G15: ='Pepsico-CFS'!F19 -> -7469.2155
B16: Debt free cash flow (Free Cash Flows to Firm) | C16: =C12+C13+C15+C14 -> 7079.4598 | D16: =D12+D13+D15+D14 -> 12490.184 | E16: =E12+E13+E15+E14 -> 11261.99 | F16: =F12+F13+F15+F14 -> 11906.354 | G16: =G12+G13+G15+G14 -> 12582.489
A17: =WACC!N8 -> 0.066785734 | B17: Discount rate (%) | C17: =C16*$A$17 -> 472.80692 | D17: =D16*$A$17 -> 834.16612 | E17: =E16*$A$17 -> 752.14025 | F17: =F16*$A$17 -> 795.17457 | G17: =G16*$A$17 -> 840.33076
B18: Discounting Period-Year End | C18: 0.5 | D18: =C18+1 -> 1.5 | E18: =D18+1 -> 2.5 | F18: =E18+1 -> 3.5 | G18: =F18+1 -> 4.5
B19: Discounting Period-Mid Year | C19: =0.25 -> 0.25 | D19: 1 | E19: =D19+1 -> 2 | F19: =E19+1 -> 3 | G19: =F19+1 -> 4
B20: Present value factor- Year end discounting | C20: =1/(1+$A$17)^C18 -> 0.9681918 | D20: =1/(1+$A$17)^D18 -> 0.9075785 | E20: =1/(1+$A$17)^E18 -> 0.85075988 | F20: =1/(1+$A$17)^F18 -> 0.79749837 | G20: =1/(1+$A$17)^G18 -> 0.74757127 | I20: this is done using the formula of fv, when wacc is given
B21: Present value factor- Mid year discounting | C21: =1/(1+$A$17)^C19 -> 0.98396738 | D21: =1/(1+$A$17)^D19 -> 0.93739536 | E21: =1/(1+$A$17)^E19 -> 0.87871007 | F21: =1/(1+$A$17)^F19 -> 0.82369874 | G21: =1/(1+$A$17)^G19 -> 0.77213138
B22: Present value debt free cash flow | C22: =CHOOSE($D$5,C21,C20)*C16 -> 6854.2749 | D22: =CHOOSE($D$5,D21,D20)*D16 -> 11335.823 | E22: =CHOOSE($D$5,E21,E20)*E16 -> 9581.249 | F22: =CHOOSE($D$5,F21,F20)*F16 -> 9495.2975 | G22: =CHOOSE($D$5,G21,G20)*G16 -> 9406.3071 | I22: =CHOOSE($D$5,C21,C20)*C16 -> 6854.2749 | J22: =CHOOSE($D$5,D21,D20)*D16 -> 11335.823 | K22: =CHOOSE($D$5,E21,E20)*E16 -> 9581.249 | L22: =CHOOSE($D$5,F21,F20)*F16 -> 9495.2975 | M22: =CHOOSE($D$5,G21,G20)*G16 -> 9406.3071 | N22: =CHOOSE($D$5,H21,H20)*H16 -> 0 | O22: =CHOOSE($D$5,I21,I20)*I16 -> #VALUE!
B24: Present value for explicit period | C24: =SUM(C22:G22) -> 46672.951
J25: WACC
B26: Terminal value | D26: Gordon growth | I26: =D38 -> 157.98255 | J26: 0.0575 | K26: =J26+0.25% -> 0.06 | L26: =K26+0.25% -> 0.0625 | M26: =L26+0.25% -> 0.065 | N26: =M26+0.25% -> 0.0675 | O26: =N26+0.25% -> 0.07 | P26: =O26+0.25% -> 0.0725 | Q26: =P26+0.25% -> 0.075 | R26: =Q26+0.25% -> 0.0775
B27: Long Term Growth Rate | D27: 0.02 | H27: LTGR | I27: 0.01 | J27: 160.90666 | K27: 151.62214 | L27: 143.22253 | M27: 135.58714 | N27: 128.61629 | O27: 122.22689 | P27: 116.34918 | Q27: 110.9241 | R27: 105.90135
B28: Terminal Value | D28: =G16*(1+D27)/(A17-D27) -> 274317.35 | F28: FCFF/WACC-g | I28: =I27+0.25% -> 0.0125 | J28: 169.69724 | K28: 159.46855 | L28: 150.26337 | M28: 141.93547 | N28: 134.36521 | O28: 127.45378 | P28: 121.11879 | Q28: 115.29109 | R28: 109.91212
B29: Present Value of TV | D29: =D28*CHOOSE(D5,G21,G20) -> 205071.77 | F29: multiplied by discounting factor | I29: =I28+0.25% -> 0.015 | J29: 179.522 | K29: 168.18678 | L29: 158.04535 | M29: 148.91863 | N29: 140.66166 | O29: 133.15583 | P29: 126.30315 | Q29: 120.02199 | R29: 114.24374
B30: DCF Value of Firm / Operating Business Enterprise Value | D30: =C24+D29 -> 251744.72 | I30: =I29+0.25% -> 0.0175 | J30: 190.57486 | K30: 177.93068 | L30: 166.69199 | M30: 156.63686 | N30: 147.58775 | O30: 139.40093 | P30: 131.95882 | Q30: 125.16427 | R30: 118.93634
B31: Add: Non Operating Assets | D31: ='PepsiCo-BS'!F6+'PepsiCo-BS'!F17 -> 3376 | I31: =I30+0.25% -> 0.02 | J31: 203.10144 | K31: 188.89257 | L31: 176.35588 | M31: 165.21267 | N31: 155.2429 | O31: 146.27055 | P31: 138.15312 | Q31: 130.77404 | R31: 124.03699
B32: Total Value of Firm | D32: =D30+D31 -> 255120.72 | I32: =I31+0.25% -> 0.0225 | J32: 217.41752 | K32: 201.31605 | L32: 187.22776 | M32: 174.7974 | N32: 163.74862 | O32: 153.86328 | P32: 144.96685 | Q32: 136.91807 | R32: 129.60133
B33: Less: Gross Debt & Debt Equivalents | D33: ='PepsiCo-BS'!F23+'PepsiCo-BS'!F28 -> 43621 | I33: =I32+0.25% -> 0.025 | J33: 233.93608 | K33: 215.5143 | L33: 199.54923 | M33: 185.58022 | N33: 173.25501 | O33: 162.29965 | P33: 152.49782 | Q33: 143.6765 | R33: 135.69561
B34: Add: Cash | D34: ='PepsiCo-BS'!F5 -> 6116 | I34: =I33+0.25% -> 0.0275 | J34: 253.20773 | K34: 231.89691 | L34: 213.6309 | M34: 197.80075 | N34: 183.94971 | O34: 171.72853 | P34: 160.86556 | Q34: 151.14635 | R34: 142.39932
B35: Less: Non Controling Interest | D35: ='PepsiCo-BS'!F39 -> 140 | I35: =I34+0.25% -> 0.03 | J35: 275.98333 | K35: 251.00995 | L35: 229.87899 | M35: 211.76707 | N35: 196.07036 | O35: 182.33602 | P35: 170.21774 | Q35: 159.44618 | R35: 149.80868
B36: DCF value of Common Equity | D36: =D32-D33+D34-D35 -> 217475.72
B37: No. of shares o/s | D37: =WACC!E38 -> 1376.5806
B38: DCF value per share | D38: =D36/D37 -> 157.98255
J39: WACC
B40: Terminal Value | D40: Exit Multiple Method | E40: from this we can find the values directly | I40: =D53 -> 188.00843 | J40: =J26 -> 0.0575 | K40: =K26 -> 0.06 | L40: =L26 -> 0.0625 | M40: =M26 -> 0.065 | N40: =N26 -> 0.0675 | O40: =O26 -> 0.07 | P40: =P26 -> 0.0725 | Q40: =Q26 -> 0.075 | R40: =R26 -> 0.0775
B41: LTM EV/EBITDA | D41: =(16.9+10.01)/2 -> 13.455 | E41: us industry based multiples+damodaran | H41: Exit Multiple | I41: 12.5 | J41: 182.74904 | K41: 180.70996 | L41: 178.69656 | M41: 176.70846 | N41: 174.74528 | O41: 172.80665 | P41: 170.8922 | Q41: 169.00158 | R41: 167.13442
B42: Terminal Year EBITDA | D42: =G10+G13 -> 24496.999 | E42: ebit+dep is ebidta | I42: =I41+1 -> 13.5 | J42: 196.58628 | K42: 194.40095 | L42: 192.24318 | M42: 190.11257 | N42: 188.00871 | O42: 185.9312 | P42: 183.87964 | Q42: 181.85365 | R42: 179.85285
B43: Terminal Value | D43: =D41*D42 -> 329607.12 | I43: =I42+1 -> 14.5 | J43: 210.42353 | K43: 208.09194 | L43: 205.7898 | M43: 203.51668 | N43: 201.27214 | O43: 199.05574 | P43: 196.86707 | Q43: 194.70572 | R43: 192.57128
B44: Present Value of TV | D44: =D43*CHOOSE($D$5,G21,G20) -> 246404.81 | I44: =I43+1 -> 15.5 | J44: 224.26077 | K44: 221.78293 | L44: 219.33642 | M44: 216.92079 | N44: 214.53556 | O44: 212.18028 | P44: 209.85451 | Q44: 207.55779 | R44: 205.28971
B45: DCF Value of Firm / Operating Business Enterprise Value | D45: =D44+C24 -> 293077.76 | I45: =I44+1 -> 16.5 | J45: 238.09801 | K45: 235.47392 | L45: 232.88305 | M45: 230.3249 | N45: 227.79899 | O45: 225.30483 | P45: 222.84194 | Q45: 220.40986 | R45: 218.00814
B46: Add: Non Operating Assets | D46: =D31 -> 3376 | I46: =I45+1 -> 17.5 | J46: 251.93525 | K46: 249.1649 | L46: 246.42967 | M46: 243.72901 | N46: 241.06242 | O46: 238.42937 | P46: 235.82938 | Q46: 233.26194 | R46: 230.72657
B47: Total Value of Firm | D47: =D45+D46 -> 296453.76 | I47: =I46+1 -> 18.5 | J47: 265.77249 | K47: 262.85589 | L47: 259.97629 | M47: 257.13312 | N47: 254.32584 | O47: 251.55392 | P47: 248.81681 | Q47: 246.11401 | R47: 243.445
B48: Less: Gross Debt & Debt Equivalents | D48: =D33 -> 43621 | I48: =I47+1 -> 19.5 | J48: 279.60974 | K48: 276.54688 | L48: 273.52291 | M48: 270.53723 | N48: 267.58927 | O48: 264.67846 | P48: 261.80425 | Q48: 258.96608 | R48: 256.16343
B49: Add: Cash | D49: =D34 -> 6116 | I49: =I48+1 -> 20.5 | J49: 293.44698 | K49: 290.23787 | L49: 287.06953 | M49: 283.94134 | N49: 280.8527 | O49: 277.80301 | P49: 274.79168 | Q49: 271.81815 | R49: 268.88185
B50: Less: Non Controling Interest | D50: =D35 -> 140
B51: DCF value of Common Equity | D51: =D47-D48+D49-D50 -> 258808.76
B52: No. of shares o/s-Diluted | D52: =D37 -> 1376.5806
B53: DCF value per share | D53: =D51/D52 -> 188.00843
A59: 1 | B59: Mid year discounting
A60: 2 | B60: Year end discounting

Sheet WACC
B1: PepsiCo WACC Calculation
B2: (in USD million except per Share Data)
C3: 1 | D3: =IF(C3=A24,B24,B25) -> Bottoms Up beta
B4: Cost of equity | F4: Cost of debt | J4: Weighted average cost of capital
B5: Particulars | C5: Notes | D5: Value | F5: Particulars | G5: Notes | H5: Value | J5: Particulars | K5: Weight | L5: Particulars | M5: Cost | N5: Value
B6: Risk-free rate (%) | C6: 10-year treasury rate | D6: 0.0397 | F6: Debt borrowing rate (%) | G6: Ratings Based | H6: =D6+0.7% -> 0.0467 | J6: Debt (%) | K6: =D25 -> 0.15108108 | L6: Cost of debt (%) | M6: =H8 -> 0.034091 | N6: =M6*K6 -> 0.0051505052 | S6: S&P 500
B7: Beta | C7: =D3 -> Bottoms Up beta | D7: =CHOOSE(C3,H22,H25) -> 0.73120838 | F7: Expected income tax rate (%) | H7: 0.27 | J7: Equity (%) | K7: =1-K6 -> 0.84891892 | L7: Cost of equity (%) | M7: =D9 -> 0.072604377 | N7: =M7*K7 -> 0.061635229
B8: Equity market risk premium (%) | C8: Damodaram ERP | D8: =4.5% -> 0.045 | F8: After-tax cost of debt (%) | H8: =H6*(1-H7) -> 0.034091 | J8: WACC | N8: =SUM(N6:N7) -> 0.066785734 | S8: Initial date | U8: 57.57 | V8: 22284
B9: Cost of equity capital (%) | D9: =D6+D7*D8 -> 0.072604377 | S9: End date | U9: 7431.6 | V9: 46188
C11: from erp predictive model- damodaram site | S11: time | V11: =YEARFRAC(V8,V9,1) -> 65.446943
S12: CAGR | V12: =RATE(V11,0,-U8,U9,0) -> 0.077093475
B13: Calculation of beta
B14: Particulars | C14: Levered beta | D14: D/(D+E) (last three years) | E14: E/(D+E) (last three years) | F14: Tax rate (%) | G14: Unlevered beta | H14: Relevered beta | S14: ERP | V14: =V12-D6 -> 0.037393475
B15: Bottom-up
B16: =[1]Beta!D6 -> Coca Cola | C16: =Beta!E6 -> 0.81092836 | D16: =AVERAGE(C33:C35)/(AVERAGE(C33:C35)+AVERAGE(F33:F35)) -> 0.13729357 | E16: =1-D16 -> 0.86270643 | F16: 0.27 | G16: =(C16*E16)/(E16+D16*(1-F16)) -> 0.72652485 | H16: =G16*(1+$D$25/$E$25*(1-F16)) -> 0.82091294
B17: =[1]Beta!D7 -> Keurig Dr. Pepper | C17: =Beta!E7 -> 0.51960989 | D17: =AVERAGE($C$43:$C$45)/(AVERAGE($C$43:$C$45)+AVERAGE($F$43:$F$45)) -> 0.19730473 | E17: =1-D17 -> 0.80269527 | F17: 0.27 | G17: =(C17*E17)/(E17+D17*(1-F17)) -> 0.44055793 | H17: =G17*(1+$D$25/$E$25*(1-F17)) -> 0.49779399
B18: =[1]Beta!D8 -> Monster Beverages | C18: =Beta!E8 -> 0.84032716 | D18: =AVERAGE(C48:C50)/(AVERAGE(C48:C50)+AVERAGE(F48:F50)) -> 0 | E18: =1-D18 -> 1 | F18: 0.27 | G18: =(C18*E18)/(E18+D18*(1-F18)) -> 0.84032716 | H18: =G18*(1+$D$25/$E$25*(1-F18)) -> 0.94950014
B19: =[1]Beta!D12 -> Mondelez | C19: =Beta!E12 -> 0.6570591 | D19: =AVERAGE($C$53:$C$55)/(AVERAGE($C$53:$C$55)+AVERAGE($F$53:$F$55)) -> 0.17729387 | E19: =1-D19 -> 0.82270613 | F19: 0.27 | G19: =(C19*E19)/(E19+D19*(1-F19)) -> 0.56774409 | H19: =G19*(1+$D$25/$E$25*(1-F19)) -> 0.64150382
B20: =[1]Beta!D13 -> Hershey Co. | C20: =Beta!E13 -> 0.58104066 | D20: =AVERAGE($C$58:$C$60)/(AVERAGE($C$58:$C$60)+AVERAGE($F$58:$F$60)) -> 0.13189005 | E20: =1-D20 -> 0.86810995 | F20: 0.27 | G20: =(C20*E20)/(E20+D20*(1-F20)) -> 0.52303253 | H20: =G20*(1+$D$25/$E$25*(1-F20)) -> 0.59098347
B21: =[1]Beta!D15 -> Constellation Brands | C21: =Beta!E15 -> 1.1962912 | D21: =AVERAGE($C$63:$C$65)/(AVERAGE($C$63:$C$65)+AVERAGE($F$63:$F$65)) -> 0.21075915 | E21: =1-D21 -> 0.78924085 | F21: 0.27 | G21: =(C21*E21)/(E21+D21*(1-F21)) -> 1.0011312 | H21: =G21*(1+$D$25/$E$25*(1-F21)) -> 1.1311954
D22: =MEDIAN(D16:D21) -> 0.15729372 | E22: =MEDIAN(E16:E21) -> 0.84270628 | H22: =MEDIAN(H16:H21) -> 0.73120838 | I22: this is bottoms up beta
B23: Beta Calculation for Target Co
A24: 1 | B24: Bottoms Up beta
A25: 2 | B25: Regression beta | C25: =Beta!E5 -> 0.67732435 | D25: =AVERAGE(C38:C40)/(AVERAGE(C38:C40)+AVERAGE(F38:F40)) -> 0.15108108 | E25: =1-D25 -> 0.84891892 | F25: =F21 -> 0.27 | G25: =(C25*E25)/(E25+D25*(1-F25)) -> 0.59944599 | H25: =G25*(1+$D$25/$E$25*(1-F25)) -> 0.67732435
B30: Calculation of Capital Structure of Peer Group Companies
C31: Debt | D31: Equity
B32: Coca Cola | D32: Share Price | E32: Shares O/S | F32: M.Cap | G32: Tax Rate
B33: 45134 | C33: =4828+35626+1171 -> 41625 | D33: 62.44 | E33: =4324344812/10^6 -> 4324.3448 | F33: =E33*D33 -> 270012.09 | G33: 0.27
B34: 44769 | C34: =4358+788+36755 -> 41901 | D34: 63.01 | E34: =4324629174/10^6 -> 4324.6292 | F34: =E34*D34 -> 272494.88 | G34: 0.27
B35: 44403 | C35: =1867+337+39804 -> 42008 | D35: 57.06 | E35: =4316618703/10^6 -> 4316.6187 | F35: =E35*D35 -> 246306.26 | G35: 0.27
B37: Pepsico
B38: 45120 | C38: =7613+36008 -> 43621 | D38: 187.53 | E38: =1376580611/10^6 -> 1376.5806 | F38: =E38*D38 -> 258150.16 | G38: 0.27
B39: 44754 | C39: =6032+33247 -> 39279 | D39: 169.5 | E39: =1380084844/10^6 -> 1380.0848 | F39: =E39*D39 -> 233924.38 | G39: 0.27
B40: 44390 | C40: =4264+38034 -> 42298 | D40: 152.96 | E40: =1382114956/10^6 -> 1382.115 | F40: =E40*D40 -> 211408.3 | G40: 0.27
B42: Keurig Dr. Pepper
B43: 45134 | C43: =2635+9934 -> 12569 | D43: 33.76 | E43: =1397259384/10^6 -> 1397.2594 | F43: =E43*D43 -> 47171.477 | G43: 0.27
B44: 44770 | C44: =0+11555 -> 11555 | D44: 38.5 | E44: =1416070252/10^6 -> 1416.0703 | F44: =E44*D44 -> 54518.705 | G44: 0.27
B45: 44406 | C45: =1328+11721 -> 13049 | D45: 34.95 | E45: =1417476953/10^6 -> 1417.477 | F45: =E45*D45 -> 49540.82 | G45: 0.27
B47: Monster Beverages
B48: 45051 | C48: 0 | D48: 59.71 | E48: =1046711932/10^6 -> 1046.7119 | F48: =E48*D48 -> 62499.169 | G48: 0.27
B49: 44687 | C49: 0 | D49: 43.33 | E49: =529671407/10^6 -> 529.67141 | F49: =E49*D49 -> 22950.662 | G49: 0.27
B50: 44323 | C50: 0 | D50: 45.63 | E50: =528562217/10^6 -> 528.56222 | F50: =E50*D50 -> 24118.294 | G50: 0.27
B52: Mondelez
B53: 45134 | C53: =2178+901+18147 -> 21226 | D53: 72.36 | E53: =1360417919/10^6 -> 1360.4179 | F53: =E53*D53 -> 98439.841 | G53: 0.27
B54: 44768 | C54: =605+746+17861 -> 19212 | D54: 62.94 | E54: =1370566113/10^6 -> 1370.5661 | F54: =E54*D54 -> 86263.431 | G54: 0.27
B55: 44404 | C55: =64+1905+17046 -> 19015 | D55: 65.23 | E55: =1397817443/10^6 -> 1397.8174 | F55: =E55*D55 -> 91179.632 | G55: 0.27
B57: Hershey Co.
B58: 45134 | C58: =860+8+4086 -> 4954 | D58: 233.56 | E58: =(149854381)/10^6 -> 149.85438 | F58: =D58*E58 -> 34999.989 | G58: 0.27
B59: 44770 | C59: =915+752+3340 -> 5007 | D59: 224.27 | E59: =+(146869652)/10^6 -> 146.86965 | F59: =D59*E59 -> 32938.457 | G59: 0.27
B60: 44406 | C60: =207+3+4095 -> 4305 | D60: 178.52 | E60: =+(145425767)/10^6 -> 145.42577 | F60: =D60*E60 -> 25961.408 | G60: 0.27
B62: Constellation Brands
B63: 45107 | C63: =819+558+10980 -> 12357 | D63: 272.8 | E63: =183300716/10^6 -> 183.30072 | F63: =D63*E63 -> 50004.435 | G63: 0.27
B64: 44742 | C64: =124+575+10278 -> 10977 | D64: 233.06 | E64: =159330225/10^6 -> 159.33023 | F64: =D64*E64 -> 37133.502 | G64: 0.27
B65: 44377 | C65: =529+9915 -> 10444 | D65: 233.89 | E65: =168251351/10^6 -> 168.25135 | F65: =D65*E65 -> 39352.308 | G65: 0.27

Sheet Beta
C1: BETA CALCULATION
K3: we don’t calculate beta on absolute numbers as the change will nor be apppropriate
D4: Competitors | E4: Beta | F4: Market Cap | G4: R sq
D5: Pepsico | E5: =SLOPE($E$21:$E$258,$BA$21:$BA$258) -> 0.67732435 | F5: 249 | G5: =RSQ($E$21:$E$258,$BA$21:$BA$258) -> 0.4523775
D6: Coca Cola | E6: =SLOPE($I$21:$I$258,$BA$21:$BA$258) -> 0.81092836 | F6: 261 | G6: =RSQ($I$21:$I$258,$BA$21:$BA$258) -> 0.49260567 | K6: regression eq- | L6: Y= a+bX
D7: Keurig Dr. Pepper | E7: =SLOPE($M$21:$M$258,$BA$21:$BA$258) -> 0.51960989 | F7: 47 | G7: =RSQ($M$21:$M$258,$BA$21:$BA$258) -> 0.26749515 | L7: Y is dependent, X is independent
D8: Monster Beverages | E8: =SLOPE($Q$21:$Q$258,$BA$21:$BA$258) -> 0.84032716 | F8: 60.9 | G8: =RSQ($Q$21:$Q$258,$BA$21:$BA$258) -> 0.4165087 | L8: a, b are constants
D9: Hormel Foods | E9: =SLOPE($U$21:$U$258,$BA$21:$BA$258) -> 0.19151187 | F9: 21.665 | G9: =RSQ($U$21:$U$258,$BA$21:$BA$258) -> 0.036866699 | L9: stock- dependent
D10: Kellogg Company | E10: =SLOPE($Y$21:$Y$258,$BA$21:$BA$258) -> 0.38387877 | F10: 21.126 | G10: =RSQ($Y$21:$Y$258,$BA$21:$BA$258) -> 0.13573576 | L10: market- independent
D11: Kraft Heinz Co. | E11: =SLOPE($AC$21:$AC$258,$BA$21:$BA$258) -> 0.57392097 | F11: 41.357 | G11: =RSQ($AC$21:$AC$258,$BA$21:$BA$258) -> 0.15064376
D12: Mondelez | E12: =SLOPE($AG$21:$AG$258,$BA$21:$BA$258) -> 0.6570591 | F12: 97.365 | G12: =RSQ($AG$21:$AG$258,$BA$21:$BA$258) -> 0.41399993 | J12: pepsico- regression beta
D13: Hershey Co. | E13: =SLOPE($AK$21:$AK$258,$BA$21:$BA$258) -> 0.58104066 | F13: 44.433 | G13: =RSQ($AK$21:$AK$258,$BA$21:$BA$258) -> 0.27795919 | J13: rest companies- bottoms up beta | O13: rsq- systematic risk
D14: Campbell Soup | E14: =SLOPE($AO$21:$AO$258,$BA$21:$BA$258) -> 0.23143192 | F14: 12.508 | G14: =RSQ($AO$21:$AO$258,$BA$21:$BA$258) -> 0.036177526 | J14: beta relevant- rsq=25 above
D15: Constellation Brands | E15: =SLOPE($AS$21:$AS$258,$BA$21:$BA$258) -> 1.1962912 | F15: 47.816 | G15: =RSQ($AS$21:$AS$258,$BA$21:$BA$258) -> 0.52522879
D16: General Mills | E16: =SLOPE($AW$21:$AW$258,$BA$21:$BA$258) -> 0.20453619 | F16: 39.683 | G16: =RSQ($AW$21:$AW$258,$BA$21:$BA$258) -> 0.040573428
D17: Source : marketscreener.com
D18: marketscreener.com
C19: Pepsico | G19: Coca-Cola | K19: Keurig Dr. Pepper | O19: Monster Beverage Corporation | S19: Hormel Foods Corporation (HFL) | W19: Kellogg Company | AA19: Kraft Heinz Co (KHC) | AE19: Mondelez (MDLZ) | AI19: Hershey Co. | AM19: Campbell Soup (CPB) | AQ19: Constellation Brands (STZ) | AU19: General Mills Inc (GIS) | AY19: S&P 500
C20: Date | D20: Adj Close | E20: % Change | G20: Date | H20: Adj Close | I20: % Change | K20: Date | L20: Adj Close | M20: % Change | O20: Date | P20: Adj Close | Q20: % Change | S20: Date | T20: Adj Close | U20: % Change | W20: Date | X20: Adj Close | Y20: % Change | AA20: Date | AB20: Adj Close | AC20: % Change | AE20: Date | AF20: Adj Close | AG20: % Change | AI20: Date | AJ20: Adj Close | AK20: % Change | AM20: Date | AN20: Adj Close | AO20: % Change | AQ20: Date | AR20: Adj Close | AS20: % Change | AU20: Date | AV20: Adj Close | AW20: % Change | AY20: Date | AZ20: Adj Close | BA20: % Change
C21: 07/30/2023 | D21: 184.6 | E21: =D21/D22-1 -> -0.030003678 | G21: 07/30/2023 | H21: 60.71 | I21: =H21/H22-1 -> -0.028329065 | K21: 07/30/2023 | L21: 33.6 | M21: =L21/L22-1 -> -0.0094339623 | O21: 07/30/2023 | P21: 55.11 | Q21: =P21/P22-1 -> -0.05227859 | S21: 07/30/2023 | T21: 40.54 | U21: =T21/T22-1 -> -0.012183236 | W21: 07/30/2023 | X21: 64.8 | Y21: =X21/X22-1 -> -0.041136431 | AA21: 07/30/2023 | AB21: 35.28 | AC21: =AB21/AB22-1 -> -0.024336283 | AE21: 07/30/2023 | AF21: 73.92 | AG21: =AF21/AF22-1 -> -0.014925373 | AI21: 07/30/2023 | AJ21: 228.23 | AK21: =AJ21/AJ22-1 -> -0.031446274 | AM21: 07/30/2023 | AN21: 45.15 | AO21: =AN21/AN22-1 -> -0.023783784 | AQ21: 07/30/2023 | AR21: 268.02 | AS21: =AR21/AR22-1 -> -0.016440367 | AU21: 07/30/2023 | AV21: 73.59 | AW21: =AV21/AV22-1 -> -0.024652087 | AY21: 07/30/2023 | AZ21: 4478.03 | BA21: =AZ21/AZ22-1 -> -0.02274002
C22: 07/23/2023 | D22: 190.31 | E22: =D22/D23-1 -> 0.00078880942 | G22: 07/23/2023 | H22: 62.48 | I22: =H22/H23-1 -> 0.00064061499 | K22: 07/23/2023 | L22: 33.92 | M22: =L22/L23-1 -> 0.041129527 | O22: 07/23/2023 | P22: 58.15 | Q22: =P22/P23-1 -> 0.0008605852 | S22: 07/23/2023 | T22: 41.04 | U22: =T22/T23-1 -> 0.022421525 | W22: 07/23/2023 | X22: 67.58 | Y22: =X22/X23-1 -> -0.0029507229 | AA22: 07/23/2023 | AB22: 36.16 | AC22: =AB22/AB23-1 -> -0.0044052863 | AE22: 07/23/2023 | AF22: 75.04 | AG22: =AF22/AF23-1 -> 0.014328197 | AI22: 07/23/2023 | AJ22: 235.64 | AK22: =AJ22/AJ23-1 -> -0.044599416 | AM22: 07/23/2023 | AN22: 46.25 | AO22: =AN22/AN23-1 -> -0.0017267429 | AQ22: 07/23/2023 | AR22: 272.5 | AS22: =AR22/AR23-1 -> 0.011131725 | AU22: 07/23/2023 | AV22: 75.45 | AW22: =AV22/AV23-1 -> -0.02012987 | AY22: 07/23/2023 | AZ22: 4582.23 | BA22: =AZ22/AZ23-1 -> 0.010116085
C23: 07/16/2023 | D23: 190.16 | E23: =D23/D24-1 -> 0.010360767 | G23: 07/16/2023 | H23: 62.44 | I23: =H23/H24-1 -> 0.025287356 | K23: 07/16/2023 | L23: 32.58 | M23: =L23/L24-1 -> 0.029058749 | O23: 07/16/2023 | P23: 58.1 | Q23: =P23/P24-1 -> 0.01378468 | S23: 07/16/2023 | T23: 40.14 | U23: =T23/T24-1 -> 0.00024919013 | W23: 07/16/2023 | X23: 67.78 | Y23: =X23/X24-1 -> 0.0032563647 | AA23: 07/16/2023 | AB23: 36.32 | AC23: =AB23/AB24-1 -> 0.013110181 | AE23: 07/16/2023 | AF23: 73.98 | AG23: =AF23/AF24-1 -> 0.023519646 | AI23: 07/16/2023 | AJ23: 246.64 | AK23: =AJ23/AJ24-1 -> 0.032528153 | AM23: 07/16/2023 | AN23: 46.33 | AO23: =AN23/AN24-1 -> 0.020709407 | AQ23: 07/16/2023 | AR23: 269.5 | AS23: =AR23/AR24-1 -> 0.054918386 | AU23: 07/16/2023 | AV23: 77 | AW23: =AV23/AV24-1 -> 0.026529796 | AY23: 07/16/2023 | AZ23: 4536.34 | BA23: =AZ23/AZ24-1 -> 0.0068628452
C24: 45176 | D24: 188.21 | E24: =D24/D25-1 -> 0.028020537 | G24: 45176 | H24: 60.9 | I24: =H24/H25-1 -> 0.019076305 | K24: 45176 | L24: 31.66 | M24: =L24/L25-1 -> -0.0031486146 | O24: 45176 | P24: 57.31 | Q24: =P24/P25-1 -> 0.025774118 | S24: 45176 | T24: 40.13 | U24: =T24/T25-1 -> 0.019822109 | W24: 45176 | X24: 67.56 | Y24: =X24/X25-1 -> 0.0055067718 | AA24: 45176 | AB24: 35.85 | AC24: =AB24/AB25-1 -> 0.010998308 | AE24: 45176 | AF24: 72.28 | AG24: =AF24/AF25-1 -> 0.0038888889 | AI24: 45176 | AJ24: 238.87 | AK24: =AJ24/AJ25-1 -> -0.016914972 | AM24: 45176 | AN24: 45.39 | AO24: =AN24/AN25-1 -> -0.0032938076 | AQ24: 45176 | AR24: 255.47 | AS24: =AR24/AR25-1 -> 0.007810959 | AU24: 45176 | AV24: 75.01 | AW24: =AV24/AV25-1 -> -0.0021285087 | AY24: 45176 | AZ24: 4505.42 | BA24: =AZ24/AZ25-1 -> 0.024203503
C25: 44964 | D25: 183.08 | E25: =D25/D26-1 -> -0.011553828 | G25: 44964 | H25: 59.76 | I25: =H25/H26-1 -> -0.0076386583 | K25: 44964 | L25: 31.76 | M25: =L25/L26-1 -> 0.015669971 | O25: 44964 | P25: 55.87 | Q25: =P25/P26-1 -> -0.027332869 | S25: 44964 | T25: 39.35 | U25: =T25/T26-1 -> -0.021631029 | W25: 44964 | X25: 67.19 | Y25: =X25/X26-1 -> -0.003115727 | AA25: 44964 | AB25: 35.46 | AC25: =AB25/AB26-1 -> -0.0011267606 | AE25: 44964 | AF25: 72 | AG25: =AF25/AF26-1 -> -0.012887305 | AI25: 44964 | AJ25: 242.98 | AK25: =AJ25/AJ26-1 -> -0.026912295 | AM25: 44964 | AN25: 45.54 | AO25: =AN25/AN26-1 -> -0.0037190987 | AQ25: 44964 | AR25: 253.49 | AS25: =AR25/AR26-1 -> 0.029902897 | AU25: 44964 | AV25: 75.17 | AW25: =AV25/AV26-1 -> -0.019947849 | AY25: 44964 | AZ25: 4398.95 | BA25: =AZ25/AZ26-1 -> -0.011556317
C26: 06/25/2023 | D26: 185.22 | E26: =D26/D27-1 -> -0.0045681733 | G26: 06/25/2023 | H26: 60.22 | I26: =H26/H27-1 -> -0.016013072 | K26: 06/25/2023 | L26: 31.27 | M26: =L26/L27-1 -> 0.0028864657 | O26: 06/25/2023 | P26: 57.44 | Q26: =P26/P27-1 -> -0.028252411 | S26: 06/25/2023 | T26: 40.22 | U26: =T26/T27-1 -> -0.0061774154 | W26: 06/25/2023 | X26: 67.4 | Y26: =X26/X27-1 -> 0.034376918 | AA26: 06/25/2023 | AB26: 35.5 | AC26: =AB26/AB27-1 -> -0.011417432 | AE26: 06/25/2023 | AF26: 72.94 | AG26: =AF26/AF27-1 -> -0.0021887825 | AI26: 06/25/2023 | AJ26: 249.7 | AK26: =AJ26/AJ27-1 -> -0.036242232 | AM26: 06/25/2023 | AN26: 45.71 | AO26: =AN26/AN27-1 -> 0.0026321562 | AQ26: 06/25/2023 | AR26: 246.13 | AS26: =AR26/AR27-1 -> 0.015471574 | AU26: 06/25/2023 | AV26: 76.7 | AW26: =AV26/AV27-1 -> -0.056812592 | AY26: 06/25/2023 | AZ26: 4450.38 | BA26: =AZ26/AZ27-1 -> 0.02346878
C27: 06/18/2023 | D27: 186.07 | E27: =D27/D28-1 -> 0.00016125564 | G27: 06/18/2023 | H27: 61.2 | I27: =H27/H28-1 -> -0.0076212097 | K27: 06/18/2023 | L27: 31.18 | M27: =L27/L28-1 -> -0.030774013 | O27: 06/18/2023 | P27: 59.11 | Q27: =P27/P28-1 -> 0.011291702 | S27: 06/18/2023 | T27: 40.47 | U27: =T27/T28-1 -> -0.019384541 | W27: 06/18/2023 | X27: 65.16 | Y27: =X27/X28-1 -> -0.017046312 | AA27: 06/18/2023 | AB27: 35.91 | AC27: =AB27/AB28-1 -> -0.02919708 | AE27: 06/18/2023 | AF27: 73.1 | AG27: =AF27/AF28-1 -> -0.0063884736 | AI27: 06/18/2023 | AJ27: 259.09 | AK27: =AJ27/AJ28-1 -> -0.0062519178 | AM27: 06/18/2023 | AN27: 45.59 | AO27: =AN27/AN28-1 -> -0.017880224 | AQ27: 06/18/2023 | AR27: 242.38 | AS27: =AR27/AR28-1 -> -0.014835589 | AU27: 06/18/2023 | AV27: 81.32 | AW27: =AV27/AV28-1 -> 0.0075579234 | AY27: 06/18/2023 | AZ27: 4348.33 | BA27: =AZ27/AZ28-1 -> -0.013892448
C28: 45236 | D28: 186.04 | E28: =D28/D29-1 -> 0.02023581 | G28: 45236 | H28: 61.67 | I28: =H28/H29-1 -> 0.019844551 | K28: 45236 | L28: 32.17 | M28: =L28/L29-1 -> 0.027467263 | O28: 45236 | P28: 58.45 | Q28: =P28/P29-1 -> 0.020960699 | S28: 45236 | T28: 41.27 | U28: =T28/T29-1 -> 0.0097871299 | W28: 45236 | X28: 66.29 | Y28: =X28/X29-1 -> -0.012954139 | AA28: 45236 | AB28: 36.99 | AC28: =AB28/AB29-1 -> 0.0029826464 | AE28: 45236 | AF28: 73.57 | AG28: =AF28/AF29-1 -> 0.0082225572 | AI28: 45236 | AJ28: 260.72 | AK28: =AJ28/AJ29-1 -> 0.019154093 | AM28: 45236 | AN28: 46.42 | AO28: =AN28/AN29-1 -> 0.0080347448 | AQ28: 45236 | AR28: 246.03 | AS28: =AR28/AR29-1 -> 0.018293945 | AU28: 45236 | AV28: 80.71 | AW28: =AV28/AV29-1 -> -0.019319563 | AY28: 45236 | AZ28: 4409.59 | BA28: =AZ28/AZ29-1 -> 0.025757992
C29: 45022 | D29: 182.35 | E29: =D29/D30-1 -> -0.0092904488 | G29: 45022 | H29: 60.47 | I29: =H29/H30-1 -> -0.011281884 | K29: 45022 | L29: 31.31 | M29: =L29/L30-1 -> -0.0044515103 | O29: 45022 | P29: 57.25 | Q29: =P29/P30-1 -> -0.037491594 | S29: 45022 | T29: 40.87 | U29: =T29/T30-1 -> 0.0024527839 | W29: 45022 | X29: 67.16 | Y29: =X29/X30-1 -> -0.0034129693 | AA29: 45022 | AB29: 36.88 | AC29: =AB29/AB30-1 -> -0.042326668 | AE29: 45022 | AF29: 72.97 | AG29: =AF29/AF30-1 -> -0.017503703 | AI29: 45022 | AJ29: 255.82 | AK29: =AJ29/AJ30-1 -> -0.019508643 | AM29: 45022 | AN29: 46.05 | AO29: =AN29/AN30-1 -> -0.10530406 | AQ29: 45022 | AR29: 241.61 | AS29: =AR29/AR30-1 -> -0.015524407 | AU29: 45022 | AV29: 82.3 | AW29: =AV29/AV30-1 -> -0.027071758 | AY29: 45022 | AZ29: 4298.86 | BA29: =AZ29/AZ30-1 -> 0.0038506715
C30: 05/28/2023 | D30: 184.06 | E30: =D30/D31-1 -> 0.0026146639 | G30: 05/28/2023 | H30: 61.16 | I30: =H30/H31-1 -> 0.01493528 | K30: 05/28/2023 | L30: 31.45 | M30: =L30/L31-1 -> 0.0012734798 | O30: 05/28/2023 | P30: 59.48 | Q30: =P30/P31-1 -> 0.032459642 | S30: 05/28/2023 | T30: 40.77 | U30: =T30/T31-1 -> 0.059786847 | W30: 05/28/2023 | X30: 67.39 | Y30: =X30/X31-1 -> -0.0041377272 | AA30: 05/28/2023 | AB30: 38.51 | AC30: =AB30/AB31-1 -> 0.0044340115 | AE30: 05/28/2023 | AF30: 74.27 | AG30: =AF30/AF31-1 -> -0.011446826 | AI30: 05/28/2023 | AJ30: 260.91 | AK30: =AJ30/AJ31-1 -> 0.012377774 | AM30: 05/28/2023 | AN30: 51.47 | AO30: =AN30/AN31-1 -> -0.00077654824 | AQ30: 05/28/2023 | AR30: 245.42 | AS30: =AR30/AR31-1 -> 0.053847475 | AU30: 05/28/2023 | AV30: 84.59 | AW30: =AV30/AV31-1 -> 0.0048705156 | AY30: 05/28/2023 | AZ30: 4282.37 | BA30: =AZ30/AZ31-1 -> 0.018290552
C31: 05/21/2023 | D31: 183.58 | E31: =D31/D32-1 -> -0.043056714 | G31: 05/21/2023 | H31: 60.26 | I31: =H31/H32-1 -> -0.040904027 | K31: 05/21/2023 | L31: 31.41 | M31: =L31/L32-1 -> -0.013195099 | O31: 05/21/2023 | P31: 57.61 | Q31: =P31/P32-1 -> -0.034684987 | S31: 05/21/2023 | T31: 38.47 | U31: =T31/T32-1 -> -0.022114896 | W31: 05/21/2023 | X31: 67.67 | Y31: =X31/X32-1 -> -0.023943459 | AA31: 05/21/2023 | AB31: 38.34 | AC31: =AB31/AB32-1 -> -0.018684413 | AE31: 05/21/2023 | AF31: 75.13 | AG31: =AF31/AF32-1 -> -0.025045419 | AI31: 05/21/2023 | AJ31: 257.72 | AK31: =AJ31/AJ32-1 -> -0.031273493 | AM31: 05/21/2023 | AN31: 51.51 | AO31: =AN31/AN32-1 -> -0.022209567 | AQ31: 05/21/2023 | AR31: 232.88 | AS31: =AR31/AR32-1 -> -0.010242679 | AU31: 05/21/2023 | AV31: 84.18 | AW31: =AV31/AV32-1 -> -0.039370079 | AY31: 05/21/2023 | AZ31: 4205.45 | BA31: =AZ31/AZ32-1 -> 0.0032132787
C32: 05/14/2023 | D32: 191.84 | E32: =D32/D33-1 -> -0.021823373 | G32: 05/14/2023 | H32: 62.83 | I32: =H32/H33-1 -> -0.019965684 | K32: 05/14/2023 | L32: 31.83 | M32: =L32/L33-1 -> -0.025711662 | O32: 05/14/2023 | P32: 59.68 | Q32: =P32/P33-1 -> 0.0023513604 | S32: 05/14/2023 | T32: 39.34 | U32: =T32/T33-1 -> -0.022365805 | W32: 05/14/2023 | X32: 69.33 | Y32: =X32/X33-1 -> -0.020901003 | AA32: 05/14/2023 | AB32: 39.07 | AC32: =AB32/AB33-1 -> -0.039104771 | AE32: 05/14/2023 | AF32: 77.06 | AG32: =AF32/AF33-1 -> -0.010529019 | AI32: 05/14/2023 | AJ32: 266.04 | AK32: =AJ32/AJ33-1 -> -0.031102047 | AM32: 05/14/2023 | AN32: 52.68 | AO32: =AN32/AN33-1 -> -0.030369961 | AQ32: 05/14/2023 | AR32: 235.29 | AS32: =AR32/AR33-1 -> 0.033106476 | AU32: 05/14/2023 | AV32: 87.63 | AW32: =AV32/AV33-1 -> -0.032888202 | AY32: 05/14/2023 | AZ32: 4191.98 | BA32: =AZ32/AZ33-1 -> 0.016464278
C33: 45112 | D33: 196.12 | E33: =D33/D34-1 -> 0.0095228291 | G33: 45112 | H33: 64.11 | I33: =H33/H34-1 -> 0.0014058107 | K33: 45112 | L33: 32.67 | M33: =L33/L34-1 -> -0.016852242 | O33: 45112 | P33: 59.54 | Q33: =P33/P34-1 -> -0.0028470943 | S33: 45112 | T33: 40.24 | U33: =T33/T34-1 -> -0.023300971 | W33: 45112 | X33: 70.81 | Y33: =X33/X34-1 -> 0.0065387349 | AA33: 45112 | AB33: 40.66 | AC33: =AB33/AB34-1 -> -0.015972894 | AE33: 45112 | AF33: 77.88 | AG33: =AF33/AF34-1 -> 0.0041258381 | AI33: 45112 | AJ33: 274.58 | AK33: =AJ33/AJ34-1 -> -0.0027240039 | AM33: 45112 | AN33: 54.33 | AO33: =AN33/AN34-1 -> -0.0074899525 | AQ33: 45112 | AR33: 227.75 | AS33: =AR33/AR34-1 -> 0.019289295 | AU33: 45112 | AV33: 90.61 | AW33: =AV33/AV34-1 -> 0.008907694 | AY33: 45112 | AZ33: 4124.08 | BA33: =AZ33/AZ34-1 -> -0.0029422786
C34: 04/30/2023 | D34: 194.27 | E34: =D34/D35-1 -> 0.017706533 | G34: 04/30/2023 | H34: 64.02 | I34: =H34/H35-1 -> -0.0020265004 | K34: 04/30/2023 | L34: 33.23 | M34: =L34/L35-1 -> 0.016207951 | O34: 04/30/2023 | P34: 59.71 | Q34: =P34/P35-1 -> 0.06625 | S34: 04/30/2023 | T34: 41.2 | U34: =T34/T35-1 -> 0.018793274 | W34: 04/30/2023 | X34: 70.35 | Y34: =X34/X35-1 -> 0.0083130285 | AA34: 04/30/2023 | AB34: 41.32 | AC34: =AB34/AB35-1 -> 0.052202699 | AE34: 04/30/2023 | AF34: 77.56 | AG34: =AF34/AF35-1 -> 0.010948905 | AI34: 04/30/2023 | AJ34: 275.33 | AK34: =AJ34/AJ35-1 -> 0.0083131912 | AM34: 04/30/2023 | AN34: 54.74 | AO34: =AN34/AN35-1 -> 0.0081031308 | AQ34: 04/30/2023 | AR34: 223.44 | AS34: =AR34/AR35-1 -> -0.026277945 | AU34: 04/30/2023 | AV34: 89.81 | AW34: =AV34/AV35-1 -> 0.013313776 | AY34: 04/30/2023 | AZ34: 4136.25 | BA34: =AZ34/AZ35-1 -> -0.0079698188
C35: 04/23/2023 | D35: 190.89 | E35: =D35/D36-1 -> 0.029556119 | G35: 04/23/2023 | H35: 64.15 | I35: =H35/H36-1 -> 0.0015612802 | K35: 04/23/2023 | L35: 32.7 | M35: =L35/L36-1 -> -0.073916737 | O35: 04/23/2023 | P35: 56 | Q35: =P35/P36-1 -> 0.0552101 | S35: 04/23/2023 | T35: 40.44 | U35: =T35/T36-1 -> 0.014805521 | W35: 04/23/2023 | X35: 69.77 | Y35: =X35/X36-1 -> 0.0359317 | AA35: 04/23/2023 | AB35: 39.27 | AC35: =AB35/AB36-1 -> 0.0012748598 | AE35: 04/23/2023 | AF35: 76.72 | AG35: =AF35/AF36-1 -> 0.075715087 | AI35: 04/23/2023 | AJ35: 273.06 | AK35: =AJ35/AJ36-1 -> 0.046808511 | AM35: 04/23/2023 | AN35: 54.3 | AO35: =AN35/AN36-1 -> 0.011738401 | AQ35: 04/23/2023 | AR35: 229.47 | AS35: =AR35/AR36-1 -> 0.013381028 | AU35: 04/23/2023 | AV35: 88.63 | AW35: =AV35/AV36-1 -> 0.013493425 | AY35: 04/23/2023 | AZ35: 4169.48 | BA35: =AZ35/AZ36-1 -> 0.0086996071
C36: 04/16/2023 | D36: 185.41 | E36: =D36/D37-1 -> 0.010353659 | G36: 04/16/2023 | H36: 64.05 | I36: =H36/H37-1 -> 0.015860428 | K36: 04/16/2023 | L36: 35.31 | M36: =L36/L37-1 -> 0.005982906 | O36: 04/16/2023 | P36: 53.07 | Q36: =P36/P37-1 -> 0.0097031963 | S36: 04/16/2023 | T36: 39.85 | U36: =T36/T37-1 -> 0.015028018 | W36: 04/16/2023 | X36: 67.35 | Y36: =X36/X37-1 -> 0.0052238806 | AA36: 04/16/2023 | AB36: 39.22 | AC36: =AB36/AB37-1 -> 0.0030690537 | AE36: 04/16/2023 | AF36: 71.32 | AG36: =AF36/AF37-1 -> 0.021630139 | AI36: 04/16/2023 | AJ36: 260.85 | AK36: =AJ36/AJ37-1 -> 0.017832059 | AM36: 04/16/2023 | AN36: 53.67 | AO36: =AN36/AN37-1 -> -0.02026287 | AQ36: 04/16/2023 | AR36: 226.44 | AS36: =AR36/AR37-1 -> -0.0078429654 | AU36: 04/16/2023 | AV36: 87.45 | AW36: =AV36/AV37-1 -> 0.010281885 | AY36: 04/16/2023 | AZ36: 4133.52 | BA36: =AZ36/AZ37-1 -> -0.0009957367
C37: 45173 | D37: 183.51 | E37: =D37/D38-1 -> -0.0046105446 | G37: 45173 | H37: 63.05 | I37: =H37/H38-1 -> 0.0033418205 | K37: 45173 | L37: 35.1 | M37: =L37/L38-1 -> -0.015151515 | O37: 45173 | P37: 52.56 | Q37: =P37/P38-1 -> 0 | S37: 45173 | T37: 39.26 | U37: =T37/T38-1 -> -0.026048127 | W37: 45173 | X37: 67 | Y37: =X37/X38-1 -> -0.014560965 | AA37: 45173 | AB37: 39.1 | AC37: =AB37/AB38-1 -> -0.0010219724 | AE37: 45173 | AF37: 69.81 | AG37: =AF37/AF38-1 -> -0.017452498 | AI37: 45173 | AJ37: 256.28 | AK37: =AJ37/AJ38-1 -> -0.0138146 | AM37: 45173 | AN37: 54.78 | AO37: =AN37/AN38-1 -> -0.012439156 | AQ37: 45173 | AR37: 228.23 | AS37: =AR37/AR38-1 -> 0.015981125 | AU37: 45173 | AV37: 86.56 | AW37: =AV37/AV38-1 -> -0.0039125432 | AY37: 45173 | AZ37: 4137.64 | BA37: =AZ37/AZ38-1 -> 0.0079463681
C38: 44961 | D38: 184.36 | E38: =D38/D39-1 -> 0.011300055 | G38: 44961 | H38: 62.84 | I38: =H38/H39-1 -> 0.013058198 | K38: 44961 | L38: 35.64 | M38: =L38/L39-1 -> 0.010204082 | O38: 44961 | P38: 52.56 | Q38: =P38/P39-1 -> -0.02684688 | S38: 44961 | T38: 40.31 | U38: =T38/T39-1 -> 0.010782347 | W38: 44961 | X38: 67.99 | Y38: =X38/X39-1 -> 0.015382318 | AA38: 44961 | AB38: 39.14 | AC38: =AB38/AB39-1 -> 0.012154125 | AE38: 44961 | AF38: 71.05 | AG38: =AF38/AF39-1 -> 0.019076305 | AI38: 44961 | AJ38: 259.87 | AK38: =AJ38/AJ39-1 -> 0.021461421 | AM38: 44961 | AN38: 55.47 | AO38: =AN38/AN39-1 -> 0.0089123318 | AQ38: 44961 | AR38: 224.64 | AS38: =AR38/AR39-1 -> -0.0055336668 | AU38: 44961 | AV38: 86.9 | AW38: =AV38/AV39-1 -> 0.016849988 | AY38: 44961 | AZ38: 4105.02 | BA38: =AZ38/AZ39-1 -> -0.0010439709
C39: 03/26/2023 | D39: 182.3 | E39: =D39/D40-1 -> 0.017923949 | G39: 03/26/2023 | H39: 62.03 | I39: =H39/H40-1 -> 0.018555008 | K39: 03/26/2023 | L39: 35.28 | M39: =L39/L40-1 -> 0.011757958 | O39: 03/26/2023 | P39: 54.01 | Q39: =P39/P40-1 -> 0.037855496 | S39: 03/26/2023 | T39: 39.88 | U39: =T39/T40-1 -> 0.031824062 | W39: 03/26/2023 | X39: 66.96 | Y39: =X39/X40-1 -> 0.022758515 | AA39: 03/26/2023 | AB39: 38.67 | AC39: =AB39/AB40-1 -> 0.012833944 | AE39: 03/26/2023 | AF39: 69.72 | AG39: =AF39/AF40-1 -> 0.0098493627 | AI39: 03/26/2023 | AJ39: 254.41 | AK39: =AJ39/AJ40-1 -> 0.026426208 | AM39: 03/26/2023 | AN39: 54.98 | AO39: =AN39/AN40-1 -> 0.0080674734 | AQ39: 03/26/2023 | AR39: 225.89 | AS39: =AR39/AR40-1 -> 0.036430374 | AU39: 03/26/2023 | AV39: 85.46 | AW39: =AV39/AV40-1 -> 0.0077830189 | AY39: 03/26/2023 | AZ39: 4109.31 | BA39: =AZ39/AZ40-1 -> 0.034832624
C40: 03/19/2023 | D40: 179.09 | E40: =D40/D41-1 -> 0.022611774 | G40: 03/19/2023 | H40: 60.9 | I40: =H40/H41-1 -> 0.014661779 | K40: 03/19/2023 | L40: 34.87 | M40: =L40/L41-1 -> 0.00028686173 | O40: 03/19/2023 | P40: 52.04 | Q40: =P40/P41-1 -> 0.010681686 | S40: 03/19/2023 | T40: 38.65 | U40: =T40/T41-1 -> 0.0078226858 | W40: 03/19/2023 | X40: 65.47 | Y40: =X40/X41-1 -> 0.011275873 | AA40: 03/19/2023 | AB40: 38.18 | AC40: =AB40/AB41-1 -> 0.014615998 | AE40: 03/19/2023 | AF40: 69.04 | AG40: =AF40/AF41-1 -> 0.039759036 | AI40: 03/19/2023 | AJ40: 247.86 | AK40: =AJ40/AJ41-1 -> 0.019370759 | AM40: 03/19/2023 | AN40: 54.54 | AO40: =AN40/AN41-1 -> 0.021730985 | AQ40: 03/19/2023 | AR40: 217.95 | AS40: =AR40/AR41-1 -> 0.033428165 | AU40: 03/19/2023 | AV40: 84.8 | AW40: =AV40/AV41-1 -> 0.062789823 | AY40: 03/19/2023 | AZ40: 3970.99 | BA40: =AZ40/AZ41-1 -> 0.01387669
C41: 45263 | D41: 175.13 | E41: =D41/D42-1 -> 0.018020113 | G41: 45263 | H41: 60.02 | I41: =H41/H42-1 -> 0.013680122 | K41: 45263 | L41: 34.86 | M41: =L41/L42-1 -> 0.015734266 | O41: 45263 | P41: 51.49 | Q41: =P41/P42-1 -> 0.027949691 | S41: 45263 | T41: 38.35 | U41: =T41/T42-1 -> -0.021184278 | W41: 45263 | X41: 64.74 | Y41: =X41/X42-1 -> 0.013304116 | AA41: 45263 | AB41: 37.63 | AC41: =AB41/AB42-1 -> -0.008170796 | AE41: 45263 | AF41: 66.4 | AG41: =AF41/AF42-1 -> 0.023112481 | AI41: 45263 | AJ41: 243.15 | AK41: =AJ41/AJ42-1 -> 0.022755952 | AM41: 45263 | AN41: 53.38 | AO41: =AN41/AN42-1 -> 0.016568273 | AQ41: 45263 | AR41: 210.9 | AS41: =AR41/AR42-1 -> -0.0051886792 | AU41: 45263 | AV41: 79.79 | AW41: =AV41/AV42-1 -> 0.016174223 | AY41: 45263 | AZ41: 3916.64 | BA41: =AZ41/AZ42-1 -> 0.014255786
C42: 45049 | D42: 172.03 | E42: =D42/D43-1 -> -0.00646838 | G42: 45049 | H42: 59.21 | I42: =H42/H43-1 -> -0.0038694482 | K42: 45049 | L42: 34.32 | M42: =L42/L43-1 -> -0.0066570188 | O42: 45049 | P42: 50.09 | Q42: =P42/P43-1 -> -0.018035679 | S42: 45049 | T42: 39.18 | U42: =T42/T43-1 -> -0.035687915 | W42: 45049 | X42: 63.89 | Y42: =X42/X43-1 -> -0.022191613 | AA42: 45049 | AB42: 37.94 | AC42: =AB42/AB43-1 -> -0.02817623 | AE42: 45049 | AF42: 64.9 | AG42: =AF42/AF43-1 -> -0.012326891 | AI42: 45049 | AJ42: 237.74 | AK42: =AJ42/AJ43-1 -> -0.0027684564 | AM42: 45049 | AN42: 52.51 | AO42: =AN42/AN43-1 -> 0.0019080328 | AQ42: 45049 | AR42: 212 | AS42: =AR42/AR43-1 -> -0.050391937 | AU42: 45049 | AV42: 78.52 | AW42: =AV42/AV43-1 -> -0.013567839 | AY42: 45049 | AZ42: 3861.59 | BA42: =AZ42/AZ43-1 -> -0.04549342
C43: 02/26/2023 | D43: 173.15 | E43: =D43/D44-1 -> -0.015969539 | G43: 02/26/2023 | H43: 59.44 | I43: =H43/H44-1 -> -0.006684492 | K43: 02/26/2023 | L43: 34.55 | M43: =L43/L44-1 -> -0.034646549 | O43: 02/26/2023 | P43: 51.01 | Q43: =P43/P44-1 -> 0.0077044646 | S43: 02/26/2023 | T43: 40.63 | U43: =T43/T44-1 -> -0.099113082 | W43: 02/26/2023 | X43: 65.34 | Y43: =X43/X44-1 -> -0.034574468 | AA43: 02/26/2023 | AB43: 39.04 | AC43: =AB43/AB44-1 -> -0.014390305 | AE43: 02/26/2023 | AF43: 65.71 | AG43: =AF43/AF44-1 -> 0.0024408848 | AI43: 02/26/2023 | AJ43: 238.4 | AK43: =AJ43/AJ44-1 -> -0.0025939252 | AM43: 02/26/2023 | AN43: 52.41 | AO43: =AN43/AN44-1 -> -0.013551666 | AQ43: 02/26/2023 | AR43: 223.25 | AS43: =AR43/AR44-1 -> -0.0037484939 | AU43: 02/26/2023 | AV43: 79.6 | AW43: =AV43/AV44-1 -> -0.012896825 | AY43: 02/26/2023 | AZ43: 4045.64 | BA43: =AZ43/AZ44-1 -> 0.019042629
C44: 02/19/2023 | D44: 175.96 | E44: =D44/D45-1 -> -0.0018152939 | G44: 02/19/2023 | H44: 59.84 | I44: =H44/H45-1 -> -0.004657352 | K44: 02/19/2023 | L44: 35.79 | M44: =L44/L45-1 -> 0.0033641716 | O44: 02/19/2023 | P44: 50.62 | Q44: =P44/P45-1 -> -0.028220388 | S44: 02/19/2023 | T44: 45.1 | U44: =T44/T45-1 -> -0.013992129 | W44: 02/19/2023 | X44: 67.68 | Y44: =X44/X45-1 -> -0.010236911 | AA44: 02/19/2023 | AB44: 39.61 | AC44: =AB44/AB45-1 -> -0.00975 | AE44: 02/19/2023 | AF44: 65.55 | AG44: =AF44/AF45-1 -> -0.019446522 | AI44: 02/19/2023 | AJ44: 239.02 | AK44: =AJ44/AJ45-1 -> -0.0069383855 | AM44: 02/19/2023 | AN44: 53.13 | AO44: =AN44/AN45-1 -> 0.014899713 | AQ44: 02/19/2023 | AR44: 224.09 | AS44: =AR44/AR45-1 -> -0.011948854 | AU44: 02/19/2023 | AV44: 80.64 | AW44: =AV44/AV45-1 -> 0.050410317 | AY44: 02/19/2023 | AZ44: 3970.04 | BA44: =AZ44/AZ45-1 -> -0.026733904
C45: 45262 | D45: 176.28 | E45: =D45/D46-1 -> 0.00045402951 | G45: 45262 | H45: 60.12 | I45: =H45/H46-1 -> 0.0083864475 | K45: 45262 | L45: 35.67 | M45: =L45/L46-1 -> 0.011054422 | O45: 45262 | P45: 52.09 | Q45: =P45/P46-1 -> 0.013424125 | S45: 45262 | T45: 45.74 | U45: =T45/T46-1 -> 0.017575083 | W45: 45262 | X45: 68.38 | Y45: =X45/X46-1 -> 0.010193529 | AA45: 45262 | AB45: 40 | AC45: =AB45/AB46-1 -> 0.0093363613 | AE45: 45262 | AF45: 66.85 | AG45: =AF45/AF46-1 -> 0.020610687 | AI45: 45262 | AJ45: 240.69 | AK45: =AJ45/AJ46-1 -> 0.0066499373 | AM45: 45262 | AN45: 52.35 | AO45: =AN45/AN46-1 -> 0.017888392 | AQ45: 45262 | AR45: 226.8 | AS45: =AR45/AR46-1 -> -0.0065703022 | AU45: 45262 | AV45: 76.77 | AW45: =AV45/AV46-1 -> 0.0089367854 | AY45: 45262 | AZ45: 4079.09 | BA45: =AZ45/AZ46-1 -> -0.0027796385
C46: 45048 | D46: 176.2 | E46: =D46/D47-1 -> 0.041863765 | G46: 45048 | H46: 59.62 | I46: =H46/H47-1 -> -0.0035099448 | K46: 45048 | L46: 35.28 | M46: =L46/L47-1 -> 0.0036984353 | O46: 45048 | P46: 51.4 | Q46: =P46/P47-1 -> 0.0098231827 | S46: 45048 | T46: 44.95 | U46: =T46/T47-1 -> -0.0064102564 | W46: 45048 | X46: 67.69 | Y46: =X46/X47-1 -> 0.0011832569 | AA46: 45048 | AB46: 39.63 | AC46: =AB46/AB47-1 -> 0.0063484002 | AE46: 45048 | AF46: 65.5 | AG46: =AF46/AF47-1 -> -0.0062206039 | AI46: 45048 | AJ46: 239.1 | AK46: =AJ46/AJ47-1 -> 0.011934992 | AM46: 45048 | AN46: 51.43 | AO46: =AN46/AN47-1 -> 0.010809748 | AQ46: 45048 | AR46: 228.3 | AS46: =AR46/AR47-1 -> -0.010917598 | AU46: 45048 | AV46: 76.09 | AW46: =AV46/AV47-1 -> 0.008081611 | AY46: 45048 | AZ46: 4090.46 | BA46: =AZ46/AZ47-1 -> -0.011125401
C47: 01/29/2023 | D47: 169.12 | E47: =D47/D48-1 -> -0.0029477656 | G47: 01/29/2023 | H47: 59.83 | I47: =H47/H48-1 -> -0.010910894 | K47: 01/29/2023 | L47: 35.15 | M47: =L47/L48-1 -> 0.0129683 | O47: 01/29/2023 | P47: 50.9 | Q47: =P47/P48-1 -> -0.0097276265 | S47: 01/29/2023 | T47: 45.24 | U47: =T47/T48-1 -> 0.0077968367 | W47: 01/29/2023 | X47: 67.61 | Y47: =X47/X48-1 -> 0.00014792899 | AA47: 01/29/2023 | AB47: 39.38 | AC47: =AB47/AB48-1 -> -0.0078105316 | AE47: 01/29/2023 | AF47: 65.91 | AG47: =AF47/AF48-1 -> 0.018386897 | AI47: 01/29/2023 | AJ47: 236.28 | AK47: =AJ47/AJ48-1 -> 0.080087767 | AM47: 01/29/2023 | AN47: 50.88 | AO47: =AN47/AN48-1 -> -0.0048894974 | AQ47: 01/29/2023 | AR47: 230.82 | AS47: =AR47/AR48-1 -> 0.0088727654 | AU47: 01/29/2023 | AV47: 75.48 | AW47: =AV47/AV48-1 -> -0.030941071 | AY47: 01/29/2023 | AZ47: 4136.48 | BA47: =AZ47/AZ48-1 -> 0.016194332
C48: 01/22/2023 | D48: 169.62 | E48: =D48/D49-1 -> -0.0015304921 | G48: 01/22/2023 | H48: 60.49 | I48: =H48/H49-1 -> 0.0068242344 | K48: 01/22/2023 | L48: 34.7 | M48: =L48/L49-1 -> -0.00028810141 | O48: 01/22/2023 | P48: 51.4 | Q48: =P48/P49-1 -> 0.028 | S48: 01/22/2023 | T48: 44.89 | U48: =T48/T49-1 -> 0.0069537909 | W48: 01/22/2023 | X48: 67.6 | Y48: =X48/X49-1 -> 0.0014814815 | AA48: 01/22/2023 | AB48: 39.69 | AC48: =AB48/AB49-1 -> -0.0047642929 | AE48: 01/22/2023 | AF48: 64.72 | AG48: =AF48/AF49-1 -> 0.010618364 | AI48: 01/22/2023 | AJ48: 218.76 | AK48: =AJ48/AJ49-1 -> 0.019765057 | AM48: 01/22/2023 | AN48: 51.13 | AO48: =AN48/AN49-1 -> -0.017486549 | AQ48: 01/22/2023 | AR48: 228.79 | AS48: =AR48/AR49-1 -> 0.0358113 | AU48: 01/22/2023 | AV48: 77.89 | AW48: =AV48/AV49-1 -> 0.0055512523 | AY48: 01/22/2023 | AZ48: 4070.56 | BA48: =AZ48/AZ49-1 -> 0.024656334
C49: 01/15/2023 | D49: 169.88 | E49: =D49/D50-1 -> -0.030586624 | G49: 01/15/2023 | H49: 60.08 | I49: =H49/H50-1 -> -0.021976233 | K49: 01/15/2023 | L49: 34.71 | M49: =L49/L50-1 -> -0.027458672 | O49: 01/15/2023 | P49: 50 | Q49: =P49/P50-1 -> -0.020376176 | S49: 01/15/2023 | T49: 44.58 | U49: =T49/T50-1 -> -0.0329718 | W49: 01/15/2023 | X49: 67.5 | Y49: =X49/X50-1 -> -0.035714286 | AA49: 01/15/2023 | AB49: 39.88 | AC49: =AB49/AB50-1 -> -0.059877416 | AE49: 01/15/2023 | AF49: 64.04 | AG49: =AF49/AF50-1 -> -0.045034298 | AI49: 01/15/2023 | AJ49: 214.52 | AK49: =AJ49/AJ50-1 -> -0.053351573 | AM49: 01/15/2023 | AN49: 52.04 | AO49: =AN49/AN50-1 -> -0.053129549 | AQ49: 01/15/2023 | AR49: 220.88 | AS49: =AR49/AR50-1 -> -0.018311111 | AU49: 01/15/2023 | AV49: 77.46 | AW49: =AV49/AV50-1 -> -0.061204702 | AY49: 01/15/2023 | AZ49: 3972.61 | BA49: =AZ49/AZ50-1 -> -0.0066215064
C50: 45139 | D50: 175.24 | E50: =D50/D51-1 -> -0.032357813 | G50: 45139 | H50: 61.43 | I50: =H50/H51-1 -> -0.031072555 | K50: 45139 | L50: 35.69 | M50: =L50/L51-1 -> -0.015719801 | O50: 45139 | P50: 51.04 | Q50: =P50/P51-1 -> -0.0035142522 | S50: 45139 | T50: 46.1 | U50: =T50/T51-1 -> -0.017267107 | W50: 45139 | X50: 70 | Y50: =X50/X51-1 -> -0.033816425 | AA50: 45139 | AB50: 42.42 | AC50: =AB50/AB51-1 -> -0.0039915473 | AE50: 45139 | AF50: 67.06 | AG50: =AF50/AF51-1 -> -0.014113496 | AI50: 45139 | AJ50: 226.61 | AK50: =AJ50/AJ51-1 -> 0.0042543762 | AM50: 45139 | AN50: 54.96 | AO50: =AN50/AN51-1 -> -0.035958604 | AQ50: 45139 | AR50: 225 | AS50: =AR50/AR51-1 -> 0.050273071 | AU50: 45139 | AV50: 82.51 | AW50: =AV50/AV51-1 -> -0.040134946 | AY50: 45139 | AZ50: 3999.09 | BA50: =AZ50/AZ51-1 -> 0.026702918
C51: 44927 | D51: 181.1 | E51: =D51/D52-1 -> 0.0024355142 | G51: 44927 | H51: 63.4 | I51: =H51/H52-1 -> -0.0033013677 | K51: 44927 | L51: 36.26 | M51: =L51/L52-1 -> 0.016825575 | O51: 44927 | P51: 51.22 | Q51: =P51/P52-1 -> 0.0088635021 | S51: 44927 | T51: 46.91 | U51: =T51/T52-1 -> 0.0298573 | W51: 44927 | X51: 72.45 | Y51: =X51/X52-1 -> 0.01698484 | AA51: 44927 | AB51: 42.59 | AC51: =AB51/AB52-1 -> 0.0461803 | AE51: 44927 | AF51: 68.02 | AG51: =AF51/AF52-1 -> 0.020555139 | AI51: 44927 | AJ51: 225.65 | AK51: =AJ51/AJ52-1 -> -0.025564624 | AM51: 44927 | AN51: 57.01 | AO51: =AN51/AN52-1 -> 0.0045814978 | AQ51: 44927 | AR51: 214.23 | AS51: =AR51/AR52-1 -> -0.075598706 | AU51: 44927 | AV51: 85.96 | AW51: =AV51/AV52-1 -> 0.025163983 | AY51: 44927 | AZ51: 3895.08 | BA51: =AZ51/AZ52-1 -> 0.014475843
C52: 12/25/2022 | D52: 180.66 | E52: =D52/D53-1 -> -0.0087786678 | G52: 12/25/2022 | H52: 63.61 | I52: =H52/H53-1 -> -0.0032905045 | K52: 12/25/2022 | L52: 35.66 | M52: =L52/L53-1 -> -0.019521584 | O52: 12/25/2022 | P52: 50.77 | Q52: =P52/P53-1 -> 0.002765159 | S52: 12/25/2022 | T52: 45.55 | U52: =T52/T53-1 -> -0.0017532325 | W52: 12/25/2022 | X52: 71.24 | Y52: =X52/X53-1 -> -0.013022998 | AA52: 12/25/2022 | AB52: 40.71 | AC52: =AB52/AB53-1 -> 0.0046890424 | AE52: 12/25/2022 | AF52: 66.65 | AG52: =AF52/AF53-1 -> -0.0067064083 | AI52: 12/25/2022 | AJ52: 231.57 | AK52: =AJ52/AJ53-1 -> -0.018272003 | AM52: 12/25/2022 | AN52: 56.75 | AO52: =AN52/AN53-1 -> -0.0092527933 | AQ52: 12/25/2022 | AR52: 231.75 | AS52: =AR52/AR53-1 -> -0.002839809 | AU52: 12/25/2022 | AV52: 83.85 | AW52: =AV52/AV53-1 -> -0.01826484 | AY52: 12/25/2022 | AZ52: 3839.5 | BA52: =AZ52/AZ53-1 -> -0.0013836799
C53: 12/18/2022 | D53: 182.26 | E53: =D53/D54-1 -> 0.010646557 | G53: 12/18/2022 | H53: 63.82 | I53: =H53/H54-1 -> 0.017051793 | K53: 12/18/2022 | L53: 36.37 | M53: =L53/L54-1 -> 0.0083171611 | O53: 12/18/2022 | P53: 50.63 | Q53: =P53/P54-1 -> 0.0047628498 | S53: 12/18/2022 | T53: 45.63 | U53: =T53/T54-1 -> -0.00065703022 | W53: 12/18/2022 | X53: 72.18 | Y53: =X53/X54-1 -> 0.012484219 | AA53: 12/18/2022 | AB53: 40.52 | AC53: =AB53/AB54-1 -> 0.01503006 | AE53: 12/18/2022 | AF53: 67.1 | AG53: =AF53/AF54-1 -> 0.014207981 | AI53: 12/18/2022 | AJ53: 235.88 | AK53: =AJ53/AJ54-1 -> 0.0037446809 | AM53: 12/18/2022 | AN53: 57.28 | AO53: =AN53/AN54-1 -> 0.0038555906 | AQ53: 12/18/2022 | AR53: 232.41 | AS53: =AR53/AR54-1 -> 0.0045383817 | AU53: 12/18/2022 | AV53: 85.41 | AW53: =AV53/AV54-1 -> -0.017485333 | AY53: 12/18/2022 | AZ53: 3844.82 | BA53: =AZ53/AZ54-1 -> -0.0019572418
C54: 44877 | D54: 180.34 | E54: =D54/D55-1 -> -0.01507373 | G54: 44877 | H54: 62.75 | I54: =H54/H55-1 -> -0.0061767501 | K54: 44877 | L54: 36.07 | M54: =L54/L55-1 -> -0.049037701 | O54: 44877 | P54: 50.39 | Q54: =P54/P55-1 -> 0.0073970412 | S54: 44877 | T54: 45.66 | U54: =T54/T55-1 -> -0.028923862 | W54: 44877 | X54: 71.29 | Y54: =X54/X55-1 -> -0.014514791 | AA54: 44877 | AB54: 39.92 | AC54: =AB54/AB55-1 -> -0.00050075113 | AE54: 44877 | AF54: 66.16 | AG54: =AF54/AF55-1 -> -0.013420817 | AI54: 44877 | AJ54: 235 | AK54: =AJ54/AJ55-1 -> -0.0074756092 | AM54: 44877 | AN54: 57.06 | AO54: =AN54/AN55-1 -> 0.025152713 | AQ54: 44877 | AR54: 231.36 | AS54: =AR54/AR55-1 -> -0.044124938 | AU54: 44877 | AV54: 86.93 | AW54: =AV54/AV55-1 -> 0.012698043 | AY54: 44877 | AZ54: 3852.36 | BA54: =AZ54/AZ55-1 -> -0.020846995
C55: 44663 | D55: 183.1 | E55: =D55/D56-1 -> -0.013947978 | G55: 44663 | H55: 63.14 | I55: =H55/H56-1 -> -0.018803419 | K55: 44663 | L55: 37.93 | M55: =L55/L56-1 -> -0.020908622 | O55: 44663 | P55: 50.02 | Q55: =P55/P56-1 -> -0.038446751 | S55: 44663 | T55: 47.02 | U55: =T55/T56-1 -> -0.013014274 | W55: 44663 | X55: 72.34 | Y55: =X55/X56-1 -> -0.020181498 | AA55: 44663 | AB55: 39.94 | AC55: =AB55/AB56-1 -> 0.0027617374 | AE55: 44663 | AF55: 67.06 | AG55: =AF55/AF56-1 -> -0.018298931 | AI55: 44663 | AJ55: 236.77 | AK55: =AJ55/AJ56-1 -> 0.0086908363 | AM55: 44663 | AN55: 55.66 | AO55: =AN55/AN56-1 -> 0.02883549 | AQ55: 44663 | AR55: 242.04 | AS55: =AR55/AR56-1 -> -0.072821299 | AU55: 44663 | AV55: 85.84 | AW55: =AV55/AV56-1 -> -0.0078594545 | AY55: 44663 | AZ55: 3934.38 | BA55: =AZ55/AZ56-1 -> -0.033725471
C56: 11/27/2022 | D56: 185.69 | E56: =D56/D57-1 -> 0.0085818261 | G56: 11/27/2022 | H56: 64.35 | I56: =H56/H57-1 -> 0.026479502 | K56: 11/27/2022 | L56: 38.74 | M56: =L56/L57-1 -> 0.012810458 | O56: 11/27/2022 | P56: 52.02 | Q56: =P56/P57-1 -> 0.0063842136 | S56: 11/27/2022 | T56: 47.64 | U56: =T56/T57-1 -> -0.035822708 | W56: 11/27/2022 | X56: 73.83 | Y56: =X56/X57-1 -> 0.014148352 | AA56: 11/27/2022 | AB56: 39.83 | AC56: =AB56/AB57-1 -> 0.023907455 | AE56: 11/27/2022 | AF56: 68.31 | AG56: =AF56/AF57-1 -> 0.024291498 | AI56: 11/27/2022 | AJ56: 234.73 | AK56: =AJ56/AJ57-1 -> 0.0041495551 | AM56: 11/27/2022 | AN56: 54.1 | AO56: =AN56/AN57-1 -> 0.019984917 | AQ56: 11/27/2022 | AR56: 261.05 | AS56: =AR56/AR57-1 -> 0.01382578 | AU56: 11/27/2022 | AV56: 86.52 | AW56: =AV56/AV57-1 -> 0.042786549 | AY56: 11/27/2022 | AZ56: 4071.7 | BA56: =AZ56/AZ57-1 -> 0.011321073
C57: 11/20/2022 | D57: 184.11 | E57: =D57/D58-1 -> 0.015331164 | G57: 11/20/2022 | H57: 62.69 | I57: =H57/H58-1 -> 0.025351652 | K57: 11/20/2022 | L57: 38.25 | M57: =L57/L58-1 -> 0.022180652 | O57: 11/20/2022 | P57: 51.69 | Q57: =P57/P58-1 -> 0.036910732 | S57: 11/20/2022 | T57: 49.41 | U57: =T57/T58-1 -> 0.01541307 | W57: 11/20/2022 | X57: 72.8 | Y57: =X57/X58-1 -> 0.031015437 | AA57: 11/20/2022 | AB57: 38.9 | AC57: =AB57/AB58-1 -> 0.020997375 | AE57: 11/20/2022 | AF57: 66.69 | AG57: =AF57/AF58-1 -> 0.02615787 | AI57: 11/20/2022 | AJ57: 233.76 | AK57: =AJ57/AJ58-1 -> 0.037964566 | AM57: 11/20/2022 | AN57: 53.04 | AO57: =AN57/AN58-1 -> 0.028704422 | AQ57: 11/20/2022 | AR57: 257.49 | AS57: =AR57/AR58-1 -> 0.039733495 | AU57: 11/20/2022 | AV57: 82.97 | AW57: =AV57/AV58-1 -> 0.02394175 | AY57: 11/20/2022 | AZ57: 4026.12 | BA57: =AZ57/AZ58-1 -> 0.015327816
C58: 11/13/2022 | D58: 181.33 | E58: =D58/D59-1 -> 0.018421792 | G58: 11/13/2022 | H58: 61.14 | I58: =H58/H59-1 -> -0.0029354207 | K58: 11/13/2022 | L58: 37.42 | M58: =L58/L59-1 -> 0.0021424746 | O58: 11/13/2022 | P58: 49.85 | Q58: =P58/P59-1 -> 0.016102731 | S58: 11/13/2022 | T58: 48.66 | U58: =T58/T59-1 -> 0.026582278 | W58: 11/13/2022 | X58: 70.61 | Y58: =X58/X59-1 -> 0.023630038 | AA58: 11/13/2022 | AB58: 38.1 | AC58: =AB58/AB59-1 -> 0.03000811 | AE58: 11/13/2022 | AF58: 64.99 | AG58: =AF58/AF59-1 -> 0.0029320988 | AI58: 11/13/2022 | AJ58: 225.21 | AK58: =AJ58/AJ59-1 -> 0.028919956 | AM58: 11/13/2022 | AN58: 51.56 | AO58: =AN58/AN59-1 -> 0.052889524 | AQ58: 11/13/2022 | AR58: 247.65 | AS58: =AR58/AR59-1 -> 0.0026315789 | AU58: 11/13/2022 | AV58: 81.03 | AW58: =AV58/AV59-1 -> 0.048932039 | AY58: 11/13/2022 | AZ58: 3965.34 | BA58: =AZ58/AZ59-1 -> -0.0069097129
C59: 44723 | D59: 178.05 | E59: =D59/D60-1 -> -0.0040832308 | G59: 44723 | H59: 61.32 | I59: =H59/H60-1 -> 0.034762065 | K59: 44723 | L59: 37.34 | M59: =L59/L60-1 -> 0.0097349919 | O59: 44723 | P59: 49.06 | Q59: =P59/P60-1 -> 0.0018378599 | S59: 44723 | T59: 47.4 | U59: =T59/T60-1 -> 0.029092488 | W59: 44723 | X59: 68.98 | Y59: =X59/X60-1 -> -0.012596622 | AA59: 44723 | AB59: 36.99 | AC59: =AB59/AB60-1 -> -0.027091005 | AE59: 44723 | AF59: 64.8 | AG59: =AF59/AF60-1 -> 0.024992091 | AI59: 44723 | AJ59: 218.88 | AK59: =AJ59/AJ60-1 -> -0.044317338 | AM59: 44723 | AN59: 48.97 | AO59: =AN59/AN60-1 -> -0.036592563 | AQ59: 44723 | AR59: 247 | AS59: =AR59/AR60-1 -> 0.0088632929 | AU59: 44723 | AV59: 77.25 | AW59: =AV59/AV60-1 -> -0.022894005 | AY59: 44723 | AZ59: 3992.93 | BA59: =AZ59/AZ60-1 -> 0.058978133
C60: 10/30/2022 | D60: 178.78 | E60: =D60/D61-1 -> -0.018932119 | G60: 10/30/2022 | H60: 59.26 | I60: =H60/H61-1 -> -0.024687294 | K60: 10/30/2022 | L60: 36.98 | M60: =L60/L61-1 -> -0.064981037 | O60: 10/30/2022 | P60: 48.97 | Q60: =P60/P61-1 -> 0.0470387 | S60: 10/30/2022 | T60: 46.06 | U60: =T60/T61-1 -> -0.019165247 | W60: 10/30/2022 | X60: 69.86 | Y60: =X60/X61-1 -> -0.090246126 | AA60: 10/30/2022 | AB60: 38.02 | AC60: =AB60/AB61-1 -> -0.023626091 | AE60: 10/30/2022 | AF60: 63.22 | AG60: =AF60/AF61-1 -> 0.024635332 | AI60: 10/30/2022 | AJ60: 229.03 | AK60: =AJ60/AJ61-1 -> -0.045549258 | AM60: 10/30/2022 | AN60: 50.83 | AO60: =AN60/AN61-1 -> -0.036032619 | AQ60: 10/30/2022 | AR60: 244.83 | AS60: =AR60/AR61-1 -> -0.0091464649 | AU60: 10/30/2022 | AV60: 79.06 | AW60: =AV60/AV61-1 -> -0.030771117 | AY60: 10/30/2022 | AZ60: 3770.55 | BA60: =AZ60/AZ61-1 -> -0.03345501
C61: 10/23/2022 | D61: 182.23 | E61: =D61/D62-1 -> 0.052987403 | G61: 10/23/2022 | H61: 60.76 | I61: =H61/H62-1 -> 0.085775554 | K61: 10/23/2022 | L61: 39.55 | M61: =L61/L62-1 -> 0.051302499 | O61: 10/23/2022 | P61: 46.77 | Q61: =P61/P62-1 -> 0.067808219 | S61: 10/23/2022 | T61: 46.96 | U61: =T61/T62-1 -> 0.044251723 | W61: 10/23/2022 | X61: 76.79 | Y61: =X61/X62-1 -> 0.062984496 | AA61: 10/23/2022 | AB61: 38.94 | AC61: =AB61/AB62-1 -> 0.10593581 | AE61: 10/23/2022 | AF61: 61.7 | AG61: =AF61/AF62-1 -> 0.075850044 | AI61: 10/23/2022 | AJ61: 239.96 | AK61: =AJ61/AJ62-1 -> 0.051441591 | AM61: 10/23/2022 | AN61: 52.73 | AO61: =AN61/AN62-1 -> 0.049353234 | AQ61: 10/23/2022 | AR61: 247.09 | AS61: =AR61/AR62-1 -> 0.097446147 | AU61: 10/23/2022 | AV61: 81.57 | AW61: =AV61/AV62-1 -> 0.058800623 | AY61: 10/23/2022 | AZ61: 3901.06 | BA61: =AZ61/AZ62-1 -> 0.039520352
C62: 10/16/2022 | D62: 173.06 | E62: =D62/D63-1 -> 0.016863505 | G62: 10/16/2022 | H62: 55.96 | I62: =H62/H63-1 -> 0.017824664 | K62: 10/16/2022 | L62: 37.62 | M62: =L62/L63-1 -> 0.0077685508 | O62: 10/16/2022 | P62: 43.8 | Q62: =P62/P63-1 -> 0.0022883295 | S62: 10/16/2022 | T62: 44.97 | U62: =T62/T63-1 -> 0.0017821341 | W62: 10/16/2022 | X62: 72.24 | Y62: =X62/X63-1 -> 0.0036121145 | AA62: 10/16/2022 | AB62: 35.21 | AC62: =AB62/AB63-1 -> -0.014553596 | AE62: 10/16/2022 | AF62: 57.35 | AG62: =AF62/AF63-1 -> 0.007200562 | AI62: 10/16/2022 | AJ62: 228.22 | AK62: =AJ62/AJ63-1 -> 0.024740694 | AM62: 10/16/2022 | AN62: 50.25 | AO62: =AN62/AN63-1 -> -0.0023823705 | AQ62: 10/16/2022 | AR62: 225.15 | AS62: =AR62/AR63-1 -> 0.014234875 | AU62: 10/16/2022 | AV62: 77.04 | AW62: =AV62/AV63-1 -> -0.008621799 | AY62: 10/16/2022 | AZ62: 3752.75 | BA62: =AZ62/AZ63-1 -> 0.047356038
C63: 44814 | D63: 170.19 | E63: =D63/D64-1 -> 0.053090774 | G63: 44814 | H63: 54.98 | I63: =H63/H64-1 -> 0.0086222711 | K63: 44814 | L63: 37.33 | M63: =L63/L64-1 -> 0.022739726 | O63: 44814 | P63: 43.7 | Q63: =P63/P64-1 -> -0.032115172 | S63: 44814 | T63: 44.89 | U63: =T63/T64-1 -> 0.0078581051 | W63: 44814 | X63: 71.98 | Y63: =X63/X64-1 -> 0.033452979 | AA63: 44814 | AB63: 35.73 | AC63: =AB63/AB64-1 -> 0.081743869 | AE63: 44814 | AF63: 56.94 | AG63: =AF63/AF64-1 -> 0.030401737 | AI63: 44814 | AJ63: 222.71 | AK63: =AJ63/AJ64-1 -> 0.009931072 | AM63: 44814 | AN63: 50.37 | AO63: =AN63/AN64-1 -> 0.080205876 | AQ63: 44814 | AR63: 221.99 | AS63: =AR63/AR64-1 -> -0.0031881455 | AU63: 44814 | AV63: 77.71 | AW63: =AV63/AV64-1 -> 0.031320504 | AY63: 44814 | AZ63: 3583.07 | BA63: =AZ63/AZ64-1 -> -0.015548156
C64: 44602 | D64: 161.61 | E64: =D64/D65-1 -> -0.010106578 | G64: 44602 | H64: 54.51 | I64: =H64/H65-1 -> -0.026954659 | K64: 44602 | L64: 36.5 | M64: =L64/L65-1 -> 0.018983808 | O64: 44602 | P64: 45.15 | Q64: =P64/P65-1 -> 0.038408464 | S64: 44602 | T64: 44.54 | U64: =T64/T65-1 -> -0.019806338 | W64: 44602 | X64: 69.65 | Y64: =X64/X65-1 -> -0.00014355441 | AA64: 44602 | AB64: 33.03 | AC64: =AB64/AB65-1 -> -0.0095952024 | AE64: 44602 | AF64: 55.26 | AG64: =AF64/AF65-1 -> 0.007842422 | AI64: 44602 | AJ64: 220.52 | AK64: =AJ64/AJ65-1 -> 0.00022678823 | AM64: 44602 | AN64: 46.63 | AO64: =AN64/AN65-1 -> -0.010398981 | AQ64: 44602 | AR64: 222.7 | AS64: =AR64/AR65-1 -> -0.030390108 | AU64: 44602 | AV64: 75.35 | AW64: =AV64/AV65-1 -> -0.016446939 | AY64: 44602 | AZ64: 3639.66 | BA64: =AZ64/AZ65-1 -> 0.015071313
C65: 09/25/2022 | D65: 163.26 | E65: =D65/D66-1 -> -0.031212912 | G65: 09/25/2022 | H65: 56.02 | I65: =H65/H66-1 -> -0.044027304 | K65: 09/25/2022 | L65: 35.82 | M65: =L65/L66-1 -> -0.033980583 | O65: 09/25/2022 | P65: 43.48 | Q65: =P65/P66-1 -> -0.0016073479 | S65: 09/25/2022 | T65: 45.44 | U65: =T65/T66-1 -> -0.030509921 | W65: 09/25/2022 | X65: 69.66 | Y65: =X65/X66-1 -> -0.046276013 | AA65: 09/25/2022 | AB65: 33.35 | AC65: =AB65/AB66-1 -> -0.016804245 | AE65: 09/25/2022 | AF65: 54.83 | AG65: =AF65/AF66-1 -> -0.069889737 | AI65: 09/25/2022 | AJ65: 220.47 | AK65: =AJ65/AJ66-1 -> -0.015495222 | AM65: 09/25/2022 | AN65: 47.12 | AO65: =AN65/AN66-1 -> -0.030452675 | AQ65: 09/25/2022 | AR65: 229.68 | AS65: =AR65/AR66-1 -> -0.006832137 | AU65: 09/25/2022 | AV65: 76.61 | AW65: =AV65/AV66-1 -> -0.032335481 | AY65: 09/25/2022 | AZ65: 3585.62 | BA65: =AZ65/AZ66-1 -> -0.029137097
C66: 09/18/2022 | D66: 168.52 | E66: =D66/D67-1 -> 0.0092831047 | G66: 09/18/2022 | H66: 58.6 | I66: =H66/H67-1 -> -0.015787706 | K66: 09/18/2022 | L66: 37.08 | M66: =L66/L67-1 -> -0.0024213075 | O66: 09/18/2022 | P66: 43.55 | Q66: =P66/P67-1 -> -0.0016047685 | S66: 09/18/2022 | T66: 46.87 | U66: =T66/T67-1 -> 0.023585936 | W66: 09/18/2022 | X66: 73.04 | Y66: =X66/X67-1 -> 0.027574564 | AA66: 09/18/2022 | AB66: 33.92 | AC66: =AB66/AB67-1 -> -0.022760012 | AE66: 09/18/2022 | AF66: 58.95 | AG66: =AF66/AF67-1 -> -0.02238806 | AI66: 09/18/2022 | AJ66: 223.94 | AK66: =AJ66/AJ67-1 -> 0.0184183 | AM66: 09/18/2022 | AN66: 48.6 | AO66: =AN66/AN67-1 -> 0.019081568 | AQ66: 09/18/2022 | AR66: 231.26 | AS66: =AR66/AR67-1 -> -0.036015006 | AU66: 09/18/2022 | AV66: 79.17 | AW66: =AV66/AV67-1 -> 0.052093023 | AY66: 09/18/2022 | AZ66: 3693.23 | BA66: =AZ66/AZ67-1 -> -0.046497458
C67: 44874 | D67: 166.97 | E67: =D67/D68-1 -> -0.036081284 | G67: 44874 | H67: 59.54 | I67: =H67/H68-1 -> -0.044608472 | K67: 44874 | L67: 37.17 | M67: =L67/L68-1 -> -0.039286637 | O67: 44874 | P67: 43.62 | Q67: =P67/P68-1 -> -0.056252704 | S67: 44874 | T67: 45.79 | U67: =T67/T68-1 -> -0.022833974 | W67: 44874 | X67: 71.08 | Y67: =X67/X68-1 -> -0.013599778 | AA67: 44874 | AB67: 34.71 | AC67: =AB67/AB68-1 -> -0.047997806 | AE67: 44874 | AF67: 60.3 | AG67: =AF67/AF68-1 -> -0.016794391 | AI67: 44874 | AJ67: 219.89 | AK67: =AJ67/AJ68-1 -> -0.028110497 | AM67: 44874 | AN67: 47.69 | AO67: =AN67/AN68-1 -> -0.0050073023 | AQ67: 44874 | AR67: 239.9 | AS67: =AR67/AR68-1 -> -0.027563843 | AU67: 44874 | AV67: 75.25 | AW67: =AV67/AV68-1 -> -0.0086945067 | AY67: 44874 | AZ67: 3873.33 | BA67: =AZ67/AZ68-1 -> -0.047704162
C68: 44660 | D68: 173.22 | E68: =D68/D69-1 -> 0.015000586 | G68: 44660 | H68: 62.32 | I68: =H68/H69-1 -> 0.019133279 | K68: 44660 | L68: 38.69 | M68: =L68/L69-1 -> 0.02273328 | O68: 44660 | P68: 46.22 | Q68: =P68/P69-1 -> 0.045701357 | S68: 44660 | T68: 46.86 | U68: =T68/T69-1 -> 0.010131494 | W68: 44660 | X68: 72.06 | Y68: =X68/X69-1 -> -0.0088033012 | AA68: 44660 | AB68: 36.46 | AC68: =AB68/AB69-1 -> -0.022782096 | AE68: 44660 | AF68: 61.33 | AG68: =AF68/AF69-1 -> 0.0098797958 | AI68: 44660 | AJ68: 226.25 | AK68: =AJ68/AJ69-1 -> 0.0098192368 | AM68: 44660 | AN68: 47.93 | AO68: =AN68/AN69-1 -> -0.024424995 | AQ68: 44660 | AR68: 246.7 | AS68: =AR68/AR69-1 -> 0.0075556463 | AU68: 44660 | AV68: 75.91 | AW68: =AV68/AV69-1 -> -0.010557873 | AY68: 44660 | AZ68: 4067.36 | BA68: =AZ68/AZ69-1 -> 0.036465474
C69: 08/28/2022 | D69: 170.66 | E69: =D69/D70-1 -> -0.025022852 | G69: 08/28/2022 | H69: 61.15 | I69: =H69/H70-1 -> -0.031056885 | K69: 08/28/2022 | L69: 37.83 | M69: =L69/L70-1 -> -0.020455722 | O69: 08/28/2022 | P69: 44.2 | Q69: =P69/P70-1 -> -0.0085240018 | S69: 08/28/2022 | T69: 46.39 | U69: =T69/T70-1 -> -0.091816758 | W69: 08/28/2022 | X69: 72.7 | Y69: =X69/X70-1 -> -0.015572106 | AA69: 08/28/2022 | AB69: 37.31 | AC69: =AB69/AB70-1 -> -0.020991866 | AE69: 08/28/2022 | AF69: 60.73 | AG69: =AF69/AF70-1 -> -0.031882672 | AI69: 08/28/2022 | AJ69: 224.05 | AK69: =AJ69/AJ70-1 -> -0.020203787 | AM69: 08/28/2022 | AN69: 49.13 | AO69: =AN69/AN70-1 -> -0.030775301 | AQ69: 08/28/2022 | AR69: 244.85 | AS69: =AR69/AR70-1 -> -0.027987297 | AU69: 08/28/2022 | AV69: 76.72 | AW69: =AV69/AV70-1 -> 0.0052410901 | AY69: 08/28/2022 | AZ69: 3924.26 | BA69: =AZ69/AZ70-1 -> -0.032876091
C70: 08/21/2022 | D70: 175.04 | E70: =D70/D71-1 -> -0.028473109 | G70: 08/21/2022 | H70: 63.11 | I70: =H70/H71-1 -> -0.031609636 | K70: 08/21/2022 | L70: 38.62 | M70: =L70/L71-1 -> -0.033533534 | O70: 08/21/2022 | P70: 44.58 | Q70: =P70/P71-1 -> -0.01589404 | S70: 08/21/2022 | T70: 51.08 | U70: =T70/T71-1 -> 0.00019580967 | W70: 08/21/2022 | X70: 73.85 | Y70: =X70/X71-1 -> -0.03678101 | AA70: 08/21/2022 | AB70: 38.11 | AC70: =AB70/AB71-1 -> -0.010900597 | AE70: 08/21/2022 | AF70: 62.73 | AG70: =AF70/AF71-1 -> -0.040238678 | AI70: 08/21/2022 | AJ70: 228.67 | AK70: =AJ70/AJ71-1 -> -0.019341281 | AM70: 08/21/2022 | AN70: 50.69 | AO70: =AN70/AN71-1 -> -0.012083415 | AQ70: 08/21/2022 | AR70: 251.9 | AS70: =AR70/AR71-1 -> 0.00083435973 | AU70: 08/21/2022 | AV70: 76.32 | AW70: =AV70/AV71-1 -> -0.021161985 | AY70: 08/21/2022 | AZ70: 4057.66 | BA70: =AZ70/AZ71-1 -> -0.040397495
C71: 08/14/2022 | D71: 180.17 | E71: =D71/D72-1 -> 0.016015339 | G71: 08/14/2022 | H71: 65.17 | I71: =H71/H72-1 -> 0.023076923 | K71: 08/14/2022 | L71: 39.96 | M71: =L71/L72-1 -> 0.016793893 | O71: 08/14/2022 | P71: 45.3 | Q71: =P71/P72-1 -> 0.0064430127 | S71: 08/14/2022 | T71: 51.07 | U71: =T71/T72-1 -> 0.02426795 | W71: 08/14/2022 | X71: 76.67 | Y71: =X71/X72-1 -> 0.013885216 | AA71: 08/14/2022 | AB71: 38.53 | AC71: =AB71/AB72-1 -> -0.0036203776 | AE71: 08/14/2022 | AF71: 65.36 | AG71: =AF71/AF72-1 -> 0.018068536 | AI71: 08/14/2022 | AJ71: 233.18 | AK71: =AJ71/AJ72-1 -> 0.032866761 | AM71: 08/14/2022 | AN71: 51.31 | AO71: =AN71/AN72-1 -> 0.02743292 | AQ71: 08/14/2022 | AR71: 251.69 | AS71: =AR71/AR72-1 -> 0.03265909 | AU71: 08/14/2022 | AV71: 77.97 | AW71: =AV71/AV72-1 -> 0.012597403 | AY71: 08/14/2022 | AZ71: 4228.48 | BA71: =AZ71/AZ72-1 -> -0.012072007
C72: 44750 | D72: 177.33 | E72: =D72/D73-1 -> 0.015926669 | G72: 44750 | H72: 63.7 | I72: =H72/H73-1 -> 0.0050489113 | K72: 44750 | L72: 39.3 | M72: =L72/L73-1 -> 0.014979339 | O72: 44750 | P72: 45.01 | Q72: =P72/P73-1 -> -0.014882907 | S72: 44750 | T72: 49.86 | U72: =T72/T73-1 -> 0.019423431 | W72: 44750 | X72: 75.62 | Y72: =X72/X73-1 -> 0.0077292111 | AA72: 44750 | AB72: 38.67 | AC72: =AB72/AB73-1 -> 0.02927868 | AE72: 44750 | AF72: 64.2 | AG72: =AF72/AF73-1 -> 0.0067429826 | AI72: 44750 | AJ72: 225.76 | AK72: =AJ72/AJ73-1 -> -0.0059442561 | AM72: 44750 | AN72: 49.94 | AO72: =AN72/AN73-1 -> 0.010522056 | AQ72: 44750 | AR72: 243.73 | AS72: =AR72/AR73-1 -> -0.0025781634 | AU72: 44750 | AV72: 77 | AW72: =AV72/AV73-1 -> 0.010896678 | AY72: 44750 | AZ72: 4280.15 | BA72: =AZ72/AZ73-1 -> 0.032558218
C73: 07/31/2022 | D73: 174.55 | E73: =D73/D74-1 -> -0.0023433928 | G73: 07/31/2022 | H73: 63.38 | I73: =H73/H74-1 -> -0.012311049 | K73: 07/31/2022 | L73: 38.72 | M73: =L73/L74-1 -> -0.00051626226 | O73: 07/31/2022 | P73: 45.69 | Q73: =P73/P74-1 -> -0.082714314 | S73: 07/31/2022 | T73: 48.91 | U73: =T73/T74-1 -> -0.0087150385 | W73: 07/31/2022 | X73: 75.04 | Y73: =X73/X74-1 -> 0.015151515 | AA73: 07/31/2022 | AB73: 37.57 | AC73: =AB73/AB74-1 -> 0.020092316 | AE73: 07/31/2022 | AF73: 63.77 | AG73: =AF73/AF74-1 -> -0.0042161149 | AI73: 07/31/2022 | AJ73: 227.11 | AK73: =AJ73/AJ74-1 -> -0.0037287243 | AM73: 07/31/2022 | AN73: 49.42 | AO73: =AN73/AN74-1 -> 0.0014184397 | AQ73: 07/31/2022 | AR73: 244.36 | AS73: =AR73/AR74-1 -> -0.0079168527 | AU73: 07/31/2022 | AV73: 76.17 | AW73: =AV73/AV74-1 -> 0.018451665 | AY73: 07/31/2022 | AZ73: 4145.19 | BA73: =AZ73/AZ74-1 -> 0.0036074949
C74: 07/24/2022 | D74: 174.96 | E74: =D74/D75-1 -> 0.031542951 | G74: 07/24/2022 | H74: 64.17 | I74: =H74/H75-1 -> 0.041889917 | K74: 07/24/2022 | L74: 38.74 | M74: =L74/L75-1 -> 0.063409278 | O74: 07/24/2022 | P74: 49.81 | Q74: =P74/P75-1 -> 0.047969703 | S74: 07/24/2022 | T74: 49.34 | U74: =T74/T75-1 -> 0.036772431 | W74: 07/24/2022 | X74: 73.92 | Y74: =X74/X75-1 -> 0.039077875 | AA74: 07/24/2022 | AB74: 36.83 | AC74: =AB74/AB75-1 -> -0.03888309 | AE74: 07/24/2022 | AF74: 64.04 | AG74: =AF74/AF75-1 -> 0.03306985 | AI74: 07/24/2022 | AJ74: 227.96 | AK74: =AJ74/AJ75-1 -> 0.055761393 | AM74: 07/24/2022 | AN74: 49.35 | AO74: =AN74/AN75-1 -> 0.031347962 | AQ74: 07/24/2022 | AR74: 246.31 | AS74: =AR74/AR75-1 -> 0.016214209 | AU74: 07/24/2022 | AV74: 74.79 | AW74: =AV74/AV75-1 -> 0.015754448 | AY74: 07/24/2022 | AZ74: 4130.29 | BA74: =AZ74/AZ75-1 -> 0.042573385
C75: 07/17/2022 | D75: 169.61 | E75: =D75/D76-1 -> -0.0088242169 | G75: 07/17/2022 | H75: 61.59 | I75: =H75/H76-1 -> -0.01456 | K75: 07/17/2022 | L75: 36.43 | M75: =L75/L76-1 -> -0.0054600055 | O75: 07/17/2022 | P75: 47.53 | Q75: =P75/P76-1 -> -0.021613833 | S75: 07/17/2022 | T75: 47.59 | U75: =T75/T76-1 -> -0.0041849759 | W75: 07/17/2022 | X75: 71.14 | Y75: =X75/X76-1 -> -0.018081435 | AA75: 07/17/2022 | AB75: 38.32 | AC75: =AB75/AB76-1 -> 0.0081557485 | AE75: 07/17/2022 | AF75: 61.99 | AG75: =AF75/AF76-1 -> 0.020579519 | AI75: 07/17/2022 | AJ75: 215.92 | AK75: =AJ75/AJ76-1 -> -0.0040590406 | AM75: 07/17/2022 | AN75: 47.85 | AO75: =AN75/AN76-1 -> -0.018058691 | AQ75: 07/17/2022 | AR75: 242.38 | AS75: =AR75/AR76-1 -> -0.0088329108 | AU75: 07/17/2022 | AV75: 73.63 | AW75: =AV75/AV76-1 -> -0.017218366 | AY75: 07/17/2022 | AZ75: 3961.63 | BA75: =AZ75/AZ76-1 -> 0.025489496
C76: 44841 | D76: 171.12 | E76: =D76/D77-1 -> -0.0044216896 | G76: 44841 | H76: 62.5 | I76: =H76/H77-1 -> -0.010136205 | K76: 44841 | L76: 36.63 | M76: =L76/L77-1 -> 0.011878453 | O76: 44841 | P76: 48.58 | Q76: =P76/P77-1 -> -0.0032827247 | S76: 44841 | T76: 47.79 | U76: =T76/T77-1 -> 0.0050473186 | W76: 44841 | X76: 72.45 | Y76: =X76/X77-1 -> -0.00096525097 | AA76: 44841 | AB76: 38.01 | AC76: =AB76/AB77-1 -> -0.0093823299 | AE76: 44841 | AF76: 60.74 | AG76: =AF76/AF77-1 -> -0.027226137 | AI76: 44841 | AJ76: 216.8 | AK76: =AJ76/AJ77-1 -> -0.013603895 | AM76: 44841 | AN76: 48.73 | AO76: =AN76/AN77-1 -> 0.0030876904 | AQ76: 44841 | AR76: 244.54 | AS76: =AR76/AR77-1 -> 0.0097865136 | AU76: 44841 | AV76: 74.92 | AW76: =AV76/AV77-1 -> -0.0082075721 | AY76: 44841 | AZ76: 3863.16 | BA76: =AZ76/AZ77-1 -> -0.0092886561
C77: 44627 | D77: 171.88 | E77: =D77/D78-1 -> 0.014699805 | G77: 44627 | H77: 63.14 | I77: =H77/H78-1 -> -0.01926064 | K77: 44627 | L77: 36.2 | M77: =L77/L78-1 -> 0.0036041031 | O77: 44627 | P77: 48.74 | Q77: =P77/P78-1 -> 0.030443975 | S77: 44627 | T77: 47.55 | U77: =T77/T78-1 -> -0.0035624476 | W77: 44627 | X77: 72.52 | Y77: =X77/X78-1 -> 0.010309278 | AA77: 44627 | AB77: 38.37 | AC77: =AB77/AB78-1 -> -0.0069875776 | AE77: 44627 | AF77: 62.44 | AG77: =AF77/AF78-1 -> -0.014209031 | AI77: 44627 | AJ77: 219.79 | AK77: =AJ77/AJ78-1 -> -0.0054751131 | AM77: 44627 | AN77: 48.58 | AO77: =AN77/AN78-1 -> 0.0018560528 | AQ77: 44627 | AR77: 242.17 | AS77: =AR77/AR78-1 -> 0.028628467 | AU77: 44627 | AV77: 75.54 | AW77: =AV77/AV78-1 -> -0.0032985882 | AY77: 44627 | AZ77: 3899.38 | BA77: =AZ77/AZ78-1 -> 0.019357807
C78: 06/26/2022 | D78: 169.39 | E78: =D78/D79-1 -> 0.019623187 | G78: 06/26/2022 | H78: 64.38 | I78: =H78/H79-1 -> 0.021256345 | K78: 06/26/2022 | L78: 36.07 | M78: =L78/L79-1 -> 0.0086689038 | O78: 06/26/2022 | P78: 47.3 | Q78: =P78/P79-1 -> 0.0002114612 | S78: 06/26/2022 | T78: 47.72 | U78: =T78/T79-1 -> 0.0073886426 | W78: 06/26/2022 | X78: 71.78 | Y78: =X78/X79-1 -> 0.014988688 | AA78: 06/26/2022 | AB78: 38.64 | AC78: =AB78/AB79-1 -> 0.00625 | AE78: 06/26/2022 | AF78: 63.34 | AG78: =AF78/AF79-1 -> 0.011013567 | AI78: 06/26/2022 | AJ78: 221 | AK78: =AJ78/AJ79-1 -> 0.00018102824 | AM78: 06/26/2022 | AN78: 48.49 | AO78: =AN78/AN79-1 -> 0.0010322048 | AQ78: 06/26/2022 | AR78: 235.43 | AS78: =AR78/AR79-1 -> -0.04101833 | AU78: 06/26/2022 | AV78: 75.79 | AW78: =AV78/AV79-1 -> 0.073056775 | AY78: 06/26/2022 | AZ78: 3825.33 | BA78: =AZ78/AZ79-1 -> -0.022089914
C79: 06/19/2022 | D79: 166.13 | E79: =D79/D80-1 -> 0.057748631 | G79: 06/19/2022 | H79: 63.04 | I79: =H79/H80-1 -> 0.060743732 | K79: 06/19/2022 | L79: 35.76 | M79: =L79/L80-1 -> 0.041048035 | O79: 06/19/2022 | P79: 47.29 | Q79: =P79/P80-1 -> 0.073309124 | S79: 06/19/2022 | T79: 47.37 | U79: =T79/T80-1 -> 0.059968673 | W79: 06/19/2022 | X79: 70.72 | Y79: =X79/X80-1 -> 0.04708321 | AA79: 06/19/2022 | AB79: 38.4 | AC79: =AB79/AB80-1 -> 0.07925801 | AE79: 06/19/2022 | AF79: 62.65 | AG79: =AF79/AF80-1 -> 0.06547619 | AI79: 06/19/2022 | AJ79: 220.96 | AK79: =AJ79/AJ80-1 -> 0.072465175 | AM79: 06/19/2022 | AN79: 48.44 | AO79: =AN79/AN80-1 -> 0.067195417 | AQ79: 06/19/2022 | AR79: 245.5 | AS79: =AR79/AR80-1 -> 0.078173035 | AU79: 06/19/2022 | AV79: 70.63 | AW79: =AV79/AV80-1 -> 0.06643515 | AY79: 06/19/2022 | AZ79: 3911.74 | BA79: =AZ79/AZ80-1 -> 0.064465392
C80: 44901 | D80: 157.06 | E80: =D80/D81-1 -> -0.033595865 | G80: 44901 | H80: 59.43 | I80: =H80/H81-1 -> -0.032242306 | K80: 44901 | L80: 34.35 | M80: =L80/L81-1 -> -0.032121724 | O80: 44901 | P80: 44.06 | Q80: =P80/P81-1 -> 0.012408088 | S80: 44901 | T80: 44.69 | U80: =T80/T81-1 -> -0.02508726 | W80: 44901 | X80: 67.54 | Y80: =X80/X81-1 -> -0.02931877 | AA80: 44901 | AB80: 35.58 | AC80: =AB80/AB81-1 -> -0.049933244 | AE80: 44901 | AF80: 58.8 | AG80: =AF80/AF81-1 -> -0.032894737 | AI80: 44901 | AJ80: 206.03 | AK80: =AJ80/AJ81-1 -> -0.03430982 | AM80: 44901 | AN80: 45.39 | AO80: =AN80/AN81-1 -> -0.032814831 | AQ80: 44901 | AR80: 227.7 | AS80: =AR80/AR81-1 -> -0.047638964 | AU80: 44901 | AV80: 66.23 | AW80: =AV80/AV81-1 -> -0.031441942 | AY80: 44901 | AZ80: 3674.84 | BA80: =AZ80/AZ81-1 -> -0.057941069
C81: 44687 | D81: 162.52 | E81: =D81/D82-1 -> -0.014134061 | G81: 44687 | H81: 61.41 | I81: =H81/H82-1 -> -0.024773702 | K81: 44687 | L81: 35.49 | M81: =L81/L82-1 -> 0.016032064 | O81: 44687 | P81: 43.52 | Q81: =P81/P82-1 -> -0.020040531 | S81: 44687 | T81: 45.84 | U81: =T81/T82-1 -> 0.015957447 | W81: 44687 | X81: 69.58 | Y81: =X81/X82-1 -> 0.026859504 | AA81: 44687 | AB81: 37.45 | AC81: =AB81/AB82-1 -> 0.031680441 | AE81: 44687 | AF81: 60.8 | AG81: =AF81/AF82-1 -> -0.025797148 | AI81: 44687 | AJ81: 213.35 | AK81: =AJ81/AJ82-1 -> 0.019934984 | AM81: 44687 | AN81: 46.93 | AO81: =AN81/AN82-1 -> 0.02624098 | AQ81: 44687 | AR81: 239.09 | AS81: =AR81/AR82-1 -> -0.017424896 | AU81: 44687 | AV81: 68.38 | AW81: =AV81/AV82-1 -> -0.00014622021 | AY81: 44687 | AZ81: 3900.86 | BA81: =AZ81/AZ82-1 -> -0.05054837
C82: 05/29/2022 | D82: 164.85 | E82: =D82/D83-1 -> -0.04028643 | G82: 05/29/2022 | H82: 62.97 | I82: =H82/H83-1 -> -0.026437848 | K82: 05/29/2022 | L82: 34.93 | M82: =L82/L83-1 -> -0.0071063104 | O82: 05/29/2022 | P82: 44.41 | Q82: =P82/P83-1 -> -0.0095896521 | S82: 05/29/2022 | T82: 45.12 | U82: =T82/T83-1 -> -0.072177668 | W82: 05/29/2022 | X82: 67.76 | Y82: =X82/X83-1 -> -0.02936542 | AA82: 05/29/2022 | AB82: 36.3 | AC82: =AB82/AB83-1 -> -0.040444092 | AE82: 05/29/2022 | AF82: 62.41 | AG82: =AF82/AF83-1 -> -0.021173149 | AI82: 05/29/2022 | AJ82: 209.18 | AK82: =AJ82/AJ83-1 -> -0.016132825 | AM82: 05/29/2022 | AN82: 45.73 | AO82: =AN82/AN83-1 -> -0.05144161 | AQ82: 05/29/2022 | AR82: 243.33 | AS82: =AR82/AR83-1 -> -0.012098575 | AU82: 05/29/2022 | AV82: 68.39 | AW82: =AV82/AV83-1 -> -0.021462298 | AY82: 05/29/2022 | AZ82: 4108.54 | BA82: =AZ82/AZ83-1 -> -0.011952172
C83: 05/22/2022 | D83: 171.77 | E83: =D83/D84-1 -> 0.058935947 | G83: 05/22/2022 | H83: 64.68 | I83: =H83/H84-1 -> 0.060675631 | K83: 05/22/2022 | L83: 35.18 | M83: =L83/L84-1 -> 0.01735107 | O83: 05/22/2022 | P83: 44.84 | Q83: =P83/P84-1 -> 0.023510614 | S83: 05/22/2022 | T83: 48.63 | U83: =T83/T84-1 -> 0.0076668048 | W83: 05/22/2022 | X83: 69.81 | Y83: =X83/X84-1 -> 0.030558016 | AA83: 05/22/2022 | AB83: 37.83 | AC83: =AB83/AB84-1 -> -0.014073495 | AE83: 05/22/2022 | AF83: 63.76 | AG83: =AF83/AF84-1 -> 0.042000327 | AI83: 05/22/2022 | AJ83: 212.61 | AK83: =AJ83/AJ84-1 -> 0.027200696 | AM83: 05/22/2022 | AN83: 48.21 | AO83: =AN83/AN84-1 -> 0.047360417 | AQ83: 05/22/2022 | AR83: 246.31 | AS83: =AR83/AR84-1 -> 0.050362473 | AU83: 05/22/2022 | AV83: 69.89 | AW83: =AV83/AV84-1 -> 0.04297866 | AY83: 05/22/2022 | AZ83: 4158.24 | BA83: =AZ83/AZ84-1 -> 0.065843706
C84: 05/15/2022 | D84: 162.21 | E84: =D84/D85-1 -> -0.066256044 | G84: 05/15/2022 | H84: 60.98 | I84: =H84/H85-1 -> -0.072124163 | K84: 05/15/2022 | L84: 34.58 | M84: =L84/L85-1 -> -0.070679925 | O84: 05/15/2022 | P84: 43.81 | Q84: =P84/P85-1 -> -0.0143982 | S84: 05/15/2022 | T84: 48.26 | U84: =T84/T85-1 -> -0.093027626 | W84: 05/15/2022 | X84: 67.74 | Y84: =X84/X85-1 -> -0.072181893 | AA84: 05/15/2022 | AB84: 38.37 | AC84: =AB84/AB85-1 -> -0.13366448 | AE84: 05/15/2022 | AF84: 61.19 | AG84: =AF84/AF85-1 -> -0.078186201 | AI84: 05/15/2022 | AJ84: 206.98 | AK84: =AJ84/AJ85-1 -> -0.083794431 | AM84: 05/15/2022 | AN84: 46.03 | AO84: =AN84/AN85-1 -> -0.089416419 | AQ84: 05/15/2022 | AR84: 234.5 | AS84: =AR84/AR85-1 -> -0.057930259 | AU84: 05/15/2022 | AV84: 67.01 | AW84: =AV84/AV85-1 -> -0.083310534 | AY84: 05/15/2022 | AZ84: 3901.36 | BA84: =AZ84/AZ85-1 -> -0.030450634
C85: 44778 | D85: 173.72 | E85: =D85/D86-1 -> 0.019423743 | G85: 44778 | H85: 65.72 | I85: =H85/H86-1 -> 0.015137473 | K85: 44778 | L85: 37.21 | M85: =L85/L86-1 -> 0.0067640693 | O85: 44778 | P85: 44.45 | Q85: =P85/P86-1 -> 0.025611444 | S85: 44778 | T85: 53.21 | U85: =T85/T86-1 -> 0.023072486 | W85: 44778 | X85: 73.01 | Y85: =X85/X86-1 -> 0.0038498556 | AA85: 44778 | AB85: 44.29 | AC85: =AB85/AB86-1 -> 0.016058729 | AE85: 44778 | AF85: 66.38 | AG85: =AF85/AF86-1 -> 0.0098889396 | AI85: 44778 | AJ85: 225.91 | AK85: =AJ85/AJ86-1 -> -0.00061933201 | AM85: 44778 | AN85: 50.55 | AO85: =AN85/AN86-1 -> 0.017716932 | AQ85: 44778 | AR85: 248.92 | AS85: =AR85/AR86-1 -> 0.0058592961 | AU85: 44778 | AV85: 73.1 | AW85: =AV85/AV86-1 -> 0.023809524 | AY85: 44778 | AZ85: 4023.89 | BA85: =AZ85/AZ86-1 -> -0.024118797
C86: 44566 | D86: 170.41 | E86: =D86/D87-1 -> -0.0075709044 | G86: 44566 | H86: 64.74 | I86: =H86/H87-1 -> 0.0020120724 | K86: 44566 | L86: 36.96 | M86: =L86/L87-1 -> -0.011764706 | O86: 44566 | P86: 43.34 | Q86: =P86/P87-1 -> 0.011671335 | S86: 44566 | T86: 52.01 | U86: =T86/T87-1 -> -0.0072532926 | W86: 44566 | X86: 72.73 | Y86: =X86/X87-1 -> 0.061751825 | AA86: 44566 | AB86: 43.59 | AC86: =AB86/AB87-1 -> 0.022519353 | AE86: 44566 | AF86: 65.73 | AG86: =AF86/AF87-1 -> 0.019385856 | AI86: 44566 | AJ86: 226.05 | AK86: =AJ86/AJ87-1 -> 0.0012402002 | AM86: 44566 | AN86: 49.67 | AO86: =AN86/AN87-1 -> 0.051884795 | AQ86: 44566 | AR86: 247.47 | AS86: =AR86/AR87-1 -> 0.0056077045 | AU86: 44566 | AV86: 71.4 | AW86: =AV86/AV87-1 -> 0.0094726424 | AY86: 44566 | AZ86: 4123.34 | BA86: =AZ86/AZ87-1 -> -0.0020789316
C87: 04/24/2022 | D87: 171.71 | E87: =D87/D88-1 -> -0.0025559105 | G87: 04/24/2022 | H87: 64.61 | I87: =H87/H88-1 -> -0.0098084291 | K87: 04/24/2022 | L87: 37.4 | M87: =L87/L88-1 -> 0.010810811 | O87: 04/24/2022 | P87: 42.84 | Q87: =P87/P88-1 -> 0.0002334812 | S87: 04/24/2022 | T87: 52.39 | U87: =T87/T88-1 -> -0.02220978 | W87: 04/24/2022 | X87: 68.5 | Y87: =X87/X88-1 -> -0.011971729 | AA87: 04/24/2022 | AB87: 42.63 | AC87: =AB87/AB88-1 -> -0.012737378 | AE87: 04/24/2022 | AF87: 64.48 | AG87: =AF87/AF88-1 -> -0.0089148478 | AI87: 04/24/2022 | AJ87: 225.77 | AK87: =AJ87/AJ88-1 -> 0.0072722406 | AM87: 04/24/2022 | AN87: 47.22 | AO87: =AN87/AN88-1 -> 0.0059650618 | AQ87: 04/24/2022 | AR87: 246.09 | AS87: =AR87/AR88-1 -> -0.019405483 | AU87: 04/24/2022 | AV87: 70.73 | AW87: =AV87/AV88-1 -> -0.024413793 | AY87: 04/24/2022 | AZ87: 4131.93 | BA87: =AZ87/AZ88-1 -> -0.032738109
C88: 04/17/2022 | D88: 172.15 | E88: =D88/D89-1 -> 0.0014543339 | G88: 04/17/2022 | H88: 65.25 | I88: =H88/H89-1 -> 0.0035373731 | K88: 04/17/2022 | L88: 37 | M88: =L88/L89-1 -> -0.0064446831 | O88: 04/17/2022 | P88: 42.83 | Q88: =P88/P89-1 -> 0.037046005 | S88: 04/17/2022 | T88: 53.58 | U88: =T88/T89-1 -> 0.0028074116 | W88: 04/17/2022 | X88: 69.33 | Y88: =X88/X89-1 -> 0.021361226 | AA88: 04/17/2022 | AB88: 43.18 | AC88: =AB88/AB89-1 -> 0.021045164 | AE88: 04/17/2022 | AF88: 65.06 | AG88: =AF88/AF89-1 -> 0.021029504 | AI88: 04/17/2022 | AJ88: 224.14 | AK88: =AJ88/AJ89-1 -> -0.0081423135 | AM88: 04/17/2022 | AN88: 46.94 | AO88: =AN88/AN89-1 -> 0.016017316 | AQ88: 04/17/2022 | AR88: 250.96 | AS88: =AR88/AR89-1 -> -0.0018296078 | AU88: 04/17/2022 | AV88: 72.5 | AW88: =AV88/AV89-1 -> 0.022278624 | AY88: 04/17/2022 | AZ88: 4271.78 | BA88: =AZ88/AZ89-1 -> -0.027503136
C89: 44838 | D89: 171.9 | E89: =D89/D90-1 -> -0.007104488 | G89: 44838 | H89: 65.02 | I89: =H89/H90-1 -> 0.018643271 | K89: 44838 | L89: 37.24 | M89: =L89/L90-1 -> -0.010889774 | O89: 44838 | P89: 41.3 | Q89: =P89/P90-1 -> 0.012006861 | S89: 44838 | T89: 53.43 | U89: =T89/T90-1 -> 0.013659647 | W89: 44838 | X89: 67.88 | Y89: =X89/X90-1 -> 0.0047365305 | AA89: 44838 | AB89: 42.29 | AC89: =AB89/AB90-1 -> 0.032975085 | AE89: 44838 | AF89: 63.72 | AG89: =AF89/AF90-1 -> 0.0050473186 | AI89: 44838 | AJ89: 225.98 | AK89: =AJ89/AJ90-1 -> 0.010101913 | AM89: 44838 | AN89: 46.2 | AO89: =AN89/AN90-1 -> 0.016054541 | AQ89: 44838 | AR89: 251.42 | AS89: =AR89/AR90-1 -> 0.028470915 | AU89: 44838 | AV89: 70.92 | AW89: =AV89/AV90-1 -> 0.010688328 | AY89: 44838 | AZ89: 4392.59 | BA89: =AZ89/AZ90-1 -> -0.021319971
C90: 44624 | D90: 173.13 | E90: =D90/D91-1 -> 0.019851555 | G90: 44624 | H90: 63.83 | I90: =H90/H91-1 -> 0.015269604 | K90: 44624 | L90: 37.65 | M90: =L90/L91-1 -> -0.01542887 | O90: 44624 | P90: 40.81 | Q90: =P90/P91-1 -> -0.0065725414 | S90: 44624 | T90: 52.71 | U90: =T90/T91-1 -> 0.0055322396 | W90: 44624 | X90: 67.56 | Y90: =X90/X91-1 -> 0.029721079 | AA90: 44624 | AB90: 40.94 | AC90: =AB90/AB91-1 -> 0.025294265 | AE90: 44624 | AF90: 63.4 | AG90: =AF90/AF91-1 -> -0.0020462773 | AI90: 44624 | AJ90: 223.72 | AK90: =AJ90/AJ91-1 -> 0.022626503 | AM90: 44624 | AN90: 45.47 | AO90: =AN90/AN91-1 -> 0.0093229745 | AQ90: 44624 | AR90: 244.46 | AS90: =AR90/AR91-1 -> 0.045997176 | AU90: 44624 | AV90: 70.17 | AW90: =AV90/AV91-1 -> 0.019172113 | AY90: 44624 | AZ90: 4488.28 | BA90: =AZ90/AZ91-1 -> -0.01266647
C91: 03/27/2022 | D91: 169.76 | E91: =D91/D92-1 -> 0.027354152 | G91: 03/27/2022 | H91: 62.87 | I91: =H91/H92-1 -> 0.021777994 | K91: 03/27/2022 | L91: 38.24 | M91: =L91/L92-1 -> 0.017562533 | O91: 03/27/2022 | P91: 41.08 | Q91: =P91/P92-1 -> 0.043964422 | S91: 03/27/2022 | T91: 52.42 | U91: =T91/T92-1 -> 0.033925049 | W91: 03/27/2022 | X91: 65.61 | Y91: =X91/X92-1 -> 0.044412607 | AA91: 03/27/2022 | AB91: 39.93 | AC91: =AB91/AB92-1 -> 0.016289132 | AE91: 03/27/2022 | AF91: 63.53 | AG91: =AF91/AF92-1 -> 0.032672302 | AI91: 03/27/2022 | AJ91: 218.77 | AK91: =AJ91/AJ92-1 -> 0.02052526 | AM91: 03/27/2022 | AN91: 45.05 | AO91: =AN91/AN92-1 -> 0.011677521 | AQ91: 03/27/2022 | AR91: 233.71 | AS91: =AR91/AR92-1 -> 0.018743734 | AU91: 03/27/2022 | AV91: 68.85 | AW91: =AV91/AV92-1 -> 0.021664935 | AY91: 03/27/2022 | AZ91: 4545.86 | BA91: =AZ91/AZ92-1 -> 0.00062072973
C92: 03/20/2022 | D92: 165.24 | E92: =D92/D93-1 -> 0.015050065 | G92: 03/20/2022 | H92: 61.53 | I92: =H92/H93-1 -> 0.023793677 | K92: 03/20/2022 | L92: 37.58 | M92: =L92/L93-1 -> -0.0060830468 | O92: 03/20/2022 | P92: 39.35 | Q92: =P92/P93-1 -> -0.023573201 | S92: 03/20/2022 | T92: 50.7 | U92: =T92/T93-1 -> 0.029232643 | W92: 03/20/2022 | X92: 62.82 | Y92: =X92/X93-1 -> 0.033903884 | AA92: 03/20/2022 | AB92: 39.29 | AC92: =AB92/AB93-1 -> 0.044391281 | AE92: 03/20/2022 | AF92: 61.52 | AG92: =AF92/AF93-1 -> 0.00016257519 | AI92: 03/20/2022 | AJ92: 214.37 | AK92: =AJ92/AJ93-1 -> 0.036956417 | AM92: 03/20/2022 | AN92: 44.53 | AO92: =AN92/AN93-1 -> 0.049493283 | AQ92: 03/20/2022 | AR92: 229.41 | AS92: =AR92/AR93-1 -> 0.015403001 | AU92: 03/20/2022 | AV92: 67.39 | AW92: =AV92/AV93-1 -> 0.079794905 | AY92: 03/20/2022 | AZ92: 4543.04 | BA92: =AZ92/AZ93-1 -> 0.017913598
C93: 03/13/2022 | D93: 162.79 | E93: =D93/D94-1 -> 0.058934496 | G93: 03/13/2022 | H93: 60.1 | I93: =H93/H94-1 -> 0.037638122 | K93: 03/13/2022 | L93: 37.81 | M93: =L93/L94-1 -> 0.027166531 | O93: 03/13/2022 | P93: 40.3 | Q93: =P93/P94-1 -> 0.10079213 | S93: 03/13/2022 | T93: 49.26 | U93: =T93/T94-1 -> -0.024167987 | W93: 03/13/2022 | X93: 60.76 | Y93: =X93/X94-1 -> 0.015204678 | AA93: 03/13/2022 | AB93: 37.62 | AC93: =AB93/AB94-1 -> 0.0069593148 | AE93: 03/13/2022 | AF93: 61.51 | AG93: =AF93/AF94-1 -> 0.040426252 | AI93: 03/13/2022 | AJ93: 206.73 | AK93: =AJ93/AJ94-1 -> 0.0099662905 | AM93: 03/13/2022 | AN93: 42.43 | AO93: =AN93/AN94-1 -> 0.0061655205 | AQ93: 03/13/2022 | AR93: 225.93 | AS93: =AR93/AR94-1 -> 0.063750647 | AU93: 03/13/2022 | AV93: 62.41 | AW93: =AV93/AV94-1 -> 0.0022482736 | AY93: 03/13/2022 | AZ93: 4463.09 | BA93: =AZ93/AZ94-1 -> 0.061551123
C94: 44715 | D94: 153.73 | E94: =D94/D95-1 -> -0.072518854 | G94: 44715 | H94: 57.92 | I94: =H94/H95-1 -> -0.074316765 | K94: 44715 | L94: 36.81 | M94: =L94/L95-1 -> -0.053240741 | O94: 44715 | P94: 36.61 | Q94: =P94/P95-1 -> -0.099606493 | S94: 44715 | T94: 50.48 | U94: =T94/T95-1 -> -0.024163928 | W94: 44715 | X94: 59.85 | Y94: =X94/X95-1 -> -0.07852194 | AA94: 44715 | AB94: 37.36 | AC94: =AB94/AB95-1 -> -0.062248996 | AE94: 44715 | AF94: 59.12 | AG94: =AF94/AF95-1 -> -0.073789754 | AI94: 44715 | AJ94: 204.69 | AK94: =AJ94/AJ95-1 -> -0.038201297 | AM94: 44715 | AN94: 42.17 | AO94: =AN94/AN95-1 -> -0.074204171 | AQ94: 44715 | AR94: 212.39 | AS94: =AR94/AR95-1 -> -0.024212074 | AU94: 44715 | AV94: 62.27 | AW94: =AV94/AV95-1 -> -0.085877863 | AY94: 44715 | AZ94: 4204.31 | BA94: =AZ94/AZ95-1 -> -0.028774253
C95: 02/27/2022 | D95: 165.75 | E95: =D95/D96-1 -> -0.015619432 | G95: 02/27/2022 | H95: 62.57 | I95: =H95/H96-1 -> -0.0044550517 | K95: 02/27/2022 | L95: 38.88 | M95: =L95/L96-1 -> 0.015143603 | O95: 02/27/2022 | P95: 40.66 | Q95: =P95/P96-1 -> -0.038315989 | S95: 02/27/2022 | T95: 51.73 | U95: =T95/T96-1 -> 0.067478333 | W95: 02/27/2022 | X95: 64.95 | Y95: =X95/X96-1 -> -0.011114495 | AA95: 02/27/2022 | AB95: 39.84 | AC95: =AB95/AB96-1 -> 0.0027686886 | AE95: 02/27/2022 | AF95: 63.83 | AG95: =AF95/AF96-1 -> -0.043888556 | AI95: 02/27/2022 | AJ95: 212.82 | AK95: =AJ95/AJ96-1 -> 0.04160141 | AM95: 02/27/2022 | AN95: 45.55 | AO95: =AN95/AN96-1 -> 0.0079663642 | AQ95: 02/27/2022 | AR95: 217.66 | AS95: =AR95/AR96-1 -> 0.0028566163 | AU95: 02/27/2022 | AV95: 68.12 | AW95: =AV95/AV96-1 -> 0.0019120459 | AY95: 02/27/2022 | AZ95: 4328.87 | BA95: =AZ95/AZ96-1 -> -0.012714899
C96: 02/20/2022 | D96: 168.38 | E96: =D96/D97-1 -> 0.0039949914 | G96: 02/20/2022 | H96: 62.85 | I96: =H96/H97-1 -> 0.0049568276 | K96: 02/20/2022 | L96: 38.3 | M96: =L96/L97-1 -> -0.0046777547 | O96: 02/20/2022 | P96: 42.28 | Q96: =P96/P97-1 -> 0.040610386 | S96: 02/20/2022 | T96: 48.46 | U96: =T96/T97-1 -> 0.021285564 | W96: 02/20/2022 | X96: 65.68 | Y96: =X96/X97-1 -> -0.0059028303 | AA96: 02/20/2022 | AB96: 39.73 | AC96: =AB96/AB97-1 -> 0.033021321 | AE96: 02/20/2022 | AF96: 66.76 | AG96: =AF96/AF97-1 -> 0.011515152 | AI96: 02/20/2022 | AJ96: 204.32 | AK96: =AJ96/AJ97-1 -> 0.0085394146 | AM96: 02/20/2022 | AN96: 45.19 | AO96: =AN96/AN97-1 -> 0.0053392659 | AQ96: 02/20/2022 | AR96: 217.04 | AS96: =AR96/AR97-1 -> 0.0055130878 | AU96: 02/20/2022 | AV96: 67.99 | AW96: =AV96/AV97-1 -> -0.0023477623 | AY96: 02/20/2022 | AZ96: 4384.62 | BA96: =AZ96/AZ97-1 -> 0.0082205263
C97: 02/13/2022 | D97: 167.71 | E97: =D97/D98-1 -> -0.0051607545 | G97: 02/13/2022 | H97: 62.54 | I97: =H97/H98-1 -> 0.037319622 | K97: 02/13/2022 | L97: 38.48 | M97: =L97/L98-1 -> 0.011832764 | O97: 02/13/2022 | P97: 40.63 | Q97: =P97/P98-1 -> -0.018599034 | S97: 02/13/2022 | T97: 47.45 | U97: =T97/T98-1 -> -0.0098080134 | W97: 02/13/2022 | X97: 66.07 | Y97: =X97/X98-1 -> 0.03476899 | AA97: 02/13/2022 | AB97: 38.46 | AC97: =AB97/AB98-1 -> 0.10739994 | AE97: 02/13/2022 | AF97: 66 | AG97: =AF97/AF98-1 -> -0.010494753 | AI97: 02/13/2022 | AJ97: 202.59 | AK97: =AJ97/AJ98-1 -> -0.012671183 | AM97: 02/13/2022 | AN97: 44.95 | AO97: =AN97/AN98-1 -> 0.018120045 | AQ97: 02/13/2022 | AR97: 215.85 | AS97: =AR97/AR98-1 -> -0.085148767 | AU97: 02/13/2022 | AV97: 68.15 | AW97: =AV97/AV98-1 -> 0.0013223626 | AY97: 02/13/2022 | AZ97: 4348.87 | BA97: =AZ97/AZ98-1 -> -0.015789926
C98: 44714 | D98: 168.58 | E98: =D98/D99-1 -> -0.022667981 | G98: 44714 | H98: 60.29 | I98: =H98/H99-1 -> -0.010990814 | K98: 44714 | L98: 38.03 | M98: =L98/L99-1 -> -0.0054916318 | O98: 44714 | P98: 41.4 | Q98: =P98/P99-1 -> -0.017793594 | S98: 44714 | T98: 47.92 | U98: =T98/T99-1 -> 0.020008514 | W98: 44714 | X98: 63.85 | Y98: =X98/X99-1 -> 0.036862618 | AA98: 44714 | AB98: 34.73 | AC98: =AB98/AB99-1 -> -0.00057553957 | AE98: 44714 | AF98: 66.7 | AG98: =AF98/AF99-1 -> -0.0047746941 | AI98: 44714 | AJ98: 205.19 | AK98: =AJ98/AJ99-1 -> 0.011884801 | AM98: 44714 | AN98: 44.15 | AO98: =AN98/AN99-1 -> 0.024599675 | AQ98: 44714 | AR98: 235.94 | AS98: =AR98/AR99-1 -> -0.0058568238 | AU98: 44714 | AV98: 68.06 | AW98: =AV98/AV99-1 -> 0.0020612485 | AY98: 44714 | AZ98: 4418.64 | BA98: =AZ98/AZ99-1 -> -0.018197816
C99: 01/30/2022 | D99: 172.49 | E99: =D99/D100-1 -> -0.0010424509 | G99: 01/30/2022 | H99: 60.96 | I99: =H99/H100-1 -> 0.0019723866 | K99: 01/30/2022 | L99: 38.24 | M99: =L99/L100-1 -> 0.015940489 | O99: 01/30/2022 | P99: 42.15 | Q99: =P99/P100-1 -> -0.011954993 | S99: 01/30/2022 | T99: 46.98 | U99: =T99/T100-1 -> -0.0052932458 | W99: 01/30/2022 | X99: 61.58 | Y99: =X99/X100-1 -> -0.056389825 | AA99: 01/30/2022 | AB99: 34.75 | AC99: =AB99/AB100-1 -> -0.036061026 | AE99: 01/30/2022 | AF99: 67.02 | AG99: =AF99/AF100-1 -> 0.0090334237 | AI99: 01/30/2022 | AJ99: 202.78 | AK99: =AJ99/AJ100-1 -> 0.030229132 | AM99: 01/30/2022 | AN99: 43.09 | AO99: =AN99/AN100-1 -> -0.025554048 | AQ99: 01/30/2022 | AR99: 237.33 | AS99: =AR99/AR100-1 -> 0.00542258 | AU99: 01/30/2022 | AV99: 67.92 | AW99: =AV99/AV100-1 -> -0.021043528 | AY99: 01/30/2022 | AZ99: 4500.54 | BA99: =AZ99/AZ100-1 -> 0.015499171
C100: 01/23/2022 | D100: 172.67 | E100: =D100/D101-1 -> -0.0088967972 | G100: 01/23/2022 | H100: 60.84 | I100: =H100/H101-1 -> 0.0064516129 | K100: 01/23/2022 | L100: 37.64 | M100: =L100/L101-1 -> -0.0050224689 | O100: 01/23/2022 | P100: 42.66 | Q100: =P100/P101-1 -> -0.0035038542 | S100: 01/23/2022 | T100: 47.23 | U100: =T100/T101-1 -> -0.038672909 | W100: 01/23/2022 | X100: 65.26 | Y100: =X100/X101-1 -> -0.020267227 | AA100: 01/23/2022 | AB100: 36.05 | AC100: =AB100/AB101-1 -> -0.025675676 | AE100: 01/23/2022 | AF100: 66.42 | AG100: =AF100/AF101-1 -> -0.028379169 | AI100: 01/23/2022 | AJ100: 196.83 | AK100: =AJ100/AJ101-1 -> -0.017569254 | AM100: 01/23/2022 | AN100: 44.22 | AO100: =AN100/AN101-1 -> -0.02384106 | AQ100: 01/23/2022 | AR100: 236.05 | AS100: =AR100/AR101-1 -> -0.020580059 | AU100: 01/23/2022 | AV100: 69.38 | AW100: =AV100/AV101-1 -> 0.0050702593 | AY100: 01/23/2022 | AZ100: 4431.85 | BA100: =AZ100/AZ101-1 -> 0.0077127194
C101: 01/16/2022 | D101: 174.22 | E101: =D101/D102-1 -> -0.0080847187 | G101: 01/16/2022 | H101: 60.45 | I101: =H101/H102-1 -> -0.01531194 | K101: 01/16/2022 | L101: 37.83 | M101: =L101/L102-1 -> -0.03691446 | O101: 01/16/2022 | P101: 42.81 | Q101: =P101/P102-1 -> -0.047608454 | S101: 01/16/2022 | T101: 49.13 | U101: =T101/T102-1 -> 0.0010187449 | W101: 01/16/2022 | X101: 66.61 | Y101: =X101/X102-1 -> -0.013623575 | AA101: 01/16/2022 | AB101: 37 | AC101: =AB101/AB102-1 -> -0.026827985 | AE101: 01/16/2022 | AF101: 68.36 | AG101: =AF101/AF102-1 -> 0.0038179148 | AI101: 01/16/2022 | AJ101: 200.35 | AK101: =AJ101/AJ102-1 -> 0.0041096577 | AM101: 01/16/2022 | AN101: 45.3 | AO101: =AN101/AN102-1 -> -0.023285899 | AQ101: 01/16/2022 | AR101: 241.01 | AS101: =AR101/AR102-1 -> -0.030686937 | AU101: 01/16/2022 | AV101: 69.03 | AW101: =AV101/AV102-1 -> -0.012446352 | AY101: 01/16/2022 | AZ101: 4397.93 | BA101: =AZ101/AZ102-1 -> -0.056815038
...

Sheet Fixed Assets Schedule
A1: PepsiCo Inc.
A2: (in USD million except per Share Data)
A3: Property, Plant & Equipment | B3: 12 months | C3: 12 months | D3: 12 months | E3: 12 months | F3: 6 months | H3: 6 months | I3: 12 months | J3: 12 months | K3: 12 months | L3: 12 months
B4: Dec. 31, 2019 | C4: Dec. 31, 2020 | D4: Dec. 31, 2021 | E4: Dec. 31, 2022 | F4: Jun. 17, 2023 | H4: Dec. 31, 2023 | I4: Dec. 31, 2024 | J4: Dec. 31, 2025 | K4: Dec. 31, 2026 | L4: Dec. 31, 2027
A5: Opening Balance-WDV | B5: 17589 | C5: =B9 -> 19305 | D5: =C9 -> 21369 | E5: =D9 -> 22407 | F5: =E9 -> 24291 | H5: =F9 -> 24500 | I5: =H9 -> 29585.985 | J5: =I9 -> 30294.778 | K5: =J9 -> 32827.916 | L5: =K9 -> 35581.071
A6: Add: Net Addition during the Period | B6: =B7-B5 -> 4067 | C6: =C7-C5 -> 4522 | D6: =D7-D5 -> 3657 | E6: =E7-E5 -> 4569 | F6: =F7-F5 -> 1435.6514 | H6: =H7-H5 -> 6708.4559 | I6: =I7-I5 -> 4224.2602 | J6: =J7-J5 -> 6342.5553 | K6: =K7-K5 -> 6882.0533 | L6: =L7-L5 -> 7469.2155
A7: Total Depreciable Assets During the Year | B7: =B9+B8 -> 21656 | C7: =C9+C8 -> 23827 | D7: =D9+D8 -> 25026 | E7: =E9+E8 -> 26976 | F7: =F9+F8 -> 25726.651 | H7: ='PepsiCo-IS'!H6/'Fixed Assets Schedule'!H13 -> 31208.456 | I7: ='PepsiCo-IS'!I6/'Fixed Assets Schedule'!I13 -> 33810.245 | J7: ='PepsiCo-IS'!J6/'Fixed Assets Schedule'!J13 -> 36637.334 | K7: ='PepsiCo-IS'!K6/'Fixed Assets Schedule'!K13 -> 39709.97 | L7: ='PepsiCo-IS'!L6/'Fixed Assets Schedule'!L13 -> 43050.287
A8: Less: Depreciation during the year | B8: =B20 -> 2351 | C8: =C20 -> 2458 | D8: =D20 -> 2619 | E8: =E20 -> 2685 | F8: =F20 -> 1226.6514 | H8: =H7*H15/2 -> 1622.4711 | I8: =I7*I15 -> 3515.4667 | J8: =J7*J15 -> 3809.4171 | K8: =K7*K15 -> 4128.8987 | L8: =L7*L15 -> 4476.2127
A9: Closing Balance-WDV | B9: ='PepsiCo-BS'!B13 -> 19305 | C9: ='PepsiCo-BS'!C13 -> 21369 | D9: ='PepsiCo-BS'!D13 -> 22407 | E9: ='PepsiCo-BS'!E13 -> 24291 | F9: ='PepsiCo-BS'!F13 -> 24500 | H9: =H7-H8 -> 29585.985 | I9: =I7-I8 -> 30294.778 | J9: =J7-J8 -> 32827.916 | K9: =K7-K8 -> 35581.071 | L9: =L7-L8 -> 38574.074
A10: Source | H10: Calculation
A13: PPE Turnover Ratio | B13: ='PepsiCo-IS'!B6/'Fixed Assets Schedule'!B7 -> 3.1012652 | C13: ='PepsiCo-IS'!C6/'Fixed Assets Schedule'!C7 -> 2.9534562 | D13: ='PepsiCo-IS'!D6/'Fixed Assets Schedule'!D7 -> 3.1756573 | E13: ='PepsiCo-IS'!E6/'Fixed Assets Schedule'!E7 -> 3.2025504 | F13: ='PepsiCo-IS'!F6/'Fixed Assets Schedule'!F7 -> 1.5613381 | H13: =AVERAGE(B13:E13) -> 3.1082323 | I13: =H13 -> 3.1082323 | J13: =I13 -> 3.1082323 | K13: =J13 -> 3.1082323 | L13: =K13 -> 3.1082323
A15: Depreciation Rate | B15: =B8/B7 -> 0.10856114 | C15: =C8/C7 -> 0.10316028 | D15: =D8/D7 -> 0.10465116 | E15: =E8/E7 -> 0.099532918 | F15: =F8/F7 -> 0.047680181 | H15: =AVERAGE(B15:E15) -> 0.10397637 | I15: =H15 -> 0.10397637 | J15: =I15 -> 0.10397637 | K15: =J15 -> 0.10397637 | L15: =K15 -> 0.10397637
A18: Depreciation Exp | B18: ='PepsiCo-IS'!B11 -> 2196 | C18: ='PepsiCo-IS'!C11 -> 2331 | D18: ='PepsiCo-IS'!D11 -> 2496 | E18: ='PepsiCo-IS'!E11 -> 2564 | F18: ='PepsiCo-IS'!F11 -> 1162.3774 | G18: =AVERAGE(B21:F21) -> 0.947595 | H18: =$G$18*H20 -> 1537.4455 | I18: =$G$18*I20 -> 3331.2387 | J18: =$G$18*J20 -> 3609.7846 | K18: =$G$18*K20 -> 3912.5238 | L18: =$G$18*L20 -> 4241.6368
A19: Corporate Depreciation and Amort | B19: ='PepsiCo-IS'!B19 -> 155 | C19: ='PepsiCo-IS'!C19 -> 127 | D19: ='PepsiCo-IS'!D19 -> 123 | E19: ='PepsiCo-IS'!E19 -> 121 | F19: ='PepsiCo-IS'!F19 -> 64.273969 | H19: =H20-H18 -> 85.025593 | I19: =I20-I18 -> 184.22803 | J19: =J20-J18 -> 199.6325 | K19: =K20-K18 -> 216.37493 | L19: =L20-L18 -> 234.57592
B20: =B18+B19 -> 2351 | C20: =C18+C19 -> 2458 | D20: =D18+D19 -> 2619 | E20: =E18+E19 -> 2685 | F20: =F18+F19 -> 1226.6514 | H20: =H8 -> 1622.4711 | I20: =I8 -> 3515.4667 | J20: =J8 -> 3809.4171 | K20: =K8 -> 4128.8987 | L20: =L8 -> 4476.2127
B21: =B18/B20 -> 0.93407061 | C21: =C18/C20 -> 0.94833198 | D21: =D18/D20 -> 0.95303551 | E21: =E18/E20 -> 0.95493482 | F21: =F18/F20 -> 0.94760209
A22: Amortizable Intangible Assets, net | B22: 12 months | C22: 12 months | D22: 12 months | E22: 12 months | F22: 6 months | H22: 6 months | I22: 12 months | J22: 12 months | K22: 12 months | L22: 12 months
B23: Dec. 31, 2019 | C23: Dec. 31, 2020 | D23: Dec. 31, 2021 | E23: Dec. 31, 2022 | F23: Jun. 17, 2023 | H23: Dec. 31, 2023 | I23: Dec. 31, 2024 | J23: Dec. 31, 2025 | K23: Dec. 31, 2026 | L23: Dec. 31, 2027
A24: Opening Balance-WDV | C24: =B28 -> 1433 | D24: =C28 -> 1703 | E24: =D28 -> 1538 | F24: =E28 -> 1277 | H24: =F28 -> 1232 | I24: =H28 -> 1198.5631 | J24: =I28 -> 1133.5042 | K24: =J28 -> 1071.9767 | L24: =K28 -> 1013.7891
A25: Add: Net Addition during the Period | B25: =B26-B24 -> 1514 | C25: =C26-C24 -> 360 | D25: =D26-D24 -> -74 | E25: =E26-E24 -> -183 | F25: =F26-F24 -> -3.6513878 | H25: 0 | I25: 0 | J25: 0 | K25: 0 | L25: 0
A26: Total Amortizable Assets During the Year | B26: =B28+B27 -> 1514 | C26: =C28+C27 -> 1793 | D26: =D28+D27 -> 1629 | E26: =E28+E27 -> 1355 | F26: =F28+F27 -> 1273.3486 | H26: =H24+H25 -> 1232 | I26: =I24+I25 -> 1198.5631 | J26: =J24+J25 -> 1133.5042 | K26: =K24+K25 -> 1071.9767 | L26: =L24+L25 -> 1013.7891
A27: Less: Amortisation during the year | B27: ='PepsiCo-IS'!B20 -> 81 | C27: ='PepsiCo-IS'!C20 -> 90 | D27: ='PepsiCo-IS'!D20 -> 91 | E27: ='PepsiCo-IS'!E20 -> 78 | F27: ='PepsiCo-IS'!F20 -> 41.348612 | H27: =H26*H32/2 -> 33.436932 | I27: =I26*I32 -> 65.058882 | J27: =J26*J32 -> 61.527438 | K27: =K26*K32 -> 58.187684 | L27: =L26*L32 -> 55.029214
A28: Closing Balance-WDV | B28: ='PepsiCo-BS'!B14 -> 1433 | C28: ='PepsiCo-BS'!C14 -> 1703 | D28: ='PepsiCo-BS'!D14 -> 1538 | E28: ='PepsiCo-BS'!E14 -> 1277 | F28: ='PepsiCo-BS'!F14 -> 1232 | H28: =H26-H27 -> 1198.5631 | I28: =I26-I27 -> 1133.5042 | J28: =J26-J27 -> 1071.9767 | K28: =K26-K27 -> 1013.7891 | L28: =L26-L27 -> 958.75985
A29: Source | H29: Calculation
A32: Amortisation Rate | B32: =B27/B26 -> 0.053500661 | C32: =C27/C26 -> 0.050195204 | D32: =D27/D26 -> 0.055862492 | E32: =E27/E26 -> 0.057564576 | H32: =AVERAGE(B32:E32) -> 0.054280733 | I32: =H32 -> 0.054280733 | J32: =I32 -> 0.054280733 | K32: =J32 -> 0.054280733 | L32: =K32 -> 0.054280733

Sheet PepsiCo-BS
A1: PepsiCo Inc.
A2: (in USD million except per Share Data)
A3: Balance Sheet as of: | B3: Dec. 31, 2019 | C3: Dec. 31, 2020 | D3: Dec. 31, 2021 | E3: Dec. 31, 2022 | F3: June, 2023 | G3: Dec. 31, 2023 | H3: Dec. 31, 2024 | I3: Dec. 31, 2025 | J3: Dec. 31, 2026 | K3: Dec. 31, 2027
A4: ASSETS
A5: Cash And Equivalents | B5: 5509 | C5: 8185 | D5: 5596 | E5: 4954 | F5: 6116 | G5: ='Pepsico-CFS'!B35 -> 3131.3106 | H5: ='Pepsico-CFS'!C35 -> 4642.843 | I5: ='Pepsico-CFS'!D35 -> 4142.5892 | J5: ='Pepsico-CFS'!E35 -> 3762.4707 | K5: ='Pepsico-CFS'!F35 -> 4271.6655
A6: Short Term Investments | B6: 229 | C6: 1366 | D6: 392 | E6: 394 | F6: 338 | G6: =F6 -> 338 | H6: =G6 -> 338 | I6: =H6 -> 338 | J6: =I6 -> 338 | K6: =J6 -> 338
A7: Accounts and Notes Receivable | B7: 7822 | C7: 8404 | D7: 8680 | E7: 10163 | F7: 11456 | G7: =G59 -> 11221.934 | H7: =H59 -> 12157.485 | I7: =I59 -> 13174.049 | J7: =J59 -> 14278.907 | K7: =K59 -> 15480.018
A8: Inventories | B8: 3338 | C8: 4172 | D8: 4347 | E8: 5222 | F8: 5969 | G8: =G61 -> 5375.5778 | H8: =H61 -> 5886.1245 | I8: =I61 -> 6378.3006 | J8: =J61 -> 6913.2249 | K8: =K61 -> 7494.7504
A9: Prepaid expenses and other current assets | B9: 747 | C9: 874 | D9: 980 | E9: 806 | F9: 1075 | G9: =G63 -> 1096.2053 | H9: =H63 -> 1187.5938 | I9: =I63 -> 1286.8961 | J9: =J63 -> 1394.8232 | K9: =K63 -> 1512.1527
A10: Assets held for sale | B10: 0 | C10: 0 | D10: 1788 | E10: 0 | F10: 0 | G10: =F10 -> 0 | H10: =G10 -> 0 | I10: =H10 -> 0 | J10: =I10 -> 0 | K10: =J10 -> 0
A11: Total Current Assets | B11: =SUM(B5:B10) -> 17645 | C11: =SUM(C5:C10) -> 23001 | D11: =SUM(D5:D10) -> 21783 | E11: =SUM(E5:E10) -> 21539 | F11: =SUM(F5:F10) -> 24954 | G11: =SUM(G5:G10) -> 21163.027 | H11: =SUM(H5:H10) -> 24212.046 | I11: =SUM(I5:I10) -> 25319.835 | ... K11: =SUM(K5:K10) -> 29096.587
A13: Net Property, Plant & Equipment | B13: 19305 | C13: 21369 | D13: 22407 | E13: 24291 | F13: 24500 | G13: ='Fixed Assets Schedule'!H9 -> 29585.985 | H13: ='Fixed Assets Schedule'!I9 -> 30294.778 | I13: ='Fixed Assets Schedule'!J9 -> 32827.916 | J13: ='Fixed Assets Schedule'!K9 -> 35581.071 | K13: ='Fixed Assets Schedule'!L9 -> 38574.074
A14: Amortizable Intangible Assets, net | B14: 1433 | C14: 1703 | D14: 1538 | E14: 1277 | F14: 1232 | G14: ='Fixed Assets Schedule'!H28 -> 1198.5631 | H14: ='Fixed Assets Schedule'!I28 -> 1133.5042 | I14: ='Fixed Assets Schedule'!J28 -> 1071.9767 | J14: ='Fixed Assets Schedule'!K28 -> 1013.7891 | K14: ='Fixed Assets Schedule'!L28 -> 958.75985
A15: Goodwill | B15: 15501 | C15: 18757 | D15: 18381 | E15: 18202 | F15: 17997 | G15: =F15 -> 17997 | H15: =G15 -> 17997 | I15: =H15 -> 17997 | J15: =I15 -> 17997 | K15: =J15 -> 17997
A16: Other indefinite-lived intangible assets | B16: 14610 | C16: 17612 | D16: 17127 | E16: 14309 | F16: 14330 | G16: =F16 -> 14330 | H16: =G16 -> 14330 | I16: =H16 -> 14330 | J16: =I16 -> 14330 | K16: =J16 -> 14330
A17: Investments in Noncontrolled Affiliates | B17: 2683 | C17: 2792 | D17: 2350 | E17: 3073 | F17: 3038 | G17: =F17 -> 3038 | H17: =G17 -> 3038 | I17: =H17 -> 3038 | J17: =I17 -> 3038 | K17: =J17 -> 3038
A18: Deferred Income Taxes | B18: 4359 | C18: 4372 | D18: 4310 | E18: 4204 | F18: 4186 | G18: =F18 -> 4186 | H18: =G18 -> 4186 | I18: =H18 -> 4186 | J18: =I18 -> 4186 | K18: =J18 -> 4186
A19: Other Assets | B19: 3011 | C19: 3312 | D19: 4481 | E19: 5292 | F19: 5669 | G19: =F19 -> 5669 | H19: =G19 -> 5669 | I19: =H19 -> 5669 | J19: =I19 -> 5669 | K19: =J19 -> 5669
A20: Total Assets | B20: =SUM(B11,B13:B19) -> 78547 | C20: =SUM(C11,C13:C19) -> 92918 | D20: =SUM(D11,D13:D19) -> 92377 | E20: =SUM(E11,E13:E19) -> 92187 | F20: =SUM(F11,F13:F19) -> 95906 | G20: =SUM(G11,G13:G19) -> 97167.575 | H20: =SUM(H11,H13:H19) -> 100860.33 | I20: =SUM(I11,I13:I19) -> 104439.73 | ... K20: =SUM(K11,K13:K19) -> 113849.42
A22: LIABILITIES
A23: Short-term debt obligations | B23: 2920 | C23: 3780 | D23: 4308 | E23: 3414 | F23: 7613 | G23: ='Pepsico-Debt'!B50 -> 2867 | H23: ='Pepsico-Debt'!C50 -> 3193 | I23: ='Pepsico-Debt'!D50 -> 3246 | J23: ='Pepsico-Debt'!E50 -> 2523 | K23: ='Pepsico-Debt'!F50 -> 25302
A24: Accounts payable and other current liabilities | B24: 17541 | C24: 19592 | D24: 21159 | E24: 23371 | F24: 22005 | G24: =G67 -> 25837.618 | H24: =H67 -> 28291.552 | I24: =I67 -> 30657.188 | J24: =J67 -> 33228.292 | K24: =K67 -> 36023.384
A25: Liabilities held for sale | B25: 0 | C25: 0 | D25: 753 | E25: 0 | F25: 0 | G25: =F25 -> 0 | H25: =G25 -> 0 | I25: =H25 -> 0 | J25: =I25 -> 0 | K25: =J25 -> 0
A26: Total Current Liabilities | B26: =B23+B24+B25 -> 20461 | C26: =C23+C24+C25 -> 23372 | D26: =D23+D24+D25 -> 26220 | E26: =E23+E24+E25 -> 26785 | F26: =F23+F24+F25 -> 29618 | G26: =G23+G24+G25 -> 28704.618 | H26: =H23+H24+H25 -> 31484.552 | I26: =I23+I24+I25 -> 33903.188 | ... K26: =K23+K24+K25 -> 61325.384
A28: Long-Term Debt Obligations | B28: 29148 | C28: 40370 | D28: 36026 | E28: 35657 | F28: 36008 | G28: ='Pepsico-Debt'!B51 -> 35764 | H28: ='Pepsico-Debt'!C51 -> 32571 | I28: ='Pepsico-Debt'!D51 -> 29325 | J28: ='Pepsico-Debt'!E51 -> 26802 | K28: ='Pepsico-Debt'!F51 -> 1500
A29: Deferred Income Taxes | B29: 4091 | C29: 4284 | D29: 4826 | E29: 4133 | F29: 4113 | G29: =F29 -> 4113 | H29: =G29 -> 4113 | I29: =H29 -> 4113 | J29: =I29 -> 4113 | K29: =J29 -> 4113
A30: Other Liabilities | B30: 9979 | C30: 11340 | D30: 9154 | E30: 8339 | F30: 8342 | G30: =F30 -> 8342 | H30: =G30 -> 8342 | I30: =H30 -> 8342 | J30: =I30 -> 8342 | K30: =J30 -> 8342
A31: Total Liabilities | B31: =SUM(B26,B28:B30) -> 63679 | C31: =SUM(C26,C28:C30) -> 79366 | D31: =SUM(D26,D28:D30) -> 76226 | E31: =SUM(E26,E28:E30) -> 74914 | F31: =SUM(F26,F28:F30) -> 78081 | G31: =SUM(G26,G28:G30) -> 76923.618 | H31: =SUM(H26,H28:H30) -> 76510.552 | I31: =SUM(I26,I28:I30) -> 75683.188 | ... K31: =SUM(K26,K28:K30) -> 75280.384
A33: Common Stock | B33: 23 | C33: 23 | D33: 23 | E33: 23 | F33: 23 | G33: =F33 -> 23 | H33: =G33 -> 23 | I33: =H33 -> 23 | J33: =I33 -> 23 | K33: =J33 -> 23
A34: Capital in excess of par value | B34: 3886 | C34: 3910 | D34: 4001 | E34: 4134 | F34: 4082 | G34: =F34+'Pepsico-CFS'!B9 -> 4335.2735 | H34: =G34+'Pepsico-CFS'!C9 -> 4730.4277 | I34: =H34+'Pepsico-CFS'!D9 -> 5158.6233 | J34: =I34+'Pepsico-CFS'!E9 -> 5622.7301 | K34: =J34+'Pepsico-CFS'!F9 -> 6125.8765
A35: Retained Earnings | B35: 61946 | C35: 63443 | D35: 65165 | E35: 67800 | F35: 69135 | G35: =F35+'PepsiCo-IS'!G44+'Pepsico-CFS'!B24 -> 71249.297 | H35: =G35+'PepsiCo-IS'!I44+'Pepsico-CFS'!C24 -> 74880.116 | I35: =H35+'PepsiCo-IS'!J44+'Pepsico-CFS'!D24 -> 78773.073 | J35: =I35+'PepsiCo-IS'!K44+'Pepsico-CFS'!E24 -> 82954.466 | K35: =J35+'PepsiCo-IS'!L44+'Pepsico-CFS'!F24 -> 87427.983
A36: Accumulated other comprehensive loss | B36: -14300 | C36: -15476 | D36: -14898 | E36: -15302 | F36: -15780 | G36: =F36 -> -15780 | H36: =G36 -> -15780 | I36: =H36 -> -15780 | J36: =I36 -> -15780 | K36: =J36 -> -15780
A37: Repurchased common stock, in excess of par value | B37: -36769 | C37: -38446 | D37: -38248 | E37: -39506 | F37: -39775 | G37: =F37 -> -39775 | H37: =G37 -> -39775 | I37: =H37 -> -39775 | J37: =I37 -> -39775 | K37: =J37 -> -39775
A38: Total PepsiCo Common Shareholders’ Equity | B38: =SUM(B33:B37) -> 14786 | C38: =SUM(C33:C37) -> 13454 | D38: =SUM(D33:D37) -> 16043 | E38: =SUM(E33:E37) -> 17149 | F38: =SUM(F33:F37) -> 17685 | G38: =SUM(G33:G37) -> 20052.571 | H38: =SUM(H33:H37) -> 24078.544 | I38: =SUM(I33:I37) -> 28399.696 | ... K38: =SUM(K33:K37) -> 38021.859
A39: Noncontrolling interests | B39: 82 | C39: 98 | D39: 108 | E39: 124 | F39: 140 | G39: =F39+'PepsiCo-IS'!G42 -> 191.38588 | H39: =G39+'PepsiCo-IS'!I42 -> 271.23251 | I39: =H39+'PepsiCo-IS'!J42 -> 356.84392 | J39: =I39+'PepsiCo-IS'!K42 -> 448.79844 | K39: =J39+'PepsiCo-IS'!L42 -> 547.17716
A40: Total Equity | B40: =B38+B39 -> 14868 | C40: =C38+C39 -> 13552 | D40: =D38+D39 -> 16151 | E40: =E38+E39 -> 17273 | F40: =F38+F39 -> 17825 | G40: =G38+G39 -> 20243.957 | H40: =H38+H39 -> 24349.776 | I40: =I38+I39 -> 28756.54 | ... K40: =K38+K39 -> 38569.036
A42: Total Liabilities And Equity | B42: =B31+B40 -> 78547 | C42: =C31+C40 -> 92918 | D42: =D31+D40 -> 92377 | E42: =E31+E40 -> 92187 | F42: =F31+F40 -> 95906 | G42: =G31+G40 -> 97167.575 | H42: =H31+H40 -> 100860.33 | I42: =I31+I40 -> 104439.73 | ... K42: =K31+K40 -> 113849.42
A43: Check | B43: =B42-B20 -> 0 | C43: =C42-C20 -> 0 | D43: =D42-D20 -> 0 | E43: =E42-E20 -> 0 | F43: =F42-F20 -> 0 | G43: =G42-G20 -> 0 | H43: =H42-H20 -> 0 | I43: =I42-I20 -> 0 | ... K43: =K42-K20 -> 0
A44: Source | B44: 10K Dec'20, Pg 64 | D44: 10K Dec'22, Pg 66 | F44: 10Q June'23, Pg 8
A48: Accounts payable and other current liabilities | B48: =B24 -> 17541 | C48: =C24 -> 19592 | D48: =D24 -> 21159 | E48: =E24 -> 23371 | F48: =F24 -> 22005
A49: Less: Non Operating Items
A50: Dividends payable | B50: 1351 | C50: 1430 | D50: 1508 | E50: 1610 | F50: No info. Available
A51: Current lease liabilities | B51: 442 | C51: 460 | D51: 446 | E51: 483
A52: Soda Stream Consideration Payable | B52: 58 | C52: 0 | D52: 0 | E52: 0
A53: Accounts payable and other current liabilities-Operating | B53: =B48-B50-B51-B52 -> 15690 | C53: =C48-C50-C51 -> 17702 | D53: =D48-D50-D51 -> 19205 | E53: =E48-E50-E51 -> 21278 | F53: =E53-1960 -> 19318
A54: Accounts payable and other current liabilities-Non Operating | B54: =B50+B51+B52 -> 1851 | C54: =C50+C51 -> 1890 | D54: =D50+D51 -> 1954 | E54: =E50+E51 -> 2093 | F54: =F48-F53 -> 2687
A57: Working Capital
A58: Operating Current Assets
A59: =A7 -> Accounts and Notes Receivable | B59: =B7 -> 7822 | C59: =C7 -> 8404 | D59: =D7 -> 8680 | E59: =E7 -> 10163 | F59: =F7 -> 11456 | G59: =$G$60/365*'PepsiCo-IS'!H6 -> 11221.934 | H59: =$G$60/365*'PepsiCo-IS'!I6 -> 12157.485 | I59: =$G$60/365*'PepsiCo-IS'!J6 -> 13174.049 | J59: =$G$60/365*'PepsiCo-IS'!K6 -> 14278.907 | K59: =$G$60/365*'PepsiCo-IS'!L6 -> 15480.018
A60: Receivable Days | B60: =365*B59/'PepsiCo-IS'!B6 -> 42.510237 | C60: =365*C59/'PepsiCo-IS'!C6 -> 43.589212 | D60: =365*D59/'PepsiCo-IS'!D6 -> 39.86461 | E60: =365*E59/'PepsiCo-IS'!E6 -> 42.937946 | G60: =AVERAGE(B60:E60) -> 42.225501
A61: =A8 -> Inventories | B61: =B8 -> 3338 | C61: =C8 -> 4172 | D61: =D8 -> 4347 | E61: =E8 -> 5222 | F61: =F8 -> 5969 | G61: =$G$62/365*'PepsiCo-IS'!H10 -> 5375.5778 | H61: =$G$62/365*'PepsiCo-IS'!I10 -> 5886.1245 | I61: =$G$62/365*'PepsiCo-IS'!J10 -> 6378.3006 | J61: =$G$62/365*'PepsiCo-IS'!K10 -> 6913.2249 | K61: =$G$62/365*'PepsiCo-IS'!L10 -> 7494.7504
A62: Inventory Days | B62: =365*B61/'PepsiCo-IS'!B10 -> 43.757003 | C62: =365*C61/'PepsiCo-IS'!C10 -> 51.675716 | D62: =365*D61/'PepsiCo-IS'!D10 -> 45.976673 | E62: =365*E61/'PepsiCo-IS'!E10 -> 50.522981 | G62: =AVERAGE(B62:E62) -> 47.983094
A63: =A9 -> Prepaid expenses and other current assets | B63: =B9 -> 747 | C63: =C9 -> 874 | D63: =D9 -> 980 | E63: =E9 -> 806 | F63: =F9 -> 1075 | G63: =$G$64*'PepsiCo-IS'!H6 -> 1096.2053 | H63: =$G$64*'PepsiCo-IS'!I6 -> 1187.5938 | I63: =$G$64*'PepsiCo-IS'!J6 -> 1286.8961 | J63: =$G$64*'PepsiCo-IS'!K6 -> 1394.8232 | K63: =$G$64*'PepsiCo-IS'!L6 -> 1512.1527
A64: %age of Sales | B64: =B63/'PepsiCo-IS'!B6 -> 0.011122526 | C64: =C63/'PepsiCo-IS'!C6 -> 0.012419712 | D64: =D63/'PepsiCo-IS'!D6 -> 0.012331077 | E64: =E63/'PepsiCo-IS'!E6 -> 0.0093295676 | G64: =AVERAGE(B64:E64) -> 0.011300721
A66: Operating Current Liabilities
A67: =A53 -> Accounts payable and other current liabilities-Operating | B67: =B24 -> 17541 | C67: =C24 -> 19592 | D67: =D24 -> 21159 | E67: =E24 -> 23371 | F67: =F24 -> 22005 | G67: =$G$68/365*'PepsiCo-IS'!H10 -> 25837.618 | H67: =$G$68/365*'PepsiCo-IS'!I10 -> 28291.552 | I67: =$G$68/365*'PepsiCo-IS'!J10 -> 30657.188 | J67: =$G$68/365*'PepsiCo-IS'!K10 -> 33228.292 | K67: =$G$68/365*'PepsiCo-IS'!L10 -> 36023.384
A68: Payable Days | B68: =365*B67/'PepsiCo-IS'!B10 -> 229.94056 | C68: =365*C67/'PepsiCo-IS'!C10 -> 242.67273 | D68: =365*D67/'PepsiCo-IS'!D10 -> 223.79122 | E68: =365*E67/'PepsiCo-IS'!E10 -> 226.11501 | G68: =AVERAGE(B68:E68) -> 230.62988

Sheet Pepsico-CFS
A1: PepsiCo Inc.
A2: (in USD million except per Share Data)
A3: Cash Flow Statement | B3: 6 months | C3: 12 months | D3: 12 months | E3: 12 months | F3: 12 months
B4: Dec. 31, 2023 | C4: Dec. 31, 2024 | D4: Dec. 31, 2025 | E4: Dec. 31, 2026 | F4: Dec. 31, 2027
A6: Cash From Operating Activities
A7: Net Income | B7: ='PepsiCo-IS'!G38 -> 7135.4997 | C7: ='PepsiCo-IS'!I38 -> 11791.123 | D7: ='PepsiCo-IS'!J38 -> 12642.419 | E7: ='PepsiCo-IS'!K38 -> 13579.12 | F7: ='PepsiCo-IS'!L38 -> 14527.795
A8: Depreciation and amortization | B8: ='Fixed Assets Schedule'!H27+'Fixed Assets Schedule'!H8 -> 1655.908 | C8: ='Fixed Assets Schedule'!I27+'Fixed Assets Schedule'!I8 -> 3580.5256 | D8: ='Fixed Assets Schedule'!J27+'Fixed Assets Schedule'!J8 -> 3870.9446 | E8: ='Fixed Assets Schedule'!K27+'Fixed Assets Schedule'!K8 -> 4187.0864 | F8: ='Fixed Assets Schedule'!L27+'Fixed Assets Schedule'!L8 -> 4531.2419
A9: Share-based compensation expense | B9: ='PepsiCo-IS'!G63 -> 253.27346 | C9: ='PepsiCo-IS'!I63 -> 395.15426 | D9: ='PepsiCo-IS'!J63 -> 428.19561 | E9: ='PepsiCo-IS'!K63 -> 464.10678 | F9: ='PepsiCo-IS'!L63 -> 503.14644
A10: Change in assets and liabilities:
A11: Accounts and notes receivable | B11: =-('PepsiCo-BS'!G7-'PepsiCo-BS'!F7) -> 234.06643 | C11: =-('PepsiCo-BS'!H7-'PepsiCo-BS'!G7) -> -935.55109 | D11: =-('PepsiCo-BS'!I7-'PepsiCo-BS'!H7) -> -1016.5642 | E11: =-('PepsiCo-BS'!J7-'PepsiCo-BS'!I7) -> -1104.8582 | F11: =-('PepsiCo-BS'!K7-'PepsiCo-BS'!J7) -> -1201.1108
A12: Inventories | B12: =-('PepsiCo-BS'!G8-'PepsiCo-BS'!F8) -> 593.42225 | C12: =-('PepsiCo-BS'!H8-'PepsiCo-BS'!G8) -> -510.54676 | D12: =-('PepsiCo-BS'!I8-'PepsiCo-BS'!H8) -> -492.17613 | E12: =-('PepsiCo-BS'!J8-'PepsiCo-BS'!I8) -> -534.92423 | F12: =-('PepsiCo-BS'!K8-'PepsiCo-BS'!J8) -> -581.52553
A13: Prepaid expenses and other current assets | B13: =-('PepsiCo-BS'!G9-'PepsiCo-BS'!F9) -> -21.20529 | C13: =-('PepsiCo-BS'!H9-'PepsiCo-BS'!G9) -> -91.388533 | D13: =-('PepsiCo-BS'!I9-'PepsiCo-BS'!H9) -> -99.302236 | E13: =-('PepsiCo-BS'!J9-'PepsiCo-BS'!I9) -> -107.92716 | F13: =-('PepsiCo-BS'!K9-'PepsiCo-BS'!J9) -> -117.32951
A14: Accounts payable and other current liabilities | B14: ='PepsiCo-BS'!G24-'PepsiCo-BS'!F24 -> 3832.6183 | C14: ='PepsiCo-BS'!H24-'PepsiCo-BS'!G24 -> 2453.9339 | D14: ='PepsiCo-BS'!I24-'PepsiCo-BS'!H24 -> 2365.6357 | E14: ='PepsiCo-BS'!J24-'PepsiCo-BS'!I24 -> 2571.1038 | F14: ='PepsiCo-BS'!K24-'PepsiCo-BS'!J24 -> 2795.092
A16: Net Cash Provided by Operating Activities | B16: =SUM(B11:B14,B7:B9) -> 13683.583 | C16: =SUM(C11:C14,C7:C9) -> 16683.25 | D16: =SUM(D11:D14,D7:D9) -> 17699.153 | E16: =SUM(E11:E14,E7:E9) -> 19053.707 | F16: =SUM(F11:F14,F7:F9) -> 20457.31
A18: Cash From Investing Activities
A19: Capital Expenditure | B19: =-'Fixed Assets Schedule'!H6 -> -6708.4559 | C19: =-'Fixed Assets Schedule'!I6 -> -4224.2602 | D19: =-'Fixed Assets Schedule'!J6 -> -6342.5553 | E19: =-'Fixed Assets Schedule'!K6 -> -6882.0533 | F19: =-'Fixed Assets Schedule'!L6 -> -7469.2155
A21: Net Cash Used for Investing Activities | B21: =B19 -> -6708.4559 | C21: =C19 -> -4224.2602 | D21: =D19 -> -6342.5553 | E21: =E19 -> -6882.0533 | F21: =F19 -> -7469.2155
A23: Cash From Financing Activities
A24: Cash dividends paid | B24: =-('PepsiCo-IS'!G67*'PepsiCo-IS'!G46) -> -4969.8164 | C24: =-('PepsiCo-IS'!I67*'PepsiCo-IS'!I46) -> -8080.4578 | D24: =-('PepsiCo-IS'!J67*'PepsiCo-IS'!J46) -> -8663.8513 | E24: =-('PepsiCo-IS'!K67*'PepsiCo-IS'!K46) -> -9305.772 | F24: =-('PepsiCo-IS'!L67*'PepsiCo-IS'!L46) -> -9955.8996
A25: Cash before Raising (Repayment) of Debt | B25: =B16+B21+B24 -> 2005.3106 | C25: =C16+C21+C24 -> 4378.5324 | D25: =D16+D21+D24 -> 2692.7462 | E25: =E16+E21+E24 -> 2865.8815 | F25: =F16+F21+F24 -> 3032.1948
A27: Debt Raised | B27: ='Pepsico-Debt'!B41 -> 0 | C27: ='Pepsico-Debt'!C41 -> 0 | D27: ='Pepsico-Debt'!D41 -> 0 | E27: ='Pepsico-Debt'!E41 -> 0 | F27: ='Pepsico-Debt'!F41 -> 0
A28: Debt Repaid | B28: ='Pepsico-Debt'!B42+'Pepsico-Debt'!B9 -> -4990 | C28: ='Pepsico-Debt'!C42+'Pepsico-Debt'!C9 -> -2867 | D28: ='Pepsico-Debt'!D42+'Pepsico-Debt'!D9 -> -3193 | E28: ='Pepsico-Debt'!E42+'Pepsico-Debt'!E9 -> -3246 | F28: ='Pepsico-Debt'!F42+'Pepsico-Debt'!F9 -> -2523
A31: Net Cash Provided by/(Used for) Financing Activities | B31: =B24+B27+B28 -> -9959.8164 | C31: =C24+C27+C28 -> -10947.458 | D31: =D24+D27+D28 -> -11856.851 | E31: =E24+E27+E28 -> -12551.772 | F31: =F24+F27+F28 -> -12478.9
A33: Net Increase/(Decrease) in Cash and Cash Equivalents | B33: =B31+B21+B16 -> -2984.6894 | C33: =C31+C21+C16 -> 1511.5324 | D33: =D31+D21+D16 -> -500.25383 | E33: =E31+E21+E16 -> -380.11851 | F33: =F31+F21+F16 -> 509.19482
A34: Cash and Cash Equivalents, Beginning of Year | B34: ='PepsiCo-BS'!F5 -> 6116 | C34: ='PepsiCo-BS'!G5 -> 3131.3106 | D34: ='PepsiCo-BS'!H5 -> 4642.843 | E34: ='PepsiCo-BS'!I5 -> 4142.5892 | F34: ='PepsiCo-BS'!J5 -> 3762.4707
A35: Cash and Cash Equivalents, End of Period | B35: =B34+B33 -> 3131.3106 | C35: =C34+C33 -> 4642.843 | D35: =D34+D33 -> 4142.5892 | E35: =E34+E33 -> 3762.4707 | F35: =F34+F33 -> 4271.6655
A37: Source: Calculations

Sheet Pepsico-Debt
A1: PepsiCo Inc.
A2: (in USD million except per Share Data)
A3: Debt Schedule | B3: 6 months | C3: 12 months | D3: 12 months | E3: 12 months | F3: 12 months
B4: Dec. 31, 2023 | C4: Dec. 31, 2024 | D4: Dec. 31, 2025 | E4: Dec. 31, 2026 | F4: Dec. 31, 2027
A6: Cash Before Debt | B6: ='Pepsico-CFS'!B25 -> 2005.3106 | C6: ='Pepsico-CFS'!C25 -> 4378.5324 | D6: ='Pepsico-CFS'!D25 -> 2692.7462 | E6: ='Pepsico-CFS'!E25 -> 2865.8815 | F6: ='Pepsico-CFS'!F25 -> 3032.1948
A7: Add: Opening Cash Balance | B7: ='PepsiCo-BS'!F5 -> 6116 | C7: ='PepsiCo-BS'!G5 -> 3131.3106 | D7: ='PepsiCo-BS'!H5 -> 4642.843 | E7: ='PepsiCo-BS'!I5 -> 4142.5892 | F7: ='PepsiCo-BS'!J5 -> 3762.4707
A8: Cash Available for Debt | B8: =B6+B7 -> 8121.3106 | C8: =C6+C7 -> 7509.843 | D8: =D6+D7 -> 7335.5892 | E8: =E6+E7 -> 7008.4707 | F8: =F6+F7 -> 6794.6655
A9: Less: Mandatory Debt Repayments | B9: =-(I17+I23) -> -822 | C9: =-I18 -> -2867 | D9: =-(I19) -> -3193 | E9: =-(I20+I24+I25) -> -3246 | F9: =-(I21) -> -2523 | G9: =-(I22+I26) -> -25302
A10: Cash Available for Discretionery Sweep | B10: =B8+B9 -> 7299.3106 | C10: =C8+C9 -> 4642.843 | D10: =D8+D9 -> 4142.5892 | E10: =E8+E9 -> 3762.4707 | F10: =F8+F9 -> 4271.6655
A11: Source: Calculations
M13: Interest Expenses
A14: Mandatory Debt | F14: Balance As on 31 Dec 2022 | I14: Net Balance As on 30 June 2023 | M14: =B3 -> 6 months | N14: =C3 -> 12 months | O14: =D3 -> 12 months | P14: =E3 -> 12 months | Q14: =F3 -> 12 months
B15: Repayment Date | C15: Interest Rate | E15: Average Rate | G15: Raised | H15: Repaid | L15: 45094 | M15: 45291 | N15: 45657 | O15: 46022 | P15: 46387 | Q15: 46752
A16: 2022 Notes | B16: 44926 | C16: 0.024 | D16: 0.024 | E16: =AVERAGE(C16:D16) -> 0.024 | F16: 0 | I16: =F16+G16-H16 -> 0 | J16: 10K Dec 2022, Pg 97 | M16: =IF($B16>L$15,$I16*$E16*(MIN($B16-L$15,M$15-L$15))/365,0) -> 0 | N16: =IF($B16>M$15,$I16*$E16*(MIN($B16-M$15,N$15-M$15))/365,0) -> 0 | O16: =IF($B16>N$15,$I16*$E16*(MIN($B16-N$15,O$15-N$15))/365,0) -> 0 | P16: =IF($B16>O$15,$I16*$E16*(MIN($B16-O$15,P$15-O$15))/365,0) -> 0 | Q16: =IF($B16>P$15,$I16*$E16*(MIN($B16-P$15,Q$15-P$15))/365,0) -> 0
A17: 2023 Notes | B17: 45291 | C17: 0.017 | D17: 0.015 | E17: =AVERAGE(C17:D17) -> 0.016 | F17: 3094 | H17: 2300 | I17: =F17+G17-H17 -> 794 | J17: 10K Dec 2022, Pg 97 | L17: =I17*E17*(B17-L15)/365 -> 6.8566795 | M17: =IF($B17>L$15,$I17*$E17*(MIN($B17-L$15,M$15-L$15))/365,0) -> 6.8566795 | N17: =IF($B17>M$15,$I17*$E17*(MIN($B17-M$15,N$15-M$15))/365,0) -> 0 | O17: =IF($B17>N$15,$I17*$E17*(MIN($B17-N$15,O$15-N$15))/365,0) -> 0 | P17: =IF($B17>O$15,$I17*$E17*(MIN($B17-O$15,P$15-O$15))/365,0) -> 0 | Q17: =IF($B17>P$15,$I17*$E17*(MIN($B17-P$15,Q$15-P$15))/365,0) -> 0
A18: 2024 Notes | B18: 45657 | C18: 0.022 | D18: 0.021 | E18: =AVERAGE(C18:D18) -> 0.0215 | F18: 2867 | I18: =F18+G18-H18 -> 2867 | J18: 10K Dec 2022, Pg 97 | M18: =IF($B18>L$15,$I18*$E18*(MIN($B18-L$15,M$15-L$15))/365,0) -> 33.268982 | N18: =IF($B18>M$15,$I18*$E18*(MIN($B18-M$15,N$15-M$15))/365,0) -> 61.809378 | O18: =IF($B18>N$15,$I18*$E18*(MIN($B18-N$15,O$15-N$15))/365,0) -> 0 | P18: =IF($B18>O$15,$I18*$E18*(MIN($B18-O$15,P$15-O$15))/365,0) -> 0 | Q18: =IF($B18>P$15,$I18*$E18*(MIN($B18-P$15,Q$15-P$15))/365,0) -> 0
A19: 2025 Notes | B19: 46022 | C19: 0.027 | D19: 0.027 | E19: =AVERAGE(C19:D19) -> 0.027 | F19: 3193 | I19: =F19+G19-H19 -> 3193 | J19: 10K Dec 2022, Pg 97 | M19: =IF($B19>L$15,$I19*$E19*(MIN($B19-L$15,M$15-L$15))/365,0) -> 46.530321 | N19: =IF($B19>M$15,$I19*$E19*(MIN($B19-M$15,N$15-M$15))/365,0) -> 86.447195 | O19: =IF($B19>N$15,$I19*$E19*(MIN($B19-N$15,O$15-N$15))/365,0) -> 86.211 | P19: =IF($B19>O$15,$I19*$E19*(MIN($B19-O$15,P$15-O$15))/365,0) -> 0 | Q19: =IF($B19>P$15,$I19*$E19*(MIN($B19-P$15,Q$15-P$15))/365,0) -> 0
A20: 2026 Notes | B20: 46387 | C20: 0.031 | D20: 0.032 | E20: =AVERAGE(C20:D20) -> 0.0315 | F20: 2396 | I20: =F20+G20-H20 -> 2396 | J20: 10K Dec 2022, Pg 97 | M20: =IF($B20>L$15,$I20*$E20*(MIN($B20-L$15,M$15-L$15))/365,0) -> 40.735282 | N20: =IF($B20>M$15,$I20*$E20*(MIN($B20-M$15,N$15-M$15))/365,0) -> 75.680778 | O20: =IF($B20>N$15,$I20*$E20*(MIN($B20-N$15,O$15-N$15))/365,0) -> 75.474 | P20: =IF($B20>O$15,$I20*$E20*(MIN($B20-O$15,P$15-O$15))/365,0) -> 75.474 | Q20: =IF($B20>P$15,$I20*$E20*(MIN($B20-P$15,Q$15-P$15))/365,0) -> 0
A21: 2027 Notes | B21: 46752 | C21: 0.025 | D21: 0.024 | E21: =AVERAGE(C21:D21) -> 0.0245 | F21: 2523 | I21: =F21+G21-H21 -> 2523 | J21: 10K Dec 2022, Pg 97 | M21: =IF($B21>L$15,$I21*$E21*(MIN($B21-L$15,M$15-L$15))/365,0) -> 33.362355 | N21: =IF($B21>M$15,$I21*$E21*(MIN($B21-M$15,N$15-M$15))/365,0) -> 61.982852 | O21: =IF($B21>N$15,$I21*$E21*(MIN($B21-N$15,O$15-N$15))/365,0) -> 61.8135 | P21: =IF($B21>O$15,$I21*$E21*(MIN($B21-O$15,P$15-O$15))/365,0) -> 61.8135 | Q21: =IF($B21>P$15,$I21*$E21*(MIN($B21-P$15,Q$15-P$15))/365,0) -> 61.8135
A22: 2028-2060 Notes | B22: 47118 | C22: 0.028 | D22: 0.026 | E22: =AVERAGE(C22:D22) -> 0.027 | F22: 24652 | I22: =F22+G22-H22 -> 24652 | J22: 10K Dec 2022, Pg 97 | M22: =IF($B22>L$15,$I22*$E22*(MIN($B22-L$15,M$15-L$15))/365,0) -> 359.2438 | N22: =IF($B22>M$15,$I22*$E22*(MIN($B22-M$15,N$15-M$15))/365,0) -> 667.42757 | O22: =IF($B22>N$15,$I22*$E22*(MIN($B22-N$15,O$15-N$15))/365,0) -> 665.604 | P22: =IF($B22>O$15,$I22*$E22*(MIN($B22-O$15,P$15-O$15))/365,0) -> 665.604 | Q22: =IF($B22>P$15,$I22*$E22*(MIN($B22-P$15,Q$15-P$15))/365,0) -> 665.604
A23: 2022-2028 Notes | B23: 45291 | C23: 0.013 | D23: 0.013 | E23: =AVERAGE(C23:D23) -> 0.013 | F23: 28 | I23: =F23+G23-H23 -> 28 | J23: 10K Dec 2022, Pg 97 | M23: =IF($B23>L$15,$I23*$E23*(MIN($B23-L$15,M$15-L$15))/365,0) -> 0.19646027 | N23: =IF($B23>M$15,$I23*$E23*(MIN($B23-M$15,N$15-M$15))/365,0) -> 0 | O23: =IF($B23>N$15,$I23*$E23*(MIN($B23-N$15,O$15-N$15))/365,0) -> 0 | P23: =IF($B23>O$15,$I23*$E23*(MIN($B23-O$15,P$15-O$15))/365,0) -> 0 | Q23: =IF($B23>P$15,$I23*$E23*(MIN($B23-P$15,Q$15-P$15))/365,0) -> 0
A24: New Notes February 2026 | B24: 46054 | C24: 0.0455 | D24: 0.0455 | E24: =AVERAGE(C24:D24) -> 0.0455 | G24: 350 | I24: =F24+G24-H24 -> 350 | J24: 10Q June 2023, Pg 20 | M24: =IF($B24>L$15,$I24*$E24*(MIN($B24-L$15,M$15-L$15))/365,0) -> 8.595137 | N24: =IF($B24>M$15,$I24*$E24*(MIN($B24-M$15,N$15-M$15))/365,0) -> 15.96863 | O24: =IF($B24>N$15,$I24*$E24*(MIN($B24-N$15,O$15-N$15))/365,0) -> 15.925 | P24: =IF($B24>O$15,$I24*$E24*(MIN($B24-O$15,P$15-O$15))/365,0) -> 1.3961644 | Q24: =IF($B24>P$15,$I24*$E24*(MIN($B24-P$15,Q$15-P$15))/365,0) -> 0
A25: New Notes February 2026 | B25: 46054 | C25: 0.0455 | D25: 0.0455 | E25: =AVERAGE(C25:D25) -> 0.0455 | G25: 500 | I25: =F25+G25-H25 -> 500 | J25: 10Q June 2023, Pg 20 | M25: =IF($B25>L$15,$I25*$E25*(MIN($B25-L$15,M$15-L$15))/365,0) -> 12.278767 | N25: =IF($B25>M$15,$I25*$E25*(MIN($B25-M$15,N$15-M$15))/365,0) -> 22.812329 | O25: =IF($B25>N$15,$I25*$E25*(MIN($B25-N$15,O$15-N$15))/365,0) -> 22.75 | P25: =IF($B25>O$15,$I25*$E25*(MIN($B25-O$15,P$15-O$15))/365,0) -> 1.9945205 | Q25: =IF($B25>P$15,$I25*$E25*(MIN($B25-P$15,Q$15-P$15))/365,0) -> 0
A26: New Notes May 2028 | B26: 46874 | C26: 0.0445 | D26: 0.0445 | E26: =AVERAGE(C26:D26) -> 0.0445 | G26: 650 | I26: =F26+G26-H26 -> 650 | J26: 10Q June 2023, Pg 20 | M26: =IF($B26>L$15,$I26*$E26*(MIN($B26-L$15,M$15-L$15))/365,0) -> 15.611575 | N26: =IF($B26>M$15,$I26*$E26*(MIN($B26-M$15,N$15-M$15))/365,0) -> 29.004247 | O26: =IF($B26>N$15,$I26*$E26*(MIN($B26-N$15,O$15-N$15))/365,0) -> 28.925 | P26: =IF($B26>O$15,$I26*$E26*(MIN($B26-O$15,P$15-O$15))/365,0) -> 28.925 | Q26: =IF($B26>P$15,$I26*$E26*(MIN($B26-P$15,Q$15-P$15))/365,0) -> 28.925
A27: New Notes February 2033 | B27: 48611 | C27: 0.0445 | D27: 0.0445 | E27: =AVERAGE(C27:D27) -> 0.0445 | G27: 1000 | I27: =F27+G27-H27 -> 1000 | J27: 10Q June 2023, Pg 20 | M27: =IF($B27>L$15,$I27*$E27*(MIN($B27-L$15,M$15-L$15))/365,0) -> 24.017808 | N27: =IF($B27>M$15,$I27*$E27*(MIN($B27-M$15,N$15-M$15))/365,0) -> 44.621918 | O27: =IF($B27>N$15,$I27*$E27*(MIN($B27-N$15,O$15-N$15))/365,0) -> 44.5 | P27: =IF($B27>O$15,$I27*$E27*(MIN($B27-O$15,P$15-O$15))/365,0) -> 44.5 | Q27: =IF($B27>P$15,$I27*$E27*(MIN($B27-P$15,Q$15-P$15))/365,0) -> 44.5
A28: New Notes February 2053 | B28: 55916 | C28: 0.0465 | D28: 0.0465 | E28: =AVERAGE(C28:D28) -> 0.0465 | G28: 500 | I28: =F28+G28-H28 -> 500 | J28: 10Q June 2023, Pg 20 | M28: =IF($B28>L$15,$I28*$E28*(MIN($B28-L$15,M$15-L$15))/365,0) -> 12.54863 | N28: =IF($B28>M$15,$I28*$E28*(MIN($B28-M$15,N$15-M$15))/365,0) -> 23.313699 | O28: =IF($B28>N$15,$I28*$E28*(MIN($B28-N$15,O$15-N$15))/365,0) -> 23.25 | P28: =IF($B28>O$15,$I28*$E28*(MIN($B28-O$15,P$15-O$15))/365,0) -> 23.25 | Q28: =IF($B28>P$15,$I28*$E28*(MIN($B28-P$15,Q$15-P$15))/365,0) -> 23.25
M29: =SUM(M16:M28) -> 593.2458 | N29: =SUM(N16:N28) -> 1089.0686 | O29: =SUM(O16:O28) -> 1024.4525 | P29: =SUM(P16:P28) -> 902.95718 | Q29: =SUM(Q16:Q28) -> 824.0925
A30: Total Mandatory Debt | E30: =AVERAGE(E16:E28) -> 0.031615385 | F30: =SUM(F16:F29) -> 38753 | G30: =SUM(G16:G29) -> 3000 | H30: =SUM(H16:H29) -> 2300 | I30: =SUM(I16:I29) -> 39453
A32: Total Debt (Discretionery + Mandatory) | F32: ='PepsiCo-BS'!E23+'PepsiCo-BS'!E28 -> 39071 | I32: ='PepsiCo-BS'!F28+'PepsiCo-BS'!F23 -> 43621
A34: Discretionary Debt (Balance) | F34: =F32-F30 -> 318 | I34: =I32-I30 -> 4168
A37: Discretionary Debt Schedule
B38: 6 | C38: 12 | D38: 12 | E38: 12 | F38: 12
B39: Dec. 31, 2023 | C39: Dec. 31, 2024 | D39: Dec. 31, 2025 | E39: Dec. 31, 2026 | F39: Dec. 31, 2027
A40: Opening Balance | B40: =I34 -> 4168 | C40: =B43 -> 0 | D40: =C43 -> 0 | E40: =D43 -> 0 | F40: =E43 -> 0
A41: Add: Debt Raised | B41: =IF(B10<0,-B10,0) -> 0 | C41: =IF(C10<0,-C10,0) -> 0 | D41: =IF(D10<0,-D10,0) -> 0 | E41: =IF(E10<0,-E10,0) -> 0 | F41: =IF(F10<0,-F10,0) -> 0
A42: Less: Debt Repaid | B42: =-MIN(B40,B10) -> -4168 | C42: =-MIN(C40,C10) -> 0 | D42: =-MIN(D40,D10) -> 0 | E42: =-MIN(E40,E10) -> 0 | F42: =-MIN(F40,F10) -> 0
A43: Closing Balance | B43: =SUM(B40:B42) -> 0 | C43: =SUM(C40:C42) -> 0 | D43: =SUM(D40:D42) -> 0 | E43: =SUM(E40:E42) -> 0 | F43: =SUM(F40:F42) -> 0
A45: Interest Rate | B45: =E30 -> 0.031615385
A47: Interest Expenses | B47: =AVERAGE(B43,B40)*$B$45*B38/12 -> 32.943231 | C47: =AVERAGE(C43,C40)*$B$45*C38/12 -> 0 | D47: =AVERAGE(D43,D40)*$B$45*D38/12 -> 0 | E47: =AVERAGE(E43,E40)*$B$45*E38/12 -> 0 | F47: =AVERAGE(F43,F40)*$B$45*F38/12 -> 0
A49: Total Debt | B49: =B41+B42+B9+'PepsiCo-BS'!F23+'PepsiCo-BS'!F28 -> 38631 | C49: =C41+C42+C9+'PepsiCo-BS'!G23+'PepsiCo-BS'!G28 -> 35764 | D49: =D41+D42+D9+'PepsiCo-BS'!H23+'PepsiCo-BS'!H28 -> 32571 | E49: =E41+E42+E9+'PepsiCo-BS'!I23+'PepsiCo-BS'!I28 -> 29325 | F49: =F41+F42+F9+'PepsiCo-BS'!J23+'PepsiCo-BS'!J28 -> 26802
A50: Short term debt | B50: =-C9+B43 -> 2867 | C50: =-D9+C43 -> 3193 | D50: =-E9+D43 -> 3246 | E50: =-F9+E43 -> 2523 | F50: =-G9+F43 -> 25302
A51: Long term Debt | B51: =B49-B50 -> 35764 | C51: =C49-C50 -> 32571 | D51: =D49-D50 -> 29325 | E51: =E49-E50 -> 26802 | F51: =F49-F50 -> 1500

Sheet PepsiCo-IS
A1: PepsiCo Inc.
A2: (in USD million except per Share Data)
A3: Income Statement | B3: 12 months | C3: 12 months | D3: 12 months | E3: 12 months | F3: 6 months | G3: 6 months | H3: 12 months | I3: 12 months | J3: 12 months | K3: 12 months | L3: 12 months
B4: Dec. 31, 2019 | C4: Dec. 31, 2020 | D4: Dec. 31, 2021 | E4: Dec. 31, 2022 | F4: Jun. 17, 2023 | G4: Dec. 31, 2023 | H4: Dec. 31, 2023 | I4: Dec. 31, 2024 | J4: Dec. 31, 2025 | K4: Dec. 31, 2026 | L4: Dec. 31, 2027
A6: Net Revenue | B6: 67161 | C6: 70372 | D6: 79474 | E6: 86392 | F6: 40168 | G6: ='Revenue Segment'!K34 -> 56835.13 | H6: =F6+G6 -> 97003.13 | I6: ='Revenue Segment'!N34 -> 105090.09 | J6: ='Revenue Segment'!O34 -> 113877.34 | K6: ='Revenue Segment'!P34 -> 123427.81 | L6: ='Revenue Segment'!Q34 -> 133810.29
A7: Cost of Sales-Reported | B7: 30132 | C7: 31797 | D7: 37075 | E7: 40576 | F7: 18109
A8: Impact of Special Items | B8: -92 | C8: 2 | D8: -69 | E8: -286 | F8: -14
A9: Cost of Sales-Normalised | B9: =B7+B8 -> 30040 | C9: =C7+C8 -> 31799 | D9: =D7+D8 -> 37006 | E9: =E7+E8 -> 40290 | F9: =F7+F8 -> 18095 | G9: =G10+G11 -> 25496.015 | H9: =F9+G9 -> 43591.015 | I9: =I10+I11 -> 48106.081 | J9: =J10+J11 -> 52128.535 | K9: =K10+K11 -> 56500.36 | L9: =L10+L11 -> 61253.048
A10: Cost of Sales (Other than Depreciation Exp) | B10: =B9-B11 -> 27844 | C10: =C9-C11 -> 29468 | D10: =D9-D11 -> 34510 | E10: =E9-E11 -> 37726 | F10: =F9-F11 -> 16932.623 | G10: =G6*G54 -> 23958.569 | H10: =F10+G10 -> 40891.192 | I10: =I6*I54 -> 44774.842 | J10: =J6*J54 -> 48518.75 | K10: =K6*K54 -> 52587.836 | L10: =L6*L54 -> 57011.412
A11: Depreciation Exp | B11: 2196 | C11: 2331 | D11: 2496 | E11: 2564 | F11: =1268*F76 -> 1162.3774 | G11: ='Fixed Assets Schedule'!H18 -> 1537.4455 | H11: =F11+G11 -> 2699.8229 | I11: ='Fixed Assets Schedule'!I18 -> 3331.2387 | J11: ='Fixed Assets Schedule'!J18 -> 3609.7846 | K11: ='Fixed Assets Schedule'!K18 -> 3912.5238 | L11: ='Fixed Assets Schedule'!L18 -> 4241.6368
A13: Gross Profit-Normalised | B13: =B6-B9 -> 37121 | C13: =C6-C9 -> 38573 | D13: =D6-D9 -> 42468 | E13: =E6-E9 -> 46102 | F13: =F6-F9 -> 22073 | G13: =G6-G9 -> 31339.115 | H13: =F13+G13 -> 53412.115 | I13: =I6-I9 -> 56984.014 | J13: =J6-J9 -> 61748.808 | K13: =K6-K9 -> 66927.45 | L13: =L6-L9 -> 72557.242
A15: Selling, General & Admin Exp.-Reported | B15: 26738 | C15: 28495 | D15: 31237 | E15: 34459 | F15: 15771
A16: Impact of Special Items | B16: -219 | C16: -453 | D16: -183 | E16: -682 | F16: -359
A17: Selling, General & Admin Exp.-Normalised | B17: =B15+B16 -> 26519 | C17: =C15+C16 -> 28042 | D17: =D15+D16 -> 31054 | E17: =E15+E16 -> 33777 | F17: =F15+F16 -> 15412 | G17: =SUM(G18:G20) -> 21776 | H17: =F17+G17 -> 37188 | I17: =SUM(I18:I20) -> 41325.422 | J17: =SUM(J18:J20) -> 44771.93 | K17: =SUM(K18:K20) -> 48518.285 | L17: =SUM(L18:L20) -> 52591.485
A18: Selling, General & Admin Exp. (Excluding Amortisation Exp) | B18: =B17-B19-B20 -> 26283 | C18: =C17-C19-C20 -> 27825 | D18: =D17-D19-D20 -> 30840 | E18: =E17-E19-E20 -> 33578 | F18: =F17-F19-F20 -> 15306.377 | G18: =G6*G55 -> 21657.537 | H18: =F18+G18 -> 36963.915 | I18: =I6*I55 -> 41076.135 | J18: =J6*J55 -> 44510.771 | K18: =K6*K55 -> 48243.722 | L18: =L6*L55 -> 52301.88
A19: Corporate Depreciation and Amort | B19: 155 | C19: 127 | D19: 123 | E19: 121 | F19: =1268*F77 -> 64.273969 | G19: ='Fixed Assets Schedule'!H19 -> 85.025593 | H19: =F19+G19 -> 149.29956 | I19: ='Fixed Assets Schedule'!I19 -> 184.22803 | J19: ='Fixed Assets Schedule'!J19 -> 199.6325 | K19: ='Fixed Assets Schedule'!K19 -> 216.37493 | L19: ='Fixed Assets Schedule'!L19 -> 234.57592
A20: Amortization Exp. | B20: 81 | C20: 90 | D20: 91 | E20: 78 | F20: =1268*F78 -> 41.348612 | G20: ='Fixed Assets Schedule'!H27 -> 33.436932 | H20: =F20+G20 -> 74.785544 | I20: ='Fixed Assets Schedule'!I27 -> 65.058882 | J20: ='Fixed Assets Schedule'!J27 -> 61.527438 | K20: ='Fixed Assets Schedule'!K27 -> 58.187684 | L20: ='Fixed Assets Schedule'!L27 -> 55.029214
A22: Operating Income / EBIT-Normalised | B22: =B13-B17 -> 10602 | C22: =C13-C17 -> 10531 | D22: =D13-D17 -> 11414 | E22: =E13-E17 -> 12325 | F22: =F13-F17 -> 6661 | G22: =G13-G17 -> 9563.1158 | H22: =F22+G22 -> 16224.116 | I22: =I13-I17 -> 15658.592 | J22: =J13-J17 -> 16976.878 | K22: =K13-K17 -> 18409.165 | L22: =L13-L17 -> 19965.757
A24: Other pension and retiree medical benefits (expense)/income-Reported | B24: -44 | C24: 117 | D24: 522 | E24: 132 | F24: 121
A25: Impact of Special Items | B25: 275 | C25: 225 | D25: 22 | E25: 344 | F25: -1
A26: Other pension and retiree medical benefits (expense)/income-Normalised | B26: =B24+B25 -> 231 | C26: =C24+C25 -> 342 | D26: =D24+D25 -> 544 | E26: =E24+E25 -> 476 | F26: =F24+F25 -> 120 | G26: =G6*G57 -> 169.79226 | H26: =F26+G26 -> 289.79226 | I26: =I6*I57 -> 542.63688 | J26: =J6*J57 -> 588.01018 | K26: =K6*K57 -> 637.3244 | L26: =L6*L57 -> 690.93475
A28: Interest Expense-Reported | B28: -935 | C28: -1128 | D28: -1863 | E28: -939 | F28: -401
A29: Impact of Special Items | B29: 0 | C29: 0 | D29: 842 | E29: 0 | F29: 0
A30: Interest Expense-Normalised | B30: =B28+B29 -> -935 | C30: =C28+C29 -> -1128 | D30: =D28+D29 -> -1021 | E30: =E28+E29 -> -939 | F30: =F28+F29 -> -401 | G30: =-('Pepsico-Debt'!B47+'Pepsico-Debt'!M29) -> -626.18903 | H30: =F30+G30 -> -1027.189 | I30: =-('Pepsico-Debt'!C47+'Pepsico-Debt'!N29) -> -1089.0686 | J30: =-('Pepsico-Debt'!D47+'Pepsico-Debt'!O29) -> -1024.4525 | K30: =-('Pepsico-Debt'!E47+'Pepsico-Debt'!P29) -> -902.95718 | L30: =-('Pepsico-Debt'!F47+'Pepsico-Debt'!Q29) -> -824.0925
A32: Income before Income Taxes-Normalised | B32: =B22+B26+B30 -> 9898 | C32: =C22+C26+C30 -> 9745 | D32: =D22+D26+D30 -> 10937 | E32: =E22+E26+E30 -> 11862 | F32: =F22+F26+F30 -> 6380 | G32: =G22+G26+G30 -> 9106.719 | H32: =F32+G32 -> 15486.719 | I32: =I22+I26+I30 -> 15112.16 | J32: =J22+J26+J30 -> 16540.435 | K32: =K22+K26+K30 -> 18143.532 | L32: =L22+L26+L30 -> 19832.599
A34: Income Tax Expense-Reported | B34: 1959 | C34: 1894 | D34: 2142 | E34: 1727 | F34: 1293
A35: Impact of Special Items | B35: 120 | C35: 108 | D35: 45 | E35: 645 | F35: 88
A36: Income Tax Expense-Normalised | B36: =B34+B35 -> 2079 | C36: =C34+C35 -> 2002 | D36: =D34+D35 -> 2187 | E36: =E34+E35 -> 2372 | F36: =F34+F35 -> 1381 | G36: =G32*G59 -> 1971.2193 | H36: =F36+G36 -> 3352.2193 | I36: =I32*I59 -> 3321.0375 | J36: =J32*J59 -> 3898.0158 | K36: =K32*K59 -> 4564.4124 | L36: =L32*L59 -> 5304.8039
A38: Net Income-Normalised | B38: =B32-B36 -> 7819 | C38: =C32-C36 -> 7743 | D38: =D32-D36 -> 8750 | E38: =E32-E36 -> 9490 | F38: =F32-F36 -> 4999 | G38: =G32-G36 -> 7135.4997 | H38: =F38+G38 -> 12134.5 | I38: =I32-I36 -> 11791.123 | J38: =J32-J36 -> 12642.419 | K38: =K32-K36 -> 13579.12 | L38: =L32-L36 -> 14527.795
A40: Share of noncontrolling interests-Reported | B40: 39 | C40: 55 | D40: 61 | E40: 68 | F40: 35
A41: Impact of Special Items | B41: 5 | C41: 0 | D41: 1 | E41: 1 | F41: 1
A42: Share of noncontrolling interests-Normalised | B42: =B40+B41 -> 44 | C42: =C40+C41 -> 55 | D42: =D40+D41 -> 62 | E42: =E40+E41 -> 69 | F42: =F40+F41 -> 36 | G42: =G38*G61 -> 51.385875 | H42: =F42+G42 -> 87.385875 | I42: =I38*I61 -> 79.846636 | J42: =J38*J61 -> 85.611411 | K42: =K38*K61 -> 91.954517 | L42: =L38*L61 -> 98.37872
A44: Net Income attributable to PepsiCo-Normalised | B44: =B38-B42 -> 7775 | C44: =C38-C42 -> 7688 | D44: =D38-D42 -> 8688 | E44: =E38-E42 -> 9421 | F44: =F38-F42 -> 4963 | G44: =G38-G42 -> 7084.1139 | H44: =F44+G44 -> 12047.114 | I44: =I38-I42 -> 11711.276 | J44: =J38-J42 -> 12556.808 | K44: =K38-K42 -> 13487.165 | L44: =L38-L42 -> 14429.417
A46: Weighted Average Common Shares Outstanding-Diluted | B46: 1407 | C46: 1392 | D46: 1389 | E46: 1387 | F46: 1384 | G46: =F46 -> 1384 | H46: =G46 -> 1384 | I46: =H46 -> 1384 | J46: =I46 -> 1384 | K46: =J46 -> 1384 | L46: =K46 -> 1384
A48: Earning Per Share-Diluted | B48: =B44/B46 -> 5.5259417 | C48: =C44/C46 -> 5.5229885 | D48: =D44/D46 -> 6.2548596 | E48: =E44/E46 -> 6.7923576 | F48: =F44/F46 -> 3.5859827 | G48: =G44/G46 -> 5.1185794 | H48: =F48+G48 -> 8.704562 | I48: =I44/I46 -> 8.4619049 | J48: =J44/J46 -> 9.0728382 | K48: =K44/K46 -> 9.7450614 | L48: =L44/L46 -> 10.425879
A50: Source | B50: 10K Dec'20, Pg 46 and 60 | D50: 10K Dec'22, Pg 48, 49 and 62 | F50: 10Q June'23, Pg 4, 45 | G50: Calculation
A53: Cost as % of sales
A54: Cost of Sales (Other than Depreciation Exp) | B54: =B10/B6 -> 0.41458585 | C54: =C10/C6 -> 0.41874609 | D54: =D10/D6 -> 0.43423006 | E54: =E10/E6 -> 0.43668395 | F54: =F10/F6 -> 0.42154508 | G54: =F54 -> 0.42154508 | I54: =AVERAGE(B54:E54) -> 0.42606149 | J54: =I54 -> 0.42606149 | K54: =J54 -> 0.42606149 | L54: =K54 -> 0.42606149
A55: Selling, General & Admin Exp. (Excluding Amortisation Exp) | B55: =B18/B6 -> 0.39134319 | C55: =C18/C6 -> 0.39539874 | D55: =D18/D6 -> 0.38805144 | E55: =E18/E6 -> 0.38867025 | F55: =F18/F6 -> 0.38105899 | G55: =F55 -> 0.38105899 | I55: =AVERAGE(B55:E55) -> 0.3908659 | J55: =I55 -> 0.3908659 | K55: =J55 -> 0.3908659 | L55: =K55 -> 0.3908659
A57: Other pension and retiree medical benefits (expense)/income | B57: =B26/B6 -> 0.0034394961 | C57: =C26/C6 -> 0.0048598875 | D57: =D26/D6 -> 0.0068450059 | E57: =E26/E6 -> 0.0055097694 | F57: =F26/F6 -> 0.0029874527 | G57: =F57 -> 0.0029874527 | I57: =AVERAGE(B57:E57) -> 0.0051635397 | J57: =I57 -> 0.0051635397 | K57: =J57 -> 0.0051635397 | L57: =K57 -> 0.0051635397
O58: on an avg per annum kitne se atx inc karenge kyu 27 pe ana h
A59: Tax Rate-Normalised (%age of PBT) | B59: =B36/B32 -> 0.21004243 | C59: =C36/C32 -> 0.20543869 | D59: =D36/D32 -> 0.19996343 | E59: =E36/E32 -> 0.19996628 | F59: =F36/F32 -> 0.21645768 | G59: =F59 -> 0.21645768 | I59: =AVERAGE(B59:E59)+$O$59 -> 0.21975928 | J59: =I59+$O$59 -> 0.23566586 | K59: =J59+$O$59 -> 0.25157243 | L59: =K59+$O$59 -> 0.26747901 | M59: =AVERAGE(B59:F59) -> 0.2063737 | N59: 0.27 | O59: =(N59-M59)/4 -> 0.015906575
A61: Share of noncontrolling interests (%age of Net Income) | B61: =B42/B38 -> 0.0056273181 | C61: =C42/C38 -> 0.00710319 | D61: =D42/D38 -> 0.0070857143 | E61: =E42/E38 -> 0.0072708114 | F61: =F42/F38 -> 0.0072014403 | G61: =F61 -> 0.0072014403 | I61: =AVERAGE(B61:E61) -> 0.0067717584 | J61: =I61 -> 0.0067717584 | K61: =J61 -> 0.0067717584 | L61: =K61 -> 0.0067717584
A63: Share-based Compensation Expenses | B63: 237 | C63: 264 | D63: 301 | E63: 343 | F63: 179 | G63: =G64*G18 -> 253.27346 | I63: =I64*I18 -> 395.15426 | J63: =J64*J18 -> 428.19561 | K63: =K64*K18 -> 464.10678 | L63: =L64*L18 -> 503.14644
A64: %age of SG&A | B64: =B63/B18 -> 0.0090172355 | C64: =C63/C18 -> 0.0094878706 | D64: =D63/D18 -> 0.0097600519 | E64: =E63/E18 -> 0.010215022 | F64: =F63/F18 -> 0.011694472 | G64: =F64 -> 0.011694472 | I64: =AVERAGE(B64:E64) -> 0.0096200449 | J64: =I64 -> 0.0096200449 | K64: =J64 -> 0.0096200449 | L64: =K64 -> 0.0096200449
A67: Dividend Per Share | B67: 3.7925 | C67: 4.0225 | D67: 4.2475 | E67: 4.525 | F67: 2.415 | G67: =H67-F67 -> 3.5909078 | H67: =H68*H48 -> 6.0059078 | I67: =I68*I48 -> 5.838481 | J67: =J68*J48 -> 6.2600082 | K67: =K68*K48 -> 6.7238237 | L67: =L68*L48 -> 7.1935691
A68: Dividend Payout Ratio | B68: =B67/B48 -> 0.68630836 | C68: =C67/C48 -> 0.72831946 | D68: =D67/D48 -> 0.679072 | E68: =E67/E48 -> 0.66618989 | F68: =F67/F48 -> 0.67345557 | H68: =AVERAGE(B68:E68) -> 0.68997243 | I68: =H68 -> 0.68997243 | J68: =I68 -> 0.68997243 | K68: =J68 -> 0.68997243 | L68: =K68 -> 0.68997243
A71: Depreciation Exp | B71: =B11 -> 2196 | C71: =C11 -> 2331 | D71: =D11 -> 2496 | E71: =E11 -> 2564
A72: Corporate Depreciation and Amort | B72: =B19 -> 155 | C72: =C19 -> 127 | D72: =D19 -> 123 | E72: =E19 -> 121
A73: Less: Amortisation during the year | B73: =B20 -> 81 | C73: =C20 -> 90 | D73: =D20 -> 91 | E73: =E20 -> 78
A74: Total | B74: =B71+B72+B73 -> 2432 | C74: =C71+C72+C73 -> 2548 | D74: =D71+D72+D73 -> 2710 | E74: =E71+E72+E73 -> 2763
A76: Depreciation Exp (%) | B76: =B71/B$74 -> 0.90296053 | C76: =C71/C$74 -> 0.91483516 | D76: =D71/D$74 -> 0.92103321 | E76: =E71/E$74 -> 0.92797684 | F76: =AVERAGE(B76:E76) -> 0.91670143
A77: Corporate Depreciation and Amort (%) | B77: =B72/B$74 -> 0.063733553 | C77: =C72/C$74 -> 0.049843014 | D77: =D72/D$74 -> 0.045387454 | E77: =E72/E$74 -> 0.043792979 | F77: =AVERAGE(B77:E77) -> 0.05068925
A78: Less: Amortisation during the year (%) | B78: =B73/B$74 -> 0.033305921 | C78: =C73/C$74 -> 0.035321821 | D78: =D73/D$74 -> 0.033579336 | E78: =E73/E$74 -> 0.028230185 | F78: =AVERAGE(B78:E78) -> 0.032609316

Sheet Revenue Segment
A1: PepsiCo Inc. | C1: Valuation Date
A2: (in USD million except per Share Data) | C2: 45138
A3: Segment Information | B3: 12 months | C3: 12 months | D3: 12 months | E3: 12 months | G3: 6 months | H3: 6 months | J3: 6 months | K3: 6 months | M3: 12 months | N3: 12 months | O3: 12 months | P3: 12 months | Q3: 12 months
B4: Dec. 31, 2019 | C4: Dec. 31, 2020 | D4: Dec. 31, 2021 | E4: Dec. 31, 2022 | G4: Jun. 11, 2022 | H4: Jun. 17, 2023 | J4: Dec. 31, 2022 | K4: Dec. 31, 2023 | M4: Dec. 31, 2023 | N4: Dec. 31, 2024 | O4: Dec. 31, 2025 | P4: Dec. 31, 2026 | Q4: Dec. 31, 2027
A5: FLNA | B5: 17078 | C5: 18189 | D5: 19608 | E5: 23291 | G5: 10020 | H5: 11487 | J5: =E5-G5 -> 13271 | K5: =J5*(1+K7) -> 15261.65 | M5: =H5+K5 -> 26748.65 | N5: =M5*(1+$N7) -> 29055.721 | O5: =N5*(1+$N7) -> 31561.777 | P5: =O5*(1+$N7) -> 34283.98 | Q5: =P5*(1+$N7) -> 37240.974
A6: Growth% | C6: =C5/B5-1 -> 0.065054456 | D6: =D5/C5-1 -> 0.078014184 | E6: =E5/D5-1 -> 0.1878315 | H6: =H5/G5-1 -> 0.14640719
A7: Organic Growth % | B7: 0.045 | C7: 0.06 | D7: 0.07 | E7: 0.17 | F7: =AVERAGE(B7:E7) -> 0.08625 | H7: 0.15 | K7: =H7 -> 0.15 | N7: =F7 -> 0.08625
A9: QFNA | B9: 2482 | C9: 2742 | D9: 2751 | E9: 3160 | G9: 1388 | H9: 1461 | J9: =E9-G9 -> 1772 | K9: =J9*(1+K11) -> 1878.32 | M9: =H9+K9 -> 3339.32 | N9: =M9*(1+$N11) -> 3548.0275 | O9: =N9*(1+$N11) -> 3769.7792 | P9: =O9*(1+$N11) -> 4005.3904 | Q9: =P9*(1+$N11) -> 4255.7273
A10: Growth% | C10: =C9/B9-1 -> 0.10475423 | D10: =D9/C9-1 -> 0.0032822757 | E10: =E9/D9-1 -> 0.14867321 | H10: =H9/G9-1 -> 0.05259366
A11: Organic Growth % | B11: 0.01 | C11: 0.11 | D11: 0 | E11: 0.13 | F11: =AVERAGE(B11:E11) -> 0.0625 | H11: 0.06 | K11: =H11 -> 0.06 | N11: =F11 -> 0.0625
A13: PBNA | B13: 21730 | C13: 22559 | D13: 25276 | E13: 26213 | G13: 11473 | H13: 12553 | J13: =E13-G13 -> 14740 | K13: =J13*(1+K15) -> 16361.4 | M13: =H13+K13 -> 28914.4 | N13: =M13*(1+$N15) -> 30793.836 | O13: =N13*(1+$N15) -> 32795.435 | P13: =O13*(1+$N15) -> 34927.139 | Q13: =P13*(1+$N15) -> 37197.403
A14: Growth% | C14: =C13/B13-1 -> 0.038150023 | D14: =D13/C13-1 -> 0.12043974 | E14: =E13/D13-1 -> 0.037070739 | H14: =H13/G13-1 -> 0.094134054
A15: Organic Growth % | B15: 0.03 | C15: 0.02 | D15: 0.1 | E15: 0.11 | F15: =AVERAGE(B15:E15) -> 0.065 | H15: 0.11 | K15: =H15 -> 0.11 | N15: =F15 -> 0.065
A17: LatAm | B17: 7573 | C17: 6942 | D17: 8108 | E17: 9779 | G17: 3889 | H17: 4633 | J17: =E17-G17 -> 5890 | K17: =J17*(1+K19) -> 6714.6 | M17: =H17+K17 -> 11347.6 | N17: =M17*(1+$N19) -> 12652.574 | O17: =N17*(1+$N19) -> 14107.62 | P17: =O17*(1+$N19) -> 15729.996 | Q17: =P17*(1+$N19) -> 17538.946
A18: Growth% | C18: =C17/B17-1 -> -0.083322329 | D18: =D17/C17-1 -> 0.16796312 | E18: =E17/D17-1 -> 0.20609275 | H18: =H17/G17-1 -> 0.19130882
A19: Organic Growth % | B19: 0.07 | C19: 0.03 | D19: 0.15 | E19: 0.21 | F19: =AVERAGE(B19:E19) -> 0.115 | H19: 0.14 | K19: =H19 -> 0.14 | N19: =F19 -> 0.115
A21: Europe | B21: 11728 | C21: 11922 | D21: 13038 | E21: 12724 | G21: 4820 | H21: 5314 | J21: =E21-G21 -> 7904 | K21: =J21*(1+K23) -> 9247.68 | M21: =H21+K21 -> 14561.68 | N21: =M21*(1+$N23) -> 15744.817 | O21: =N21*(1+$N23) -> 17024.083 | P21: =O21*(1+$N23) -> 18407.29 | Q21: =P21*(1+$N23) -> 19902.882
A22: Growth% | C22: =C21/B21-1 -> 0.01654161 | D22: =D21/C21-1 -> 0.093608455 | E22: =E21/D21-1 -> -0.024083448 | H22: =H21/G21-1 -> 0.10248963
A23: Organic Growth % | B23: 0.055 | C23: 0.06 | D23: 0.09 | E23: 0.12 | F23: =AVERAGE(B23:E23) -> 0.08125 | H23: 0.17 | K23: =H23 -> 0.17 | N23: =F23 -> 0.08125
A25: AMESA | B25: 3651 | C25: 4573 | D25: 6078 | E25: 6438 | G25: 2700 | H25: 2587 | J25: =E25-G25 -> 3738 | K25: =J25*(1+K27) -> 4560.36 | M25: =H25+K25 -> 7147.36 | N25: =M25*(1+$N27) -> 7844.2276 | O25: =N25*(1+$N27) -> 8609.0398 | P25: =O25*(1+$N27) -> 9448.4212 | Q25: =P25*(1+$N27) -> 10369.642
A26: Growth% | C26: =C25/B25-1 -> 0.25253355 | D26: =D25/C25-1 -> 0.32910562 | E26: =E25/D25-1 -> 0.05923001 | H26: =H25/G25-1 -> -0.041851852
A27: Organic Growth % | B27: 0.06 | C27: 0.01 | D27: 0.12 | E27: 0.2 | F27: =AVERAGE(B27:E27) -> 0.0975 | H27: 0.22 | K27: =H27 -> 0.22 | N27: =F27 -> 0.0975
A29: APAC | B29: 2919 | C29: 3445 | D29: 4615 | E29: 4787 | G29: 2135 | H29: 2133 | J29: =E29-G29 -> 2652 | K29: =J29*(1+K31) -> 2811.12 | M29: =H29+K29 -> 4944.12 | N29: =M29*(1+$N31) -> 5450.8923 | O29: =N29*(1+$N31) -> 6009.6088 | P29: =O29*(1+$N31) -> 6625.5937 | Q29: =P29*(1+$N31) -> 7304.717
A30: Growth% | C30: =C29/B29-1 -> 0.1801987 | D30: =D29/C29-1 -> 0.33962264 | E30: =E29/D29-1 -> 0.037269772 | H30: =H29/G29-1 -> -0.00093676815
A31: Organic Growth % | B31: 0.09 | C31: 0.08 | D31: 0.13 | E31: 0.11 | F31: =AVERAGE(B31:E31) -> 0.1025 | H31: 0.06 | K31: =H31 -> 0.06 | N31: =F31 -> 0.1025
A34: Total Division | B34: =B29+B25+B21+B17+B13+B9+B5 -> 67161 | C34: =C29+C25+C21+C17+C13+C9+C5 -> 70372 | D34: =D29+D25+D21+D17+D13+D9+D5 -> 79474 | E34: =E29+E25+E21+E17+E13+E9+E5 -> 86392 | G34: =G29+G25+G21+G17+G13+G9+G5 -> 36425 | H34: =H29+H25+H21+H17+H13+H9+H5 -> 40168 | J34: =J29+J25+J21+J17+J13+J9+J5 -> 49967 | K34: =K29+K25+K21+K17+K13+K9+K5 -> 56835.13 | M34: =M29+M25+M21+M17+M13+M9+M5 -> 97003.13 | N34: =N29+N25+N21+N17+N13+N9+N5 -> 105090.09 | O34: =O29+O25+O21+O17+O13+O9+O5 -> 113877.34 | P34: =P29+P25+P21+P17+P13+P9+P5 -> 123427.81 | Q34: =Q29+Q25+Q21+Q17+Q13+Q9+Q5 -> 133810.29
A37: Source | B37: 10K Dec'19, Pg 51 & 84 | C37: 10K Dec'22, Pg 41 and 70 | G37: 10Q June'23, Pg 11 and 35 | J37: Calculation | M37: Calculation

Sheet Sheet1
